Workbook

Sheet Instrucciones
A1: AMBERES INTELLIGENCE – MODELO CONSOLIDADO
A3: QUÉ ES ESTE ARCHIVO
A4: Un solo archivo con todas las pestañas que el software reconoce por su nombre y contenido: P&L (6 hojas), Evaluación de proyectos (Panel, Supuestos, Ingresos, Costos, Estado de Resultados, Financiamiento, Flujo de Caja, Resumen, Escenarios, Valoración, Ratios), Balance y M&A.
A6: CÓMO USARLO
A7: 1. Pegue sus datos en las hojas de P&L (una hoja por empresa y escenario: Real, Budget, Forecast) y/o en Supuestos (celdas amarillas).
A8: 2. Suba el archivo a Amberes Intelligence. Cada pestaña se identifica sola; las vacías se marcan como opcionales.
A9: 3. Si solo sube un P&L, el software construye por sí mismo el flujo de caja operacional y financiero, el balance (que cuadra) y la valoración M&A, rotulando como "estimado" todo lo que no estaba cargado.
A10: 4. Balance, Estado de Flujo de Caja y M&A son opcionales: complételos solo si desea reemplazar las estimaciones. Si sube solo un Balance o solo un Flujo de Caja, el software completa los otros informes de forma aproximada (no todas las cuentas se pueden traspasar de un informe a otro; lo estimado se rotula).
A12: CÓDIGO DE COLORES
A13: Celdas amarillas con texto azul = datos que usted ingresa. Fondo blanco = fórmulas, no editar.
A15: IMPORTANTE
A16: Las hojas de ejemplo incluidas son datos ilustrativos y no están relacionadas entre sí (el P&L es de una empresa de servicios; la evaluación es un proyecto distinto). Reemplácelos con sus cifras.
... A18: Los resultados son referenciales y deben ser validados por un profesional antes de decisiones de inversión, financiamiento o transacciones.

Sheet Panel de Control
A1: MODELO DE EVALUACIÓN DE PROYECTOS
V2: Inversión | W2: USD
A3: INFORMACIÓN DEL PROYECTO | V3: Desinversión | W3: CLP
V4: Fusión | W4: EUR
A5: Nombre del Proyecto: | B5: Proyecto Ejemplo | V5: Adquisición | W5: ARS | X5: Peso Argentino
A6: Tipo de Operación: | B6: Inversión | W6: MXN | X6: Peso Mexicano
A7: Fecha de Evaluación: | B7: 46023 | W7: COP | X7: Peso Colombiano
A8: Moneda: | B8: CLP | W8: PEN | X8: Sol Peruano
A9: Unidad (miles/millones): | B9: miles | W9: UYU | X9: Peso Uruguayo
W10: CRC | X10: Colón Costarricense
A11: PARÁMETROS DE ANÁLISIS
A13: Horizonte de Evaluación (meses): | B13: 60
A14: Tasa de Descuento (WACC): | B14: 0.12
A15: Tasa Impositiva: | B15: 0.27
A17: INDICADORES PRINCIPALES
A19: VAN (Valor Actual Neto): | B19: =Resumen!B5 -> -24259406
A20: TIR (Tasa Interna de Retorno): | B20: =Resumen!B7 -> -0.025297748
A21: Período de Recuperación (meses): | B21: =Resumen!B8 -> -
A22: ROI (Return on Investment): | B22: =Resumen!B9 -> -0.097106988

Sheet Supuestos
A1: SUPUESTOS PRINCIPALES
A3: INVERSIÓN INICIAL
A4: Inversión en Activos Fijos: | B4: 50000000
A5: Capital de Trabajo Inicial: | B5: 7000000
A6: Gastos Pre-operativos: | B6: 500000
A8: INGRESOS
A9: Ingresos Mensuales Año 1: | B9: 10700000
A10: Crecimiento Anual Ingresos: | B10: 0.07
A12: COSTOS VARIABLES
A13: % Costos Variables sobre Ventas: | B13: 0.37
A15: COSTOS FIJOS MENSUALES
A16: Salarios y Cargas Sociales: | B16: 3800000
A17: Alquileres: | B17: 1900000
A18: Servicios (luz, agua, internet): | B18: 300000
A19: Marketing y Publicidad: | B19: 500000
A20: Otros Gastos Fijos: | B20: 400000
A22: DEPRECIACIÓN
A23: Vida Útil Activos (años): | B23: 10
A24: Método Depreciación: | B24: Lineal
A26: FINANCIAMIENTO
A27: Monto del Préstamo: | B27: 4000000
A28: Tasa de Interés Anual: | B28: 0.07
A29: Plazo del Préstamo (meses): | B29: 60
A31: VALOR RESIDUAL
A32: % Valor Residual de Activos Fijos: | B32: 0.2

Sheet Ingresos
A1: PROYECCIÓN DE INGRESOS
A3: Concepto | B3: Mes 1 | C3: Mes 2 | D3: Mes 3 | E3: Mes 4 | F3: Mes 5 | G3: Mes 6 | H3: Mes 7 | I3: Mes 8 | J3: Mes 9 | K3: Mes 10 | L3: Mes 11 | M3: Mes 12 | N3: Mes 13 | O3: Mes 14 | P3: Mes 15 | Q3: Mes 16 | R3: Mes 17 | S3: Mes 18 | T3: Mes 19 | U3: Mes 20 | V3: Mes 21 | W3: Mes 22 | X3: Mes 23 | Y3: Mes 24 | Z3: Mes 25 | AA3: Mes 26 | AB3: Mes 27 | AC3: Mes 28 | AD3: Mes 29 | AE3: Mes 30 | AF3: Mes 31 | AG3: Mes 32 | AH3: Mes 33 | AI3: Mes 34 | AJ3: Mes 35 | AK3: Mes 36 | AL3: Mes 37 | AM3: Mes 38 | AN3: Mes 39 | AO3: Mes 40 | AP3: Mes 41 | AQ3: Mes 42 | AR3: Mes 43 | AS3: Mes 44 | AT3: Mes 45 | AU3: Mes 46 | AV3: Mes 47 | AW3: Mes 48 | AX3: Mes 49 | AY3: Mes 50 | AZ3: Mes 51 | BA3: Mes 52 | BB3: Mes 53 | BC3: Mes 54 | BD3: Mes 55 | BE3: Mes 56 | BF3: Mes 57 | BG3: Mes 58 | BH3: Mes 59 | BI3: Mes 60 | BJ3: Mes 61 | BK3: Mes 62 | BL3: Mes 63 | BM3: Mes 64 | BN3: Mes 65 | BO3: Mes 66 | BP3: Mes 67 | BQ3: Mes 68 | BR3: Mes 69 | BS3: Mes 70 | BT3: Mes 71 | BU3: Mes 72 | BV3: Mes 73 | BW3: Mes 74 | BX3: Mes 75 | BY3: Mes 76 | BZ3: Mes 77 | CA3: Mes 78 | CB3: Mes 79 | CC3: Mes 80 | CD3: Mes 81 | CE3: Mes 82 | CF3: Mes 83 | CG3: Mes 84 | CH3: Mes 85 | CI3: Mes 86 | CJ3: Mes 87 | CK3: Mes 88 | CL3: Mes 89 | CM3: Mes 90 | CN3: Mes 91 | CO3: Mes 92 | CP3: Mes 93 | CQ3: Mes 94 | CR3: Mes 95 | CS3: Mes 96 | CT3: Mes 97 | CU3: Mes 98 | CV3: Mes 99 | CW3: Mes 100 | CX3: Mes 101 | CY3: Mes 102 | CZ3: Mes 103 | DA3: Mes 104 | DB3: Mes 105 | DC3: Mes 106 | DD3: Mes 107 | DE3: Mes 108 | DF3: Mes 109 | DG3: Mes 110 | DH3: Mes 111 | DI3: Mes 112 | DJ3: Mes 113 | DK3: Mes 114 | DL3: Mes 115 | DM3: Mes 116 | DN3: Mes 117 | DO3: Mes 118 | DP3: Mes 119 | DQ3: Mes 120 | DR3: Mes 121 | DS3: Mes 122 | DT3: Mes 123 | DU3: Mes 124 | DV3: Mes 125 | DW3: Mes 126 | DX3: Mes 127 | DY3: Mes 128 | DZ3: Mes 129 | EA3: Mes 130 | EB3: Mes 131 | EC3: Mes 132 | ED3: Mes 133 | EE3: Mes 134 | EF3: Mes 135 | EG3: Mes 136 | EH3: Mes 137 | EI3: Mes 138 | EJ3: Mes 139 | EK3: Mes 140 | EL3: Mes 141 | EM3: Mes 142 | EN3: Mes 143 | EO3: Mes 144 | EP3: Mes 145 | EQ3: Mes 146 | ER3: Mes 147 | ES3: Mes 148 | ET3: Mes 149 | EU3: Mes 150 | EV3: Mes 151 | EW3: Mes 152 | EX3: Mes 153 | EY3: Mes 154 | EZ3: Mes 155 | FA3: Mes 156 | FB3: Mes 157 | FC3: Mes 158 | FD3: Mes 159 | FE3: Mes 160 | FF3: Mes 161 | FG3: Mes 162 | FH3: Mes 163 | FI3: Mes 164 | FJ3: Mes 165 | FK3: Mes 166 | FL3: Mes 167 | FM3: Mes 168 | FN3: Mes 169 | FO3: Mes 170 | FP3: Mes 171 | FQ3: Mes 172 | FR3: Mes 173 | FS3: Mes 174 | FT3: Mes 175 | FU3: Mes 176 | FV3: Mes 177 | FW3: Mes 178 | FX3: Mes 179 | FY3: Mes 180 | FZ3: Mes 181 | GA3: Mes 182 | GB3: Mes 183 | GC3: Mes 184 | GD3: Mes 185 | GE3: Mes 186 | GF3: Mes 187 | GG3: Mes 188 | GH3: Mes 189 | GI3: Mes 190 | GJ3: Mes 191 | GK3: Mes 192 | GL3: Mes 193 | GM3: Mes 194 | GN3: Mes 195 | GO3: Mes 196 | GP3: Mes 197 | GQ3: Mes 198 | GR3: Mes 199 | GS3: Mes 200 | GT3: Mes 201 | GU3: Mes 202 | GV3: Mes 203 | GW3: Mes 204 | GX3: Mes 205 | GY3: Mes 206 | GZ3: Mes 207 | HA3: Mes 208 | HB3: Mes 209 | HC3: Mes 210 | HD3: Mes 211 | HE3: Mes 212 | HF3: Mes 213 | HG3: Mes 214 | HH3: Mes 215 | HI3: Mes 216 | HJ3: Mes 217 | HK3: Mes 218 | HL3: Mes 219 | HM3: Mes 220 | HN3: Mes 221 | HO3: Mes 222 | HP3: Mes 223 | HQ3: Mes 224 | HR3: Mes 225 | HS3: Mes 226 | HT3: Mes 227 | HU3: Mes 228 | HV3: Mes 229 | HW3: Mes 230 | HX3: Mes 231 | HY3: Mes 232 | HZ3: Mes 233 | IA3: Mes 234 | IB3: Mes 235 | IC3: Mes 236 | ID3: Mes 237 | IE3: Mes 238 | IF3: Mes 239 | IG3: Mes 240 | IH3: Mes 241 | II3: Mes 242 | IJ3: Mes 243 | IK3: Mes 244 | IL3: Mes 245 | IM3: Mes 246 | IN3: Mes 247 | IO3: Mes 248 | IP3: Mes 249 | IQ3: Mes 250 | IR3: Mes 251 | IS3: Mes 252 | IT3: Mes 253 | IU3: Mes 254 | IV3: Mes 255 | IW3: Mes 256 | IX3: Mes 257 | IY3: Mes 258 | IZ3: Mes 259 | JA3: Mes 260 | JB3: Mes 261 | JC3: Mes 262 | JD3: Mes 263 | JE3: Mes 264 | JF3: Mes 265 | JG3: Mes 266 | JH3: Mes 267 | JI3: Mes 268 | JJ3: Mes 269 | JK3: Mes 270 | JL3: Mes 271 | JM3: Mes 272 | JN3: Mes 273 | JO3: Mes 274 | JP3: Mes 275 | JQ3: Mes 276 | JR3: Mes 277 | JS3: Mes 278 | JT3: Mes 279 | JU3: Mes 280 | JV3: Mes 281 | JW3: Mes 282 | JX3: Mes 283 | JY3: Mes 284 | JZ3: Mes 285 | KA3: Mes 286 | KB3: Mes 287 | KC3: Mes 288 | KD3: Mes 289 | KE3: Mes 290 | KF3: Mes 291 | KG3: Mes 292 | KH3: Mes 293 | KI3: Mes 294 | KJ3: Mes 295 | KK3: Mes 296 | KL3: Mes 297 | KM3: Mes 298 | KN3: Mes 299 | KO3: Mes 300
A4: Ingresos por Ventas | B4: =Supuestos!$B$9*POWER(1+Supuestos!$B$10,0) -> 10700000 | C4: =Supuestos!$B$9*POWER(1+Supuestos!$B$10,0) -> 10700000 | D4: =Supuestos!$B$9*POWER(1+Supuestos!$B$10,0) -> 10700000 | E4: =Supuestos!$B$9*POWER(1+Supuestos!$B$10,0) -> 10700000 | F4: =Supuestos!$B$9*POWER(1+Supuestos!$B$10,0) -> 10700000 | G4: =Supuestos!$B$9*POWER(1+Supuestos!$B$10,0) -> 10700000 | H4: =Supuestos!$B$9*POWER(1+Supuestos!$B$10,0) -> 10700000 | I4: =Supuestos!$B$9*POWER(1+Supuestos!$B$10,0) -> 10700000 | ... M4: =Supuestos!$B$9*POWER(1+Supuestos!$B$10,0) -> 10700000 | N4: =Supuestos!$B$9*POWER(1+Supuestos!$B$10,1) -> 11449000 | O4: =Supuestos!$B$9*POWER(1+Supuestos!$B$10,1) -> 11449000 | P4: =Supuestos!$B$9*POWER(1+Supuestos!$B$10,1) -> 11449000 | Q4: =Supuestos!$B$9*POWER(1+Supuestos!$B$10,1) -> 11449000 | R4: =Supuestos!$B$9*POWER(1+Supuestos!$B$10,1) -> 11449000 | S4: =Supuestos!$B$9*POWER(1+Supuestos!$B$10,1) -> 11449000 | T4: =Supuestos!$B$9*POWER(1+Supuestos!$B$10,1) -> 11449000 | U4: =Supuestos!$B$9*POWER(1+Supuestos!$B$10,1) -> 11449000 | ... Y4: =Supuestos!$B$9*POWER(1+Supuestos!$B$10,1) -> 11449000 | Z4: =Supuestos!$B$9*POWER(1+Supuestos!$B$10,2) -> 12250430 | AA4: =Supuestos!$B$9*POWER(1+Supuestos!$B$10,2) -> 12250430 | AB4: =Supuestos!$B$9*POWER(1+Supuestos!$B$10,2) -> 12250430 | AC4: =Supuestos!$B$9*POWER(1+Supuestos!$B$10,2) -> 12250430 | AD4: =Supuestos!$B$9*POWER(1+Supuestos!$B$10,2) -> 12250430 | AE4: =Supuestos!$B$9*POWER(1+Supuestos!$B$10,2) -> 12250430 | AF4: =Supuestos!$B$9*POWER(1+Supuestos!$B$10,2) -> 12250430 | AG4: =Supuestos!$B$9*POWER(1+Supuestos!$B$10,2) -> 12250430 | ... AK4: =Supuestos!$B$9*POWER(1+Supuestos!$B$10,2) -> 12250430 | AL4: =Supuestos!$B$9*POWER(1+Supuestos!$B$10,3) -> 13107960 | AM4: =Supuestos!$B$9*POWER(1+Supuestos!$B$10,3) -> 13107960 | AN4: =Supuestos!$B$9*POWER(1+Supuestos!$B$10,3) -> 13107960 | AO4: =Supuestos!$B$9*POWER(1+Supuestos!$B$10,3) -> 13107960 | AP4: =Supuestos!$B$9*POWER(1+Supuestos!$B$10,3) -> 13107960 | AQ4: =Supuestos!$B$9*POWER(1+Supuestos!$B$10,3) -> 13107960 | AR4: =Supuestos!$B$9*POWER(1+Supuestos!$B$10,3) -> 13107960 | AS4: =Supuestos!$B$9*POWER(1+Supuestos!$B$10,3) -> 13107960 | ... AW4: =Supuestos!$B$9*POWER(1+Supuestos!$B$10,3) -> 13107960 | AX4: =Supuestos!$B$9*POWER(1+Supuestos!$B$10,4) -> 14025517 | AY4: =Supuestos!$B$9*POWER(1+Supuestos!$B$10,4) -> 14025517 | AZ4: =Supuestos!$B$9*POWER(1+Supuestos!$B$10,4) -> 14025517 | BA4: =Supuestos!$B$9*POWER(1+Supuestos!$B$10,4) -> 14025517 | BB4: =Supuestos!$B$9*POWER(1+Supuestos!$B$10,4) -> 14025517 | BC4: =Supuestos!$B$9*POWER(1+Supuestos!$B$10,4) -> 14025517 | BD4: =Supuestos!$B$9*POWER(1+Supuestos!$B$10,4) -> 14025517 | BE4: =Supuestos!$B$9*POWER(1+Supuestos!$B$10,4) -> 14025517 | ... BI4: =Supuestos!$B$9*POWER(1+Supuestos!$B$10,4) -> 14025517 | BJ4: =Supuestos!$B$9*POWER(1+Supuestos!$B$10,5) -> 15007304 | BK4: =Supuestos!$B$9*POWER(1+Supuestos!$B$10,5) -> 15007304 | BL4: =Supuestos!$B$9*POWER(1+Supuestos!$B$10,5) -> 15007304 | BM4: =Supuestos!$B$9*POWER(1+Supuestos!$B$10,5) -> 15007304 | BN4: =Supuestos!$B$9*POWER(1+Supuestos!$B$10,5) -> 15007304 | BO4: =Supuestos!$B$9*POWER(1+Supuestos!$B$10,5) -> 15007304 | BP4: =Supuestos!$B$9*POWER(1+Supuestos!$B$10,5) -> 15007304 | BQ4: =Supuestos!$B$9*POWER(1+Supuestos!$B$10,5) -> 15007304 | ... BU4: =Supuestos!$B$9*POWER(1+Supuestos!$B$10,5) -> 15007304 | BV4: =Supuestos!$B$9*POWER(1+Supuestos!$B$10,6) -> 16057815 | BW4: =Supuestos!$B$9*POWER(1+Supuestos!$B$10,6) -> 16057815 | BX4: =Supuestos!$B$9*POWER(1+Supuestos!$B$10,6) -> 16057815 | BY4: =Supuestos!$B$9*POWER(1+Supuestos!$B$10,6) -> 16057815 | BZ4: =Supuestos!$B$9*POWER(1+Supuestos!$B$10,6) -> 16057815 | CA4: =Supuestos!$B$9*POWER(1+Supuestos!$B$10,6) -> 16057815 | CB4: =Supuestos!$B$9*POWER(1+Supuestos!$B$10,6) -> 16057815 | CC4: =Supuestos!$B$9*POWER(1+Supuestos!$B$10,6) -> 16057815 | ... CG4: =Supuestos!$B$9*POWER(1+Supuestos!$B$10,6) -> 16057815 | CH4: =Supuestos!$B$9*POWER(1+Supuestos!$B$10,7) -> 17181862 | CI4: =Supuestos!$B$9*POWER(1+Supuestos!$B$10,7) -> 17181862 | CJ4: =Supuestos!$B$9*POWER(1+Supuestos!$B$10,7) -> 17181862 | CK4: =Supuestos!$B$9*POWER(1+Supuestos!$B$10,7) -> 17181862 | CL4: =Supuestos!$B$9*POWER(1+Supuestos!$B$10,7) -> 17181862 | CM4: =Supuestos!$B$9*POWER(1+Supuestos!$B$10,7) -> 17181862 | CN4: =Supuestos!$B$9*POWER(1+Supuestos!$B$10,7) -> 17181862 | CO4: =Supuestos!$B$9*POWER(1+Supuestos!$B$10,7) -> 17181862 | ... CS4: =Supuestos!$B$9*POWER(1+Supuestos!$B$10,7) -> 17181862 | CT4: =Supuestos!$B$9*POWER(1+Supuestos!$B$10,8) -> 18384592 | CU4: =Supuestos!$B$9*POWER(1+Supuestos!$B$10,8) -> 18384592 | CV4: =Supuestos!$B$9*POWER(1+Supuestos!$B$10,8) -> 18384592 | CW4: =Supuestos!$B$9*POWER(1+Supuestos!$B$10,8) -> 18384592 | CX4: =Supuestos!$B$9*POWER(1+Supuestos!$B$10,8) -> 18384592 | CY4: =Supuestos!$B$9*POWER(1+Supuestos!$B$10,8) -> 18384592 | CZ4: =Supuestos!$B$9*POWER(1+Supuestos!$B$10,8) -> 18384592 | DA4: =Supuestos!$B$9*POWER(1+Supuestos!$B$10,8) -> 18384592 | ... DE4: =Supuestos!$B$9*POWER(1+Supuestos!$B$10,8) -> 18384592 | DF4: =Supuestos!$B$9*POWER(1+Supuestos!$B$10,9) -> 19671514 | DG4: =Supuestos!$B$9*POWER(1+Supuestos!$B$10,9) -> 19671514 | DH4: =Supuestos!$B$9*POWER(1+Supuestos!$B$10,9) -> 19671514 | DI4: =Supuestos!$B$9*POWER(1+Supuestos!$B$10,9) -> 19671514 | DJ4: =Supuestos!$B$9*POWER(1+Supuestos!$B$10,9) -> 19671514 | DK4: =Supuestos!$B$9*POWER(1+Supuestos!$B$10,9) -> 19671514 | DL4: =Supuestos!$B$9*POWER(1+Supuestos!$B$10,9) -> 19671514 | DM4: =Supuestos!$B$9*POWER(1+Supuestos!$B$10,9) -> 19671514 | ... DQ4: =Supuestos!$B$9*POWER(1+Supuestos!$B$10,9) -> 19671514 | DR4: =Supuestos!$B$9*POWER(1+Supuestos!$B$10,10) -> 21048520 | DS4: =Supuestos!$B$9*POWER(1+Supuestos!$B$10,10) -> 21048520 | DT4: =Supuestos!$B$9*POWER(1+Supuestos!$B$10,10) -> 21048520 | DU4: =Supuestos!$B$9*POWER(1+Supuestos!$B$10,10) -> 21048520 | DV4: =Supuestos!$B$9*POWER(1+Supuestos!$B$10,10) -> 21048520 | DW4: =Supuestos!$B$9*POWER(1+Supuestos!$B$10,10) -> 21048520 | DX4: =Supuestos!$B$9*POWER(1+Supuestos!$B$10,10) -> 21048520 | DY4: =Supuestos!$B$9*POWER(1+Supuestos!$B$10,10) -> 21048520 | ... EC4: =Supuestos!$B$9*POWER(1+Supuestos!$B$10,10) -> 21048520 | ED4: =Supuestos!$B$9*POWER(1+Supuestos!$B$10,11) -> 22521916 | EE4: =Supuestos!$B$9*POWER(1+Supuestos!$B$10,11) -> 22521916 | EF4: =Supuestos!$B$9*POWER(1+Supuestos!$B$10,11) -> 22521916 | EG4: =Supuestos!$B$9*POWER(1+Supuestos!$B$10,11) -> 22521916 | EH4: =Supuestos!$B$9*POWER(1+Supuestos!$B$10,11) -> 22521916 | EI4: =Supuestos!$B$9*POWER(1+Supuestos!$B$10,11) -> 22521916 | EJ4: =Supuestos!$B$9*POWER(1+Supuestos!$B$10,11) -> 22521916 | EK4: =Supuestos!$B$9*POWER(1+Supuestos!$B$10,11) -> 22521916 | ... EO4: =Supuestos!$B$9*POWER(1+Supuestos!$B$10,11) -> 22521916 | EP4: =Supuestos!$B$9*POWER(1+Supuestos!$B$10,12) -> 24098450 | EQ4: =Supuestos!$B$9*POWER(1+Supuestos!$B$10,12) -> 24098450 | ER4: =Supuestos!$B$9*POWER(1+Supuestos!$B$10,12) -> 24098450 | ES4: =Supuestos!$B$9*POWER(1+Supuestos!$B$10,12) -> 24098450 | ET4: =Supuestos!$B$9*POWER(1+Supuestos!$B$10,12) -> 24098450 | EU4: =Supuestos!$B$9*POWER(1+Supuestos!$B$10,12) -> 24098450 | EV4: =Supuestos!$B$9*POWER(1+Supuestos!$B$10,12) -> 24098450 | EW4: =Supuestos!$B$9*POWER(1+Supuestos!$B$10,12) -> 24098450 | ... FA4: =Supuestos!$B$9*POWER(1+Supuestos!$B$10,12) -> 24098450 | FB4: =Supuestos!$B$9*POWER(1+Supuestos!$B$10,13) -> 25785342 | FC4: =Supuestos!$B$9*POWER(1+Supuestos!$B$10,13) -> 25785342 | FD4: =Supuestos!$B$9*POWER(1+Supuestos!$B$10,13) -> 25785342 | FE4: =Supuestos!$B$9*POWER(1+Supuestos!$B$10,13) -> 25785342 | FF4: =Supuestos!$B$9*POWER(1+Supuestos!$B$10,13) -> 25785342 | FG4: =Supuestos!$B$9*POWER(1+Supuestos!$B$10,13) -> 25785342 | FH4: =Supuestos!$B$9*POWER(1+Supuestos!$B$10,13) -> 25785342 | FI4: =Supuestos!$B$9*POWER(1+Supuestos!$B$10,13) -> 25785342 | ... FM4: =Supuestos!$B$9*POWER(1+Supuestos!$B$10,13) -> 25785342 | FN4: =Supuestos!$B$9*POWER(1+Supuestos!$B$10,14) -> 27590315 | FO4: =Supuestos!$B$9*POWER(1+Supuestos!$B$10,14) -> 27590315 | FP4: =Supuestos!$B$9*POWER(1+Supuestos!$B$10,14) -> 27590315 | FQ4: =Supuestos!$B$9*POWER(1+Supuestos!$B$10,14) -> 27590315 | FR4: =Supuestos!$B$9*POWER(1+Supuestos!$B$10,14) -> 27590315 | FS4: =Supuestos!$B$9*POWER(1+Supuestos!$B$10,14) -> 27590315 | FT4: =Supuestos!$B$9*POWER(1+Supuestos!$B$10,14) -> 27590315 | FU4: =Supuestos!$B$9*POWER(1+Supuestos!$B$10,14) -> 27590315 | ... FY4: =Supuestos!$B$9*POWER(1+Supuestos!$B$10,14) -> 27590315 | FZ4: =Supuestos!$B$9*POWER(1+Supuestos!$B$10,15) -> 29521637 | GA4: =Supuestos!$B$9*POWER(1+Supuestos!$B$10,15) -> 29521637 | GB4: =Supuestos!$B$9*POWER(1+Supuestos!$B$10,15) -> 29521637 | GC4: =Supuestos!$B$9*POWER(1+Supuestos!$B$10,15) -> 29521637 | GD4: =Supuestos!$B$9*POWER(1+Supuestos!$B$10,15) -> 29521637 | GE4: =Supuestos!$B$9*POWER(1+Supuestos!$B$10,15) -> 29521637 | GF4: =Supuestos!$B$9*POWER(1+Supuestos!$B$10,15) -> 29521637 | GG4: =Supuestos!$B$9*POWER(1+Supuestos!$B$10,15) -> 29521637 | ... GK4: =Supuestos!$B$9*POWER(1+Supuestos!$B$10,15) -> 29521637 | GL4: =Supuestos!$B$9*POWER(1+Supuestos!$B$10,16) -> 31588152 | GM4: =Supuestos!$B$9*POWER(1+Supuestos!$B$10,16) -> 31588152 | GN4: =Supuestos!$B$9*POWER(1+Supuestos!$B$10,16) -> 31588152 | GO4: =Supuestos!$B$9*POWER(1+Supuestos!$B$10,16) -> 31588152 | GP4: =Supuestos!$B$9*POWER(1+Supuestos!$B$10,16) -> 31588152 | GQ4: =Supuestos!$B$9*POWER(1+Supuestos!$B$10,16) -> 31588152 | GR4: =Supuestos!$B$9*POWER(1+Supuestos!$B$10,16) -> 31588152 | GS4: =Supuestos!$B$9*POWER(1+Supuestos!$B$10,16) -> 31588152 | ... GW4: =Supuestos!$B$9*POWER(1+Supuestos!$B$10,16) -> 31588152 | GX4: =Supuestos!$B$9*POWER(1+Supuestos!$B$10,17) -> 33799323 | GY4: =Supuestos!$B$9*POWER(1+Supuestos!$B$10,17) -> 33799323 | GZ4: =Supuestos!$B$9*POWER(1+Supuestos!$B$10,17) -> 33799323 | HA4: =Supuestos!$B$9*POWER(1+Supuestos!$B$10,17) -> 33799323 | HB4: =Supuestos!$B$9*POWER(1+Supuestos!$B$10,17) -> 33799323 | HC4: =Supuestos!$B$9*POWER(1+Supuestos!$B$10,17) -> 33799323 | HD4: =Supuestos!$B$9*POWER(1+Supuestos!$B$10,17) -> 33799323 | HE4: =Supuestos!$B$9*POWER(1+Supuestos!$B$10,17) -> 33799323 | ... HI4: =Supuestos!$B$9*POWER(1+Supuestos!$B$10,17) -> 33799323 | HJ4: =Supuestos!$B$9*POWER(1+Supuestos!$B$10,18) -> 36165275 | HK4: =Supuestos!$B$9*POWER(1+Supuestos!$B$10,18) -> 36165275 | HL4: =Supuestos!$B$9*POWER(1+Supuestos!$B$10,18) -> 36165275 | HM4: =Supuestos!$B$9*POWER(1+Supuestos!$B$10,18) -> 36165275 | HN4: =Supuestos!$B$9*POWER(1+Supuestos!$B$10,18) -> 36165275 | HO4: =Supuestos!$B$9*POWER(1+Supuestos!$B$10,18) -> 36165275 | HP4: =Supuestos!$B$9*POWER(1+Supuestos!$B$10,18) -> 36165275 | HQ4: =Supuestos!$B$9*POWER(1+Supuestos!$B$10,18) -> 36165275 | ... HU4: =Supuestos!$B$9*POWER(1+Supuestos!$B$10,18) -> 36165275 | HV4: =Supuestos!$B$9*POWER(1+Supuestos!$B$10,19) -> 38696845 | HW4: =Supuestos!$B$9*POWER(1+Supuestos!$B$10,19) -> 38696845 | HX4: =Supuestos!$B$9*POWER(1+Supuestos!$B$10,19) -> 38696845 | HY4: =Supuestos!$B$9*POWER(1+Supuestos!$B$10,19) -> 38696845 | HZ4: =Supuestos!$B$9*POWER(1+Supuestos!$B$10,19) -> 38696845 | IA4: =Supuestos!$B$9*POWER(1+Supuestos!$B$10,19) -> 38696845 | IB4: =Supuestos!$B$9*POWER(1+Supuestos!$B$10,19) -> 38696845 | IC4: =Supuestos!$B$9*POWER(1+Supuestos!$B$10,19) -> 38696845 | ... IG4: =Supuestos!$B$9*POWER(1+Supuestos!$B$10,19) -> 38696845 | IH4: =Supuestos!$B$9*POWER(1+Supuestos!$B$10,20) -> 41405624 | II4: =Supuestos!$B$9*POWER(1+Supuestos!$B$10,20) -> 41405624 | IJ4: =Supuestos!$B$9*POWER(1+Supuestos!$B$10,20) -> 41405624 | IK4: =Supuestos!$B$9*POWER(1+Supuestos!$B$10,20) -> 41405624 | IL4: =Supuestos!$B$9*POWER(1+Supuestos!$B$10,20) -> 41405624 | IM4: =Supuestos!$B$9*POWER(1+Supuestos!$B$10,20) -> 41405624 | IN4: =Supuestos!$B$9*POWER(1+Supuestos!$B$10,20) -> 41405624 | IO4: =Supuestos!$B$9*POWER(1+Supuestos!$B$10,20) -> 41405624 | ... IS4: =Supuestos!$B$9*POWER(1+Supuestos!$B$10,20) -> 41405624 | IT4: =Supuestos!$B$9*POWER(1+Supuestos!$B$10,21) -> 44304017 | IU4: =Supuestos!$B$9*POWER(1+Supuestos!$B$10,21) -> 44304017 | IV4: =Supuestos!$B$9*POWER(1+Supuestos!$B$10,21) -> 44304017 | IW4: =Supuestos!$B$9*POWER(1+Supuestos!$B$10,21) -> 44304017 | IX4: =Supuestos!$B$9*POWER(1+Supuestos!$B$10,21) -> 44304017 | IY4: =Supuestos!$B$9*POWER(1+Supuestos!$B$10,21) -> 44304017 | IZ4: =Supuestos!$B$9*POWER(1+Supuestos!$B$10,21) -> 44304017 | JA4: =Supuestos!$B$9*POWER(1+Supuestos!$B$10,21) -> 44304017 | ... JE4: =Supuestos!$B$9*POWER(1+Supuestos!$B$10,21) -> 44304017 | JF4: =Supuestos!$B$9*POWER(1+Supuestos!$B$10,22) -> 47405299 | JG4: =Supuestos!$B$9*POWER(1+Supuestos!$B$10,22) -> 47405299 | JH4: =Supuestos!$B$9*POWER(1+Supuestos!$B$10,22) -> 47405299 | JI4: =Supuestos!$B$9*POWER(1+Supuestos!$B$10,22) -> 47405299 | JJ4: =Supuestos!$B$9*POWER(1+Supuestos!$B$10,22) -> 47405299 | JK4: =Supuestos!$B$9*POWER(1+Supuestos!$B$10,22) -> 47405299 | JL4: =Supuestos!$B$9*POWER(1+Supuestos!$B$10,22) -> 47405299 | JM4: =Supuestos!$B$9*POWER(1+Supuestos!$B$10,22) -> 47405299 | ... JQ4: =Supuestos!$B$9*POWER(1+Supuestos!$B$10,22) -> 47405299 | JR4: =Supuestos!$B$9*POWER(1+Supuestos!$B$10,23) -> 50723670 | JS4: =Supuestos!$B$9*POWER(1+Supuestos!$B$10,23) -> 50723670 | JT4: =Supuestos!$B$9*POWER(1+Supuestos!$B$10,23) -> 50723670 | JU4: =Supuestos!$B$9*POWER(1+Supuestos!$B$10,23) -> 50723670 | JV4: =Supuestos!$B$9*POWER(1+Supuestos!$B$10,23) -> 50723670 | JW4: =Supuestos!$B$9*POWER(1+Supuestos!$B$10,23) -> 50723670 | JX4: =Supuestos!$B$9*POWER(1+Supuestos!$B$10,23) -> 50723670 | JY4: =Supuestos!$B$9*POWER(1+Supuestos!$B$10,23) -> 50723670 | ... KC4: =Supuestos!$B$9*POWER(1+Supuestos!$B$10,23) -> 50723670 | KD4: =Supuestos!$B$9*POWER(1+Supuestos!$B$10,24) -> 54274326 | KE4: =Supuestos!$B$9*POWER(1+Supuestos!$B$10,24) -> 54274326 | KF4: =Supuestos!$B$9*POWER(1+Supuestos!$B$10,24) -> 54274326 | KG4: =Supuestos!$B$9*POWER(1+Supuestos!$B$10,24) -> 54274326 | KH4: =Supuestos!$B$9*POWER(1+Supuestos!$B$10,24) -> 54274326 | KI4: =Supuestos!$B$9*POWER(1+Supuestos!$B$10,24) -> 54274326 | KJ4: =Supuestos!$B$9*POWER(1+Supuestos!$B$10,24) -> 54274326 | KK4: =Supuestos!$B$9*POWER(1+Supuestos!$B$10,24) -> 54274326 | ... KO4: =Supuestos!$B$9*POWER(1+Supuestos!$B$10,24) -> 54274326
A5: Otros Ingresos | B5: 0 | C5: 0 | D5: 0 | E5: 0 | F5: 0 | G5: 0 | H5: 0 | I5: 0 | J5: 0 | K5: 0 | L5: 0 | M5: 0 | N5: 0 | O5: 0 | P5: 0 | Q5: 0 | R5: 0 | S5: 0 | T5: 0 | U5: 0 | V5: 0 | W5: 0 | X5: 0 | Y5: 0 | Z5: 0 | AA5: 0 | AB5: 0 | AC5: 0 | AD5: 0 | AE5: 0 | AF5: 0 | AG5: 0 | AH5: 0 | AI5: 0 | AJ5: 0 | AK5: 0 | AL5: 0 | AM5: 0 | AN5: 0 | AO5: 0 | AP5: 0 | AQ5: 0 | AR5: 0 | AS5: 0 | AT5: 0 | AU5: 0 | AV5: 0 | AW5: 0 | AX5: 0 | AY5: 0 | AZ5: 0 | BA5: 0 | BB5: 0 | BC5: 0 | BD5: 0 | BE5: 0 | BF5: 0 | BG5: 0 | BH5: 0 | BI5: 0 | BJ5: 0 | BK5: 0 | BL5: 0 | BM5: 0 | BN5: 0 | BO5: 0 | BP5: 0 | BQ5: 0 | BR5: 0 | BS5: 0 | BT5: 0 | BU5: 0 | BV5: 0 | BW5: 0 | BX5: 0 | BY5: 0 | BZ5: 0 | CA5: 0 | CB5: 0 | CC5: 0 | CD5: 0 | CE5: 0 | CF5: 0 | CG5: 0 | CH5: 0 | CI5: 0 | CJ5: 0 | CK5: 0 | CL5: 0 | CM5: 0 | CN5: 0 | CO5: 0 | CP5: 0 | CQ5: 0 | CR5: 0 | CS5: 0 | CT5: 0 | CU5: 0 | CV5: 0 | CW5: 0 | CX5: 0 | CY5: 0 | CZ5: 0 | DA5: 0 | DB5: 0 | DC5: 0 | DD5: 0 | DE5: 0 | DF5: 0 | DG5: 0 | DH5: 0 | DI5: 0 | DJ5: 0 | DK5: 0 | DL5: 0 | DM5: 0 | DN5: 0 | DO5: 0 | DP5: 0 | DQ5: 0 | DR5: 0 | DS5: 0 | DT5: 0 | DU5: 0 | DV5: 0 | DW5: 0 | DX5: 0 | DY5: 0 | DZ5: 0 | EA5: 0 | EB5: 0 | EC5: 0 | ED5: 0 | EE5: 0 | EF5: 0 | EG5: 0 | EH5: 0 | EI5: 0 | EJ5: 0 | EK5: 0 | EL5: 0 | EM5: 0 | EN5: 0 | EO5: 0 | EP5: 0 | EQ5: 0 | ER5: 0 | ES5: 0 | ET5: 0 | EU5: 0 | EV5: 0 | EW5: 0 | EX5: 0 | EY5: 0 | EZ5: 0 | FA5: 0 | FB5: 0 | FC5: 0 | FD5: 0 | FE5: 0 | FF5: 0 | FG5: 0 | FH5: 0 | FI5: 0 | FJ5: 0 | FK5: 0 | FL5: 0 | FM5: 0 | FN5: 0 | FO5: 0 | FP5: 0 | FQ5: 0 | FR5: 0 | FS5: 0 | FT5: 0 | FU5: 0 | FV5: 0 | FW5: 0 | FX5: 0 | FY5: 0 | FZ5: 0 | GA5: 0 | GB5: 0 | GC5: 0 | GD5: 0 | GE5: 0 | GF5: 0 | GG5: 0 | GH5: 0 | GI5: 0 | GJ5: 0 | GK5: 0 | GL5: 0 | GM5: 0 | GN5: 0 | GO5: 0 | GP5: 0 | GQ5: 0 | GR5: 0 | GS5: 0 | GT5: 0 | GU5: 0 | GV5: 0 | GW5: 0 | GX5: 0 | GY5: 0 | GZ5: 0 | HA5: 0 | HB5: 0 | HC5: 0 | HD5: 0 | HE5: 0 | HF5: 0 | HG5: 0 | HH5: 0 | HI5: 0 | HJ5: 0 | HK5: 0 | HL5: 0 | HM5: 0 | HN5: 0 | HO5: 0 | HP5: 0 | HQ5: 0 | HR5: 0 | HS5: 0 | HT5: 0 | HU5: 0 | HV5: 0 | HW5: 0 | HX5: 0 | HY5: 0 | HZ5: 0 | IA5: 0 | IB5: 0 | IC5: 0 | ID5: 0 | IE5: 0 | IF5: 0 | IG5: 0 | IH5: 0 | II5: 0 | IJ5: 0 | IK5: 0 | IL5: 0 | IM5: 0 | IN5: 0 | IO5: 0 | IP5: 0 | IQ5: 0 | IR5: 0 | IS5: 0 | IT5: 0 | IU5: 0 | IV5: 0 | IW5: 0 | IX5: 0 | IY5: 0 | IZ5: 0 | JA5: 0 | JB5: 0 | JC5: 0 | JD5: 0 | JE5: 0 | JF5: 0 | JG5: 0 | JH5: 0 | JI5: 0 | JJ5: 0 | JK5: 0 | JL5: 0 | JM5: 0 | JN5: 0 | JO5: 0 | JP5: 0 | JQ5: 0 | JR5: 0 | JS5: 0 | JT5: 0 | JU5: 0 | JV5: 0 | JW5: 0 | JX5: 0 | JY5: 0 | JZ5: 0 | KA5: 0 | KB5: 0 | KC5: 0 | KD5: 0 | KE5: 0 | KF5: 0 | KG5: 0 | KH5: 0 | KI5: 0 | KJ5: 0 | KK5: 0 | KL5: 0 | KM5: 0 | KN5: 0 | KO5: 0
A6: TOTAL INGRESOS | B6: =B4+B5 -> 10700000 | C6: =C4+C5 -> 10700000 | D6: =D4+D5 -> 10700000 | E6: =E4+E5 -> 10700000 | F6: =F4+F5 -> 10700000 | G6: =G4+G5 -> 10700000 | H6: =H4+H5 -> 10700000 | I6: =I4+I5 -> 10700000 | ... KO6: =KO4+KO5 -> 54274326

Sheet Costos
A1: PROYECCIÓN DE COSTOS
A3: Concepto | B3: Mes 1 | C3: Mes 2 | D3: Mes 3 | E3: Mes 4 | F3: Mes 5 | G3: Mes 6 | H3: Mes 7 | I3: Mes 8 | J3: Mes 9 | K3: Mes 10 | L3: Mes 11 | M3: Mes 12 | N3: Mes 13 | O3: Mes 14 | P3: Mes 15 | Q3: Mes 16 | R3: Mes 17 | S3: Mes 18 | T3: Mes 19 | U3: Mes 20 | V3: Mes 21 | W3: Mes 22 | X3: Mes 23 | Y3: Mes 24 | Z3: Mes 25 | AA3: Mes 26 | AB3: Mes 27 | AC3: Mes 28 | AD3: Mes 29 | AE3: Mes 30 | AF3: Mes 31 | AG3: Mes 32 | AH3: Mes 33 | AI3: Mes 34 | AJ3: Mes 35 | AK3: Mes 36 | AL3: Mes 37 | AM3: Mes 38 | AN3: Mes 39 | AO3: Mes 40 | AP3: Mes 41 | AQ3: Mes 42 | AR3: Mes 43 | AS3: Mes 44 | AT3: Mes 45 | AU3: Mes 46 | AV3: Mes 47 | AW3: Mes 48 | AX3: Mes 49 | AY3: Mes 50 | AZ3: Mes 51 | BA3: Mes 52 | BB3: Mes 53 | BC3: Mes 54 | BD3: Mes 55 | BE3: Mes 56 | BF3: Mes 57 | BG3: Mes 58 | BH3: Mes 59 | BI3: Mes 60 | BJ3: Mes 61 | BK3: Mes 62 | BL3: Mes 63 | BM3: Mes 64 | BN3: Mes 65 | BO3: Mes 66 | BP3: Mes 67 | BQ3: Mes 68 | BR3: Mes 69 | BS3: Mes 70 | BT3: Mes 71 | BU3: Mes 72 | BV3: Mes 73 | BW3: Mes 74 | BX3: Mes 75 | BY3: Mes 76 | BZ3: Mes 77 | CA3: Mes 78 | CB3: Mes 79 | CC3: Mes 80 | CD3: Mes 81 | CE3: Mes 82 | CF3: Mes 83 | CG3: Mes 84 | CH3: Mes 85 | CI3: Mes 86 | CJ3: Mes 87 | CK3: Mes 88 | CL3: Mes 89 | CM3: Mes 90 | CN3: Mes 91 | CO3: Mes 92 | CP3: Mes 93 | CQ3: Mes 94 | CR3: Mes 95 | CS3: Mes 96 | CT3: Mes 97 | CU3: Mes 98 | CV3: Mes 99 | CW3: Mes 100 | CX3: Mes 101 | CY3: Mes 102 | CZ3: Mes 103 | DA3: Mes 104 | DB3: Mes 105 | DC3: Mes 106 | DD3: Mes 107 | DE3: Mes 108 | DF3: Mes 109 | DG3: Mes 110 | DH3: Mes 111 | DI3: Mes 112 | DJ3: Mes 113 | DK3: Mes 114 | DL3: Mes 115 | DM3: Mes 116 | DN3: Mes 117 | DO3: Mes 118 | DP3: Mes 119 | DQ3: Mes 120 | DR3: Mes 121 | DS3: Mes 122 | DT3: Mes 123 | DU3: Mes 124 | DV3: Mes 125 | DW3: Mes 126 | DX3: Mes 127 | DY3: Mes 128 | DZ3: Mes 129 | EA3: Mes 130 | EB3: Mes 131 | EC3: Mes 132 | ED3: Mes 133 | EE3: Mes 134 | EF3: Mes 135 | EG3: Mes 136 | EH3: Mes 137 | EI3: Mes 138 | EJ3: Mes 139 | EK3: Mes 140 | EL3: Mes 141 | EM3: Mes 142 | EN3: Mes 143 | EO3: Mes 144 | EP3: Mes 145 | EQ3: Mes 146 | ER3: Mes 147 | ES3: Mes 148 | ET3: Mes 149 | EU3: Mes 150 | EV3: Mes 151 | EW3: Mes 152 | EX3: Mes 153 | EY3: Mes 154 | EZ3: Mes 155 | FA3: Mes 156 | FB3: Mes 157 | FC3: Mes 158 | FD3: Mes 159 | FE3: Mes 160 | FF3: Mes 161 | FG3: Mes 162 | FH3: Mes 163 | FI3: Mes 164 | FJ3: Mes 165 | FK3: Mes 166 | FL3: Mes 167 | FM3: Mes 168 | FN3: Mes 169 | FO3: Mes 170 | FP3: Mes 171 | FQ3: Mes 172 | FR3: Mes 173 | FS3: Mes 174 | FT3: Mes 175 | FU3: Mes 176 | FV3: Mes 177 | FW3: Mes 178 | FX3: Mes 179 | FY3: Mes 180 | FZ3: Mes 181 | GA3: Mes 182 | GB3: Mes 183 | GC3: Mes 184 | GD3: Mes 185 | GE3: Mes 186 | GF3: Mes 187 | GG3: Mes 188 | GH3: Mes 189 | GI3: Mes 190 | GJ3: Mes 191 | GK3: Mes 192 | GL3: Mes 193 | GM3: Mes 194 | GN3: Mes 195 | GO3: Mes 196 | GP3: Mes 197 | GQ3: Mes 198 | GR3: Mes 199 | GS3: Mes 200 | GT3: Mes 201 | GU3: Mes 202 | GV3: Mes 203 | GW3: Mes 204 | GX3: Mes 205 | GY3: Mes 206 | GZ3: Mes 207 | HA3: Mes 208 | HB3: Mes 209 | HC3: Mes 210 | HD3: Mes 211 | HE3: Mes 212 | HF3: Mes 213 | HG3: Mes 214 | HH3: Mes 215 | HI3: Mes 216 | HJ3: Mes 217 | HK3: Mes 218 | HL3: Mes 219 | HM3: Mes 220 | HN3: Mes 221 | HO3: Mes 222 | HP3: Mes 223 | HQ3: Mes 224 | HR3: Mes 225 | HS3: Mes 226 | HT3: Mes 227 | HU3: Mes 228 | HV3: Mes 229 | HW3: Mes 230 | HX3: Mes 231 | HY3: Mes 232 | HZ3: Mes 233 | IA3: Mes 234 | IB3: Mes 235 | IC3: Mes 236 | ID3: Mes 237 | IE3: Mes 238 | IF3: Mes 239 | IG3: Mes 240 | IH3: Mes 241 | II3: Mes 242 | IJ3: Mes 243 | IK3: Mes 244 | IL3: Mes 245 | IM3: Mes 246 | IN3: Mes 247 | IO3: Mes 248 | IP3: Mes 249 | IQ3: Mes 250 | IR3: Mes 251 | IS3: Mes 252 | IT3: Mes 253 | IU3: Mes 254 | IV3: Mes 255 | IW3: Mes 256 | IX3: Mes 257 | IY3: Mes 258 | IZ3: Mes 259 | JA3: Mes 260 | JB3: Mes 261 | JC3: Mes 262 | JD3: Mes 263 | JE3: Mes 264 | JF3: Mes 265 | JG3: Mes 266 | JH3: Mes 267 | JI3: Mes 268 | JJ3: Mes 269 | JK3: Mes 270 | JL3: Mes 271 | JM3: Mes 272 | JN3: Mes 273 | JO3: Mes 274 | JP3: Mes 275 | JQ3: Mes 276 | JR3: Mes 277 | JS3: Mes 278 | JT3: Mes 279 | JU3: Mes 280 | JV3: Mes 281 | JW3: Mes 282 | JX3: Mes 283 | JY3: Mes 284 | JZ3: Mes 285 | KA3: Mes 286 | KB3: Mes 287 | KC3: Mes 288 | KD3: Mes 289 | KE3: Mes 290 | KF3: Mes 291 | KG3: Mes 292 | KH3: Mes 293 | KI3: Mes 294 | KJ3: Mes 295 | KK3: Mes 296 | KL3: Mes 297 | KM3: Mes 298 | KN3: Mes 299 | KO3: Mes 300
A4: COSTOS VARIABLES
A5: Costo de Ventas | B5: =Ingresos!B6*Supuestos!$B$13 -> 3959000 | C5: =Ingresos!C6*Supuestos!$B$13 -> 3959000 | D5: =Ingresos!D6*Supuestos!$B$13 -> 3959000 | E5: =Ingresos!E6*Supuestos!$B$13 -> 3959000 | F5: =Ingresos!F6*Supuestos!$B$13 -> 3959000 | G5: =Ingresos!G6*Supuestos!$B$13 -> 3959000 | H5: =Ingresos!H6*Supuestos!$B$13 -> 3959000 | I5: =Ingresos!I6*Supuestos!$B$13 -> 3959000 | ... KO5: =Ingresos!KO6*Supuestos!$B$13 -> 20081501
A6: Total Costos Variables | B6: =B5 -> 3959000 | C6: =C5 -> 3959000 | D6: =D5 -> 3959000 | E6: =E5 -> 3959000 | F6: =F5 -> 3959000 | G6: =G5 -> 3959000 | H6: =H5 -> 3959000 | I6: =I5 -> 3959000 | ... KO6: =KO5 -> 20081501
A8: COSTOS FIJOS
A9: Salarios y Cargas Sociales | B9: =Supuestos!$B$16 -> 3800000 | C9: =Supuestos!$B$16 -> 3800000 | D9: =Supuestos!$B$16 -> 3800000 | E9: =Supuestos!$B$16 -> 3800000 | F9: =Supuestos!$B$16 -> 3800000 | G9: =Supuestos!$B$16 -> 3800000 | H9: =Supuestos!$B$16 -> 3800000 | I9: =Supuestos!$B$16 -> 3800000 | ... KO9: =Supuestos!$B$16 -> 3800000
A10: Alquileres | B10: =Supuestos!$B$17 -> 1900000 | C10: =Supuestos!$B$17 -> 1900000 | D10: =Supuestos!$B$17 -> 1900000 | E10: =Supuestos!$B$17 -> 1900000 | F10: =Supuestos!$B$17 -> 1900000 | G10: =Supuestos!$B$17 -> 1900000 | H10: =Supuestos!$B$17 -> 1900000 | I10: =Supuestos!$B$17 -> 1900000 | ... KO10: =Supuestos!$B$17 -> 1900000
A11: Servicios | B11: =Supuestos!$B$18 -> 300000 | C11: =Supuestos!$B$18 -> 300000 | D11: =Supuestos!$B$18 -> 300000 | E11: =Supuestos!$B$18 -> 300000 | F11: =Supuestos!$B$18 -> 300000 | G11: =Supuestos!$B$18 -> 300000 | H11: =Supuestos!$B$18 -> 300000 | I11: =Supuestos!$B$18 -> 300000 | ... KO11: =Supuestos!$B$18 -> 300000
A12: Marketing y Publicidad | B12: =Supuestos!$B$19 -> 500000 | C12: =Supuestos!$B$19 -> 500000 | D12: =Supuestos!$B$19 -> 500000 | E12: =Supuestos!$B$19 -> 500000 | F12: =Supuestos!$B$19 -> 500000 | G12: =Supuestos!$B$19 -> 500000 | H12: =Supuestos!$B$19 -> 500000 | I12: =Supuestos!$B$19 -> 500000 | ... KO12: =Supuestos!$B$19 -> 500000
A13: Otros Gastos Fijos | B13: =Supuestos!$B$20 -> 400000 | C13: =Supuestos!$B$20 -> 400000 | D13: =Supuestos!$B$20 -> 400000 | E13: =Supuestos!$B$20 -> 400000 | F13: =Supuestos!$B$20 -> 400000 | G13: =Supuestos!$B$20 -> 400000 | H13: =Supuestos!$B$20 -> 400000 | I13: =Supuestos!$B$20 -> 400000 | ... KO13: =Supuestos!$B$20 -> 400000
A14: Total Costos Fijos | B14: =SUM(B9:B13) -> 6900000 | C14: =SUM(C9:C13) -> 6900000 | D14: =SUM(D9:D13) -> 6900000 | E14: =SUM(E9:E13) -> 6900000 | F14: =SUM(F9:F13) -> 6900000 | G14: =SUM(G9:G13) -> 6900000 | H14: =SUM(H9:H13) -> 6900000 | I14: =SUM(I9:I13) -> 6900000 | ... KO14: =SUM(KO9:KO13) -> 6900000
A16: Depreciación | B16: =Supuestos!$B$4/120 -> 416666.67 | C16: =Supuestos!$B$4/120 -> 416666.67 | D16: =Supuestos!$B$4/120 -> 416666.67 | E16: =Supuestos!$B$4/120 -> 416666.67 | F16: =Supuestos!$B$4/120 -> 416666.67 | G16: =Supuestos!$B$4/120 -> 416666.67 | H16: =Supuestos!$B$4/120 -> 416666.67 | I16: =Supuestos!$B$4/120 -> 416666.67 | ... DQ16: =Supuestos!$B$4/120 -> 416666.67 | DR16: 0 | DS16: 0 | DT16: 0 | DU16: 0 | DV16: 0 | DW16: 0 | DX16: 0 | DY16: 0 | DZ16: 0 | EA16: 0 | EB16: 0 | EC16: 0 | ED16: 0 | EE16: 0 | EF16: 0 | EG16: 0 | EH16: 0 | EI16: 0 | EJ16: 0 | EK16: 0 | EL16: 0 | EM16: 0 | EN16: 0 | EO16: 0 | EP16: 0 | EQ16: 0 | ER16: 0 | ES16: 0 | ET16: 0 | EU16: 0 | EV16: 0 | EW16: 0 | EX16: 0 | EY16: 0 | EZ16: 0 | FA16: 0 | FB16: 0 | FC16: 0 | FD16: 0 | FE16: 0 | FF16: 0 | FG16: 0 | FH16: 0 | FI16: 0 | FJ16: 0 | FK16: 0 | FL16: 0 | FM16: 0 | FN16: 0 | FO16: 0 | FP16: 0 | FQ16: 0 | FR16: 0 | FS16: 0 | FT16: 0 | FU16: 0 | FV16: 0 | FW16: 0 | FX16: 0 | FY16: 0 | FZ16: 0 | GA16: 0 | GB16: 0 | GC16: 0 | GD16: 0 | GE16: 0 | GF16: 0 | GG16: 0 | GH16: 0 | GI16: 0 | GJ16: 0 | GK16: 0 | GL16: 0 | GM16: 0 | GN16: 0 | GO16: 0 | GP16: 0 | GQ16: 0 | GR16: 0 | GS16: 0 | GT16: 0 | GU16: 0 | GV16: 0 | GW16: 0 | GX16: 0 | GY16: 0 | GZ16: 0 | HA16: 0 | HB16: 0 | HC16: 0 | HD16: 0 | HE16: 0 | HF16: 0 | HG16: 0 | HH16: 0 | HI16: 0 | HJ16: 0 | HK16: 0 | HL16: 0 | HM16: 0 | HN16: 0 | HO16: 0 | HP16: 0 | HQ16: 0 | HR16: 0 | HS16: 0 | HT16: 0 | HU16: 0 | HV16: 0 | HW16: 0 | HX16: 0 | HY16: 0 | HZ16: 0 | IA16: 0 | IB16: 0 | IC16: 0 | ID16: 0 | IE16: 0 | IF16: 0 | IG16: 0 | IH16: 0 | II16: 0 | IJ16: 0 | IK16: 0 | IL16: 0 | IM16: 0 | IN16: 0 | IO16: 0 | IP16: 0 | IQ16: 0 | IR16: 0 | IS16: 0 | IT16: 0 | IU16: 0 | IV16: 0 | IW16: 0 | IX16: 0 | IY16: 0 | IZ16: 0 | JA16: 0 | JB16: 0 | JC16: 0 | JD16: 0 | JE16: 0 | JF16: 0 | JG16: 0 | JH16: 0 | JI16: 0 | JJ16: 0 | JK16: 0 | JL16: 0 | JM16: 0 | JN16: 0 | JO16: 0 | JP16: 0 | JQ16: 0 | JR16: 0 | JS16: 0 | JT16: 0 | JU16: 0 | JV16: 0 | JW16: 0 | JX16: 0 | JY16: 0 | JZ16: 0 | KA16: 0 | KB16: 0 | KC16: 0 | KD16: 0 | KE16: 0 | KF16: 0 | KG16: 0 | KH16: 0 | KI16: 0 | KJ16: 0 | KK16: 0 | KL16: 0 | KM16: 0 | KN16: 0 | KO16: 0
A18: TOTAL COSTOS Y GASTOS | B18: =B6+B14+B16 -> 11275667 | C18: =C6+C14+C16 -> 11275667 | D18: =D6+D14+D16 -> 11275667 | E18: =E6+E14+E16 -> 11275667 | F18: =F6+F14+F16 -> 11275667 | G18: =G6+G14+G16 -> 11275667 | H18: =H6+H14+H16 -> 11275667 | I18: =I6+I14+I16 -> 11275667 | ... KO18: =KO6+KO14+KO16 -> 26981501

Sheet Estado de Resultados
A1: ESTADO DE RESULTADOS
A3: Concepto | B3: Mes 1 | C3: Mes 2 | D3: Mes 3 | E3: Mes 4 | F3: Mes 5 | G3: Mes 6 | H3: Mes 7 | I3: Mes 8 | J3: Mes 9 | K3: Mes 10 | L3: Mes 11 | M3: Mes 12 | N3: Mes 13 | O3: Mes 14 | P3: Mes 15 | Q3: Mes 16 | R3: Mes 17 | S3: Mes 18 | T3: Mes 19 | U3: Mes 20 | V3: Mes 21 | W3: Mes 22 | X3: Mes 23 | Y3: Mes 24 | Z3: Mes 25 | AA3: Mes 26 | AB3: Mes 27 | AC3: Mes 28 | AD3: Mes 29 | AE3: Mes 30 | AF3: Mes 31 | AG3: Mes 32 | AH3: Mes 33 | AI3: Mes 34 | AJ3: Mes 35 | AK3: Mes 36 | AL3: Mes 37 | AM3: Mes 38 | AN3: Mes 39 | AO3: Mes 40 | AP3: Mes 41 | AQ3: Mes 42 | AR3: Mes 43 | AS3: Mes 44 | AT3: Mes 45 | AU3: Mes 46 | AV3: Mes 47 | AW3: Mes 48 | AX3: Mes 49 | AY3: Mes 50 | AZ3: Mes 51 | BA3: Mes 52 | BB3: Mes 53 | BC3: Mes 54 | BD3: Mes 55 | BE3: Mes 56 | BF3: Mes 57 | BG3: Mes 58 | BH3: Mes 59 | BI3: Mes 60 | BJ3: Mes 61 | BK3: Mes 62 | BL3: Mes 63 | BM3: Mes 64 | BN3: Mes 65 | BO3: Mes 66 | BP3: Mes 67 | BQ3: Mes 68 | BR3: Mes 69 | BS3: Mes 70 | BT3: Mes 71 | BU3: Mes 72 | BV3: Mes 73 | BW3: Mes 74 | BX3: Mes 75 | BY3: Mes 76 | BZ3: Mes 77 | CA3: Mes 78 | CB3: Mes 79 | CC3: Mes 80 | CD3: Mes 81 | CE3: Mes 82 | CF3: Mes 83 | CG3: Mes 84 | CH3: Mes 85 | CI3: Mes 86 | CJ3: Mes 87 | CK3: Mes 88 | CL3: Mes 89 | CM3: Mes 90 | CN3: Mes 91 | CO3: Mes 92 | CP3: Mes 93 | CQ3: Mes 94 | CR3: Mes 95 | CS3: Mes 96 | CT3: Mes 97 | CU3: Mes 98 | CV3: Mes 99 | CW3: Mes 100 | CX3: Mes 101 | CY3: Mes 102 | CZ3: Mes 103 | DA3: Mes 104 | DB3: Mes 105 | DC3: Mes 106 | DD3: Mes 107 | DE3: Mes 108 | DF3: Mes 109 | DG3: Mes 110 | DH3: Mes 111 | DI3: Mes 112 | DJ3: Mes 113 | DK3: Mes 114 | DL3: Mes 115 | DM3: Mes 116 | DN3: Mes 117 | DO3: Mes 118 | DP3: Mes 119 | DQ3: Mes 120 | DR3: Mes 121 | DS3: Mes 122 | DT3: Mes 123 | DU3: Mes 124 | DV3: Mes 125 | DW3: Mes 126 | DX3: Mes 127 | DY3: Mes 128 | DZ3: Mes 129 | EA3: Mes 130 | EB3: Mes 131 | EC3: Mes 132 | ED3: Mes 133 | EE3: Mes 134 | EF3: Mes 135 | EG3: Mes 136 | EH3: Mes 137 | EI3: Mes 138 | EJ3: Mes 139 | EK3: Mes 140 | EL3: Mes 141 | EM3: Mes 142 | EN3: Mes 143 | EO3: Mes 144 | EP3: Mes 145 | EQ3: Mes 146 | ER3: Mes 147 | ES3: Mes 148 | ET3: Mes 149 | EU3: Mes 150 | EV3: Mes 151 | EW3: Mes 152 | EX3: Mes 153 | EY3: Mes 154 | EZ3: Mes 155 | FA3: Mes 156 | FB3: Mes 157 | FC3: Mes 158 | FD3: Mes 159 | FE3: Mes 160 | FF3: Mes 161 | FG3: Mes 162 | FH3: Mes 163 | FI3: Mes 164 | FJ3: Mes 165 | FK3: Mes 166 | FL3: Mes 167 | FM3: Mes 168 | FN3: Mes 169 | FO3: Mes 170 | FP3: Mes 171 | FQ3: Mes 172 | FR3: Mes 173 | FS3: Mes 174 | FT3: Mes 175 | FU3: Mes 176 | FV3: Mes 177 | FW3: Mes 178 | FX3: Mes 179 | FY3: Mes 180 | FZ3: Mes 181 | GA3: Mes 182 | GB3: Mes 183 | GC3: Mes 184 | GD3: Mes 185 | GE3: Mes 186 | GF3: Mes 187 | GG3: Mes 188 | GH3: Mes 189 | GI3: Mes 190 | GJ3: Mes 191 | GK3: Mes 192 | GL3: Mes 193 | GM3: Mes 194 | GN3: Mes 195 | GO3: Mes 196 | GP3: Mes 197 | GQ3: Mes 198 | GR3: Mes 199 | GS3: Mes 200 | GT3: Mes 201 | GU3: Mes 202 | GV3: Mes 203 | GW3: Mes 204 | GX3: Mes 205 | GY3: Mes 206 | GZ3: Mes 207 | HA3: Mes 208 | HB3: Mes 209 | HC3: Mes 210 | HD3: Mes 211 | HE3: Mes 212 | HF3: Mes 213 | HG3: Mes 214 | HH3: Mes 215 | HI3: Mes 216 | HJ3: Mes 217 | HK3: Mes 218 | HL3: Mes 219 | HM3: Mes 220 | HN3: Mes 221 | HO3: Mes 222 | HP3: Mes 223 | HQ3: Mes 224 | HR3: Mes 225 | HS3: Mes 226 | HT3: Mes 227 | HU3: Mes 228 | HV3: Mes 229 | HW3: Mes 230 | HX3: Mes 231 | HY3: Mes 232 | HZ3: Mes 233 | IA3: Mes 234 | IB3: Mes 235 | IC3: Mes 236 | ID3: Mes 237 | IE3: Mes 238 | IF3: Mes 239 | IG3: Mes 240 | IH3: Mes 241 | II3: Mes 242 | IJ3: Mes 243 | IK3: Mes 244 | IL3: Mes 245 | IM3: Mes 246 | IN3: Mes 247 | IO3: Mes 248 | IP3: Mes 249 | IQ3: Mes 250 | IR3: Mes 251 | IS3: Mes 252 | IT3: Mes 253 | IU3: Mes 254 | IV3: Mes 255 | IW3: Mes 256 | IX3: Mes 257 | IY3: Mes 258 | IZ3: Mes 259 | JA3: Mes 260 | JB3: Mes 261 | JC3: Mes 262 | JD3: Mes 263 | JE3: Mes 264 | JF3: Mes 265 | JG3: Mes 266 | JH3: Mes 267 | JI3: Mes 268 | JJ3: Mes 269 | JK3: Mes 270 | JL3: Mes 271 | JM3: Mes 272 | JN3: Mes 273 | JO3: Mes 274 | JP3: Mes 275 | JQ3: Mes 276 | JR3: Mes 277 | JS3: Mes 278 | JT3: Mes 279 | JU3: Mes 280 | JV3: Mes 281 | JW3: Mes 282 | JX3: Mes 283 | JY3: Mes 284 | JZ3: Mes 285 | KA3: Mes 286 | KB3: Mes 287 | KC3: Mes 288 | KD3: Mes 289 | KE3: Mes 290 | KF3: Mes 291 | KG3: Mes 292 | KH3: Mes 293 | KI3: Mes 294 | KJ3: Mes 295 | KK3: Mes 296 | KL3: Mes 297 | KM3: Mes 298 | KN3: Mes 299 | KO3: Mes 300
A4: Ingresos por Ventas | B4: =Ingresos!B6 -> 10700000 | C4: =Ingresos!C6 -> 10700000 | D4: =Ingresos!D6 -> 10700000 | E4: =Ingresos!E6 -> 10700000 | F4: =Ingresos!F6 -> 10700000 | G4: =Ingresos!G6 -> 10700000 | H4: =Ingresos!H6 -> 10700000 | I4: =Ingresos!I6 -> 10700000 | ... KO4: =Ingresos!KO6 -> 54274326
A5: Costos Variables | B5: =Costos!B6 -> 3959000 | C5: =Costos!C6 -> 3959000 | D5: =Costos!D6 -> 3959000 | E5: =Costos!E6 -> 3959000 | F5: =Costos!F6 -> 3959000 | G5: =Costos!G6 -> 3959000 | H5: =Costos!H6 -> 3959000 | I5: =Costos!I6 -> 3959000 | ... KO5: =Costos!KO6 -> 20081501
A6: MARGEN BRUTO | B6: =B4-B5 -> 6741000 | C6: =C4-C5 -> 6741000 | D6: =D4-D5 -> 6741000 | E6: =E4-E5 -> 6741000 | F6: =F4-F5 -> 6741000 | G6: =G4-G5 -> 6741000 | H6: =H4-H5 -> 6741000 | I6: =I4-I5 -> 6741000 | ... KO6: =KO4-KO5 -> 34192826
A8: Costos Fijos Operativos | B8: =Costos!B14 -> 6900000 | C8: =Costos!C14 -> 6900000 | D8: =Costos!D14 -> 6900000 | E8: =Costos!E14 -> 6900000 | F8: =Costos!F14 -> 6900000 | G8: =Costos!G14 -> 6900000 | H8: =Costos!H14 -> 6900000 | I8: =Costos!I14 -> 6900000 | ... KO8: =Costos!KO14 -> 6900000
A9: EBITDA | B9: =B6-B8 -> -159000 | C9: =C6-C8 -> -159000 | D9: =D6-D8 -> -159000 | E9: =E6-E8 -> -159000 | F9: =F6-F8 -> -159000 | G9: =G6-G8 -> -159000 | H9: =H6-H8 -> -159000 | I9: =I6-I8 -> -159000 | ... KO9: =KO6-KO8 -> 27292826
A10: Depreciación | B10: =Costos!B16 -> 416666.67 | C10: =Costos!C16 -> 416666.67 | D10: =Costos!D16 -> 416666.67 | E10: =Costos!E16 -> 416666.67 | F10: =Costos!F16 -> 416666.67 | G10: =Costos!G16 -> 416666.67 | H10: =Costos!H16 -> 416666.67 | I10: =Costos!I16 -> 416666.67 | ... KO10: =Costos!KO16 -> 0
A11: EBIT (Resultado Operativo) | B11: =B9-B10 -> -575666.67 | C11: =C9-C10 -> -575666.67 | D11: =D9-D10 -> -575666.67 | E11: =E9-E10 -> -575666.67 | F11: =F9-F10 -> -575666.67 | G11: =G9-G10 -> -575666.67 | H11: =H9-H10 -> -575666.67 | I11: =I9-I10 -> -575666.67 | ... KO11: =KO9-KO10 -> 27292826
A12: Gastos Financieros | B12: =Financiamiento!B6 -> 23333.333 | C12: =Financiamiento!C6 -> 23007.416 | D12: =Financiamiento!D6 -> 22679.598 | E12: =Financiamiento!E6 -> 22349.868 | F12: =Financiamiento!F6 -> 22018.214 | G12: =Financiamiento!G6 -> 21684.626 | H12: =Financiamiento!H6 -> 21349.092 | I12: =Financiamiento!I6 -> 21011.6 | ... KO12: =Financiamiento!KO6 -> 1.3292948e-10
A13: EBT (Utilidad antes de Impuestos) | B13: =B11-B12 -> -599000 | C13: =C11-C12 -> -598674.08 | D13: =D11-D12 -> -598346.27 | E13: =E11-E12 -> -598016.53 | F13: =F11-F12 -> -597684.88 | G13: =G11-G12 -> -597351.29 | H13: =H11-H12 -> -597015.76 | I13: =I11-I12 -> -596678.27 | ... KO13: =KO11-KO12 -> 27292826
A14: Impuestos | B14: =IF(B13>0,B13*'Panel de Control'!$B$15,0) -> 0 | C14: =IF(C13>0,C13*'Panel de Control'!$B$15,0) -> 0 | D14: =IF(D13>0,D13*'Panel de Control'!$B$15,0) -> 0 | E14: =IF(E13>0,E13*'Panel de Control'!$B$15,0) -> 0 | F14: =IF(F13>0,F13*'Panel de Control'!$B$15,0) -> 0 | G14: =IF(G13>0,G13*'Panel de Control'!$B$15,0) -> 0 | H14: =IF(H13>0,H13*'Panel de Control'!$B$15,0) -> 0 | I14: =IF(I13>0,I13*'Panel de Control'!$B$15,0) -> 0 | ... KO14: =IF(KO13>0,KO13*'Panel de Control'!$B$15,0) -> 7369062.9
A15: UTILIDAD NETA | B15: =B13-B14 -> -599000 | C15: =C13-C14 -> -598674.08 | D15: =D13-D14 -> -598346.27 | E15: =E13-E14 -> -598016.53 | F15: =F13-F14 -> -597684.88 | G15: =G13-G14 -> -597351.29 | H15: =H13-H14 -> -597015.76 | I15: =I13-I14 -> -596678.27 | ... KO15: =KO13-KO14 -> 19923763
A17: MÁRGENES
A18: Margen Bruto % | B18: =IF(B4<>0,B6/B4,0) -> 0.63 | C18: =IF(C4<>0,C6/C4,0) -> 0.63 | D18: =IF(D4<>0,D6/D4,0) -> 0.63 | E18: =IF(E4<>0,E6/E4,0) -> 0.63 | F18: =IF(F4<>0,F6/F4,0) -> 0.63 | G18: =IF(G4<>0,G6/G4,0) -> 0.63 | H18: =IF(H4<>0,H6/H4,0) -> 0.63 | I18: =IF(I4<>0,I6/I4,0) -> 0.63 | ... KO18: =IF(KO4<>0,KO6/KO4,0) -> 0.63
A19: Margen EBITDA % | B19: =IF(B4<>0,B9/B4,0) -> -0.014859813 | C19: =IF(C4<>0,C9/C4,0) -> -0.014859813 | D19: =IF(D4<>0,D9/D4,0) -> -0.014859813 | E19: =IF(E4<>0,E9/E4,0) -> -0.014859813 | F19: =IF(F4<>0,F9/F4,0) -> -0.014859813 | G19: =IF(G4<>0,G9/G4,0) -> -0.014859813 | H19: =IF(H4<>0,H9/H4,0) -> -0.014859813 | I19: =IF(I4<>0,I9/I4,0) -> -0.014859813 | ... KO19: =IF(KO4<>0,KO9/KO4,0) -> 0.50286807
A20: Margen Neto % | B20: =IF(B4<>0,B15/B4,0) -> -0.055981308 | C20: =IF(C4<>0,C15/C4,0) -> -0.055950849 | D20: =IF(D4<>0,D15/D4,0) -> -0.055920212 | E20: =IF(E4<>0,E15/E4,0) -> -0.055889396 | F20: =IF(F4<>0,F15/F4,0) -> -0.0558584 | G20: =IF(G4<>0,G15/G4,0) -> -0.055827224 | H20: =IF(H4<>0,H15/H4,0) -> -0.055795865 | I20: =IF(I4<>0,I15/I4,0) -> -0.055764324 | ... KO20: =IF(KO4<>0,KO15/KO4,0) -> 0.36709369

Sheet Financiamiento
A1: TABLA DE FINANCIAMIENTO
A3: Concepto | B3: Mes 1 | C3: Mes 2 | D3: Mes 3 | E3: Mes 4 | F3: Mes 5 | G3: Mes 6 | H3: Mes 7 | I3: Mes 8 | J3: Mes 9 | K3: Mes 10 | L3: Mes 11 | M3: Mes 12 | N3: Mes 13 | O3: Mes 14 | P3: Mes 15 | Q3: Mes 16 | R3: Mes 17 | S3: Mes 18 | T3: Mes 19 | U3: Mes 20 | V3: Mes 21 | W3: Mes 22 | X3: Mes 23 | Y3: Mes 24 | Z3: Mes 25 | AA3: Mes 26 | AB3: Mes 27 | AC3: Mes 28 | AD3: Mes 29 | AE3: Mes 30 | AF3: Mes 31 | AG3: Mes 32 | AH3: Mes 33 | AI3: Mes 34 | AJ3: Mes 35 | AK3: Mes 36 | AL3: Mes 37 | AM3: Mes 38 | AN3: Mes 39 | AO3: Mes 40 | AP3: Mes 41 | AQ3: Mes 42 | AR3: Mes 43 | AS3: Mes 44 | AT3: Mes 45 | AU3: Mes 46 | AV3: Mes 47 | AW3: Mes 48 | AX3: Mes 49 | AY3: Mes 50 | AZ3: Mes 51 | BA3: Mes 52 | BB3: Mes 53 | BC3: Mes 54 | BD3: Mes 55 | BE3: Mes 56 | BF3: Mes 57 | BG3: Mes 58 | BH3: Mes 59 | BI3: Mes 60 | BJ3: Mes 61 | BK3: Mes 62 | BL3: Mes 63 | BM3: Mes 64 | BN3: Mes 65 | BO3: Mes 66 | BP3: Mes 67 | BQ3: Mes 68 | BR3: Mes 69 | BS3: Mes 70 | BT3: Mes 71 | BU3: Mes 72 | BV3: Mes 73 | BW3: Mes 74 | BX3: Mes 75 | BY3: Mes 76 | BZ3: Mes 77 | CA3: Mes 78 | CB3: Mes 79 | CC3: Mes 80 | CD3: Mes 81 | CE3: Mes 82 | CF3: Mes 83 | CG3: Mes 84 | CH3: Mes 85 | CI3: Mes 86 | CJ3: Mes 87 | CK3: Mes 88 | CL3: Mes 89 | CM3: Mes 90 | CN3: Mes 91 | CO3: Mes 92 | CP3: Mes 93 | CQ3: Mes 94 | CR3: Mes 95 | CS3: Mes 96 | CT3: Mes 97 | CU3: Mes 98 | CV3: Mes 99 | CW3: Mes 100 | CX3: Mes 101 | CY3: Mes 102 | CZ3: Mes 103 | DA3: Mes 104 | DB3: Mes 105 | DC3: Mes 106 | DD3: Mes 107 | DE3: Mes 108 | DF3: Mes 109 | DG3: Mes 110 | DH3: Mes 111 | DI3: Mes 112 | DJ3: Mes 113 | DK3: Mes 114 | DL3: Mes 115 | DM3: Mes 116 | DN3: Mes 117 | DO3: Mes 118 | DP3: Mes 119 | DQ3: Mes 120 | DR3: Mes 121 | DS3: Mes 122 | DT3: Mes 123 | DU3: Mes 124 | DV3: Mes 125 | DW3: Mes 126 | DX3: Mes 127 | DY3: Mes 128 | DZ3: Mes 129 | EA3: Mes 130 | EB3: Mes 131 | EC3: Mes 132 | ED3: Mes 133 | EE3: Mes 134 | EF3: Mes 135 | EG3: Mes 136 | EH3: Mes 137 | EI3: Mes 138 | EJ3: Mes 139 | EK3: Mes 140 | EL3: Mes 141 | EM3: Mes 142 | EN3: Mes 143 | EO3: Mes 144 | EP3: Mes 145 | EQ3: Mes 146 | ER3: Mes 147 | ES3: Mes 148 | ET3: Mes 149 | EU3: Mes 150 | EV3: Mes 151 | EW3: Mes 152 | EX3: Mes 153 | EY3: Mes 154 | EZ3: Mes 155 | FA3: Mes 156 | FB3: Mes 157 | FC3: Mes 158 | FD3: Mes 159 | FE3: Mes 160 | FF3: Mes 161 | FG3: Mes 162 | FH3: Mes 163 | FI3: Mes 164 | FJ3: Mes 165 | FK3: Mes 166 | FL3: Mes 167 | FM3: Mes 168 | FN3: Mes 169 | FO3: Mes 170 | FP3: Mes 171 | FQ3: Mes 172 | FR3: Mes 173 | FS3: Mes 174 | FT3: Mes 175 | FU3: Mes 176 | FV3: Mes 177 | FW3: Mes 178 | FX3: Mes 179 | FY3: Mes 180 | FZ3: Mes 181 | GA3: Mes 182 | GB3: Mes 183 | GC3: Mes 184 | GD3: Mes 185 | GE3: Mes 186 | GF3: Mes 187 | GG3: Mes 188 | GH3: Mes 189 | GI3: Mes 190 | GJ3: Mes 191 | GK3: Mes 192 | GL3: Mes 193 | GM3: Mes 194 | GN3: Mes 195 | GO3: Mes 196 | GP3: Mes 197 | GQ3: Mes 198 | GR3: Mes 199 | GS3: Mes 200 | GT3: Mes 201 | GU3: Mes 202 | GV3: Mes 203 | GW3: Mes 204 | GX3: Mes 205 | GY3: Mes 206 | GZ3: Mes 207 | HA3: Mes 208 | HB3: Mes 209 | HC3: Mes 210 | HD3: Mes 211 | HE3: Mes 212 | HF3: Mes 213 | HG3: Mes 214 | HH3: Mes 215 | HI3: Mes 216 | HJ3: Mes 217 | HK3: Mes 218 | HL3: Mes 219 | HM3: Mes 220 | HN3: Mes 221 | HO3: Mes 222 | HP3: Mes 223 | HQ3: Mes 224 | HR3: Mes 225 | HS3: Mes 226 | HT3: Mes 227 | HU3: Mes 228 | HV3: Mes 229 | HW3: Mes 230 | HX3: Mes 231 | HY3: Mes 232 | HZ3: Mes 233 | IA3: Mes 234 | IB3: Mes 235 | IC3: Mes 236 | ID3: Mes 237 | IE3: Mes 238 | IF3: Mes 239 | IG3: Mes 240 | IH3: Mes 241 | II3: Mes 242 | IJ3: Mes 243 | IK3: Mes 244 | IL3: Mes 245 | IM3: Mes 246 | IN3: Mes 247 | IO3: Mes 248 | IP3: Mes 249 | IQ3: Mes 250 | IR3: Mes 251 | IS3: Mes 252 | IT3: Mes 253 | IU3: Mes 254 | IV3: Mes 255 | IW3: Mes 256 | IX3: Mes 257 | IY3: Mes 258 | IZ3: Mes 259 | JA3: Mes 260 | JB3: Mes 261 | JC3: Mes 262 | JD3: Mes 263 | JE3: Mes 264 | JF3: Mes 265 | JG3: Mes 266 | JH3: Mes 267 | JI3: Mes 268 | JJ3: Mes 269 | JK3: Mes 270 | JL3: Mes 271 | JM3: Mes 272 | JN3: Mes 273 | JO3: Mes 274 | JP3: Mes 275 | JQ3: Mes 276 | JR3: Mes 277 | JS3: Mes 278 | JT3: Mes 279 | JU3: Mes 280 | JV3: Mes 281 | JW3: Mes 282 | JX3: Mes 283 | JY3: Mes 284 | JZ3: Mes 285 | KA3: Mes 286 | KB3: Mes 287 | KC3: Mes 288 | KD3: Mes 289 | KE3: Mes 290 | KF3: Mes 291 | KG3: Mes 292 | KH3: Mes 293 | KI3: Mes 294 | KJ3: Mes 295 | KK3: Mes 296 | KL3: Mes 297 | KM3: Mes 298 | KN3: Mes 299 | KO3: Mes 300
A4: Saldo Inicial | B4: =Supuestos!$B$27 -> 4000000 | C4: =B7 -> 3944128.5 | D4: =C7 -> 3887931.2 | E4: =D7 -> 3831406 | F4: =E7 -> 3774551 | G4: =F7 -> 3717364.5 | H4: =G7 -> 3659844.3 | I4: =H7 -> 3601988.6 | J4: =I7 -> 3543795.4 | ... KO4: =KN7 -> 2.2787911e-08
A5: Cuota Mensual | B5: =IF(B4>0,IF(1<=Supuestos!$B$29,-PMT(Supuestos!$B$28/12,Supuestos!$B$29,Supuestos!$B$27),0),0) -> 79204.794 | C5: =IF(C4>0,IF(2<=Supuestos!$B$29,-PMT(Supuestos!$B$28/12,Supuestos!$B$29,Supuestos!$B$27),0),0) -> 79204.794 | D5: =IF(D4>0,IF(3<=Supuestos!$B$29,-PMT(Supuestos!$B$28/12,Supuestos!$B$29,Supuestos!$B$27),0),0) -> 79204.794 | E5: =IF(E4>0,IF(4<=Supuestos!$B$29,-PMT(Supuestos!$B$28/12,Supuestos!$B$29,Supuestos!$B$27),0),0) -> 79204.794 | F5: =IF(F4>0,IF(5<=Supuestos!$B$29,-PMT(Supuestos!$B$28/12,Supuestos!$B$29,Supuestos!$B$27),0),0) -> 79204.794 | G5: =IF(G4>0,IF(6<=Supuestos!$B$29,-PMT(Supuestos!$B$28/12,Supuestos!$B$29,Supuestos!$B$27),0),0) -> 79204.794 | H5: =IF(H4>0,IF(7<=Supuestos!$B$29,-PMT(Supuestos!$B$28/12,Supuestos!$B$29,Supuestos!$B$27),0),0) -> 79204.794 | I5: =IF(I4>0,IF(8<=Supuestos!$B$29,-PMT(Supuestos!$B$28/12,Supuestos!$B$29,Supuestos!$B$27),0),0) -> 79204.794 | J5: =IF(J4>0,IF(9<=Supuestos!$B$29,-PMT(Supuestos!$B$28/12,Supuestos!$B$29,Supuestos!$B$27),0),0) -> 79204.794 | K5: =IF(K4>0,IF(10<=Supuestos!$B$29,-PMT(Supuestos!$B$28/12,Supuestos!$B$29,Supuestos!$B$27),0),0) -> 79204.794 | L5: =IF(L4>0,IF(11<=Supuestos!$B$29,-PMT(Supuestos!$B$28/12,Supuestos!$B$29,Supuestos!$B$27),0),0) -> 79204.794 | M5: =IF(M4>0,IF(12<=Supuestos!$B$29,-PMT(Supuestos!$B$28/12,Supuestos!$B$29,Supuestos!$B$27),0),0) -> 79204.794 | N5: =IF(N4>0,IF(13<=Supuestos!$B$29,-PMT(Supuestos!$B$28/12,Supuestos!$B$29,Supuestos!$B$27),0),0) -> 79204.794 | O5: =IF(O4>0,IF(14<=Supuestos!$B$29,-PMT(Supuestos!$B$28/12,Supuestos!$B$29,Supuestos!$B$27),0),0) -> 79204.794 | P5: =IF(P4>0,IF(15<=Supuestos!$B$29,-PMT(Supuestos!$B$28/12,Supuestos!$B$29,Supuestos!$B$27),0),0) -> 79204.794 | Q5: =IF(Q4>0,IF(16<=Supuestos!$B$29,-PMT(Supuestos!$B$28/12,Supuestos!$B$29,Supuestos!$B$27),0),0) -> 79204.794 | R5: =IF(R4>0,IF(17<=Supuestos!$B$29,-PMT(Supuestos!$B$28/12,Supuestos!$B$29,Supuestos!$B$27),0),0) -> 79204.794 | S5: =IF(S4>0,IF(18<=Supuestos!$B$29,-PMT(Supuestos!$B$28/12,Supuestos!$B$29,Supuestos!$B$27),0),0) -> 79204.794 | T5: =IF(T4>0,IF(19<=Supuestos!$B$29,-PMT(Supuestos!$B$28/12,Supuestos!$B$29,Supuestos!$B$27),0),0) -> 79204.794 | U5: =IF(U4>0,IF(20<=Supuestos!$B$29,-PMT(Supuestos!$B$28/12,Supuestos!$B$29,Supuestos!$B$27),0),0) -> 79204.794 | V5: =IF(V4>0,IF(21<=Supuestos!$B$29,-PMT(Supuestos!$B$28/12,Supuestos!$B$29,Supuestos!$B$27),0),0) -> 79204.794 | W5: =IF(W4>0,IF(22<=Supuestos!$B$29,-PMT(Supuestos!$B$28/12,Supuestos!$B$29,Supuestos!$B$27),0),0) -> 79204.794 | X5: =IF(X4>0,IF(23<=Supuestos!$B$29,-PMT(Supuestos!$B$28/12,Supuestos!$B$29,Supuestos!$B$27),0),0) -> 79204.794 | Y5: =IF(Y4>0,IF(24<=Supuestos!$B$29,-PMT(Supuestos!$B$28/12,Supuestos!$B$29,Supuestos!$B$27),0),0) -> 79204.794 | Z5: =IF(Z4>0,IF(25<=Supuestos!$B$29,-PMT(Supuestos!$B$28/12,Supuestos!$B$29,Supuestos!$B$27),0),0) -> 79204.794 | AA5: =IF(AA4>0,IF(26<=Supuestos!$B$29,-PMT(Supuestos!$B$28/12,Supuestos!$B$29,Supuestos!$B$27),0),0) -> 79204.794 | AB5: =IF(AB4>0,IF(27<=Supuestos!$B$29,-PMT(Supuestos!$B$28/12,Supuestos!$B$29,Supuestos!$B$27),0),0) -> 79204.794 | AC5: =IF(AC4>0,IF(28<=Supuestos!$B$29,-PMT(Supuestos!$B$28/12,Supuestos!$B$29,Supuestos!$B$27),0),0) -> 79204.794 | AD5: =IF(AD4>0,IF(29<=Supuestos!$B$29,-PMT(Supuestos!$B$28/12,Supuestos!$B$29,Supuestos!$B$27),0),0) -> 79204.794 | AE5: =IF(AE4>0,IF(30<=Supuestos!$B$29,-PMT(Supuestos!$B$28/12,Supuestos!$B$29,Supuestos!$B$27),0),0) -> 79204.794 | AF5: =IF(AF4>0,IF(31<=Supuestos!$B$29,-PMT(Supuestos!$B$28/12,Supuestos!$B$29,Supuestos!$B$27),0),0) -> 79204.794 | AG5: =IF(AG4>0,IF(32<=Supuestos!$B$29,-PMT(Supuestos!$B$28/12,Supuestos!$B$29,Supuestos!$B$27),0),0) -> 79204.794 | AH5: =IF(AH4>0,IF(33<=Supuestos!$B$29,-PMT(Supuestos!$B$28/12,Supuestos!$B$29,Supuestos!$B$27),0),0) -> 79204.794 | AI5: =IF(AI4>0,IF(34<=Supuestos!$B$29,-PMT(Supuestos!$B$28/12,Supuestos!$B$29,Supuestos!$B$27),0),0) -> 79204.794 | AJ5: =IF(AJ4>0,IF(35<=Supuestos!$B$29,-PMT(Supuestos!$B$28/12,Supuestos!$B$29,Supuestos!$B$27),0),0) -> 79204.794 | AK5: =IF(AK4>0,IF(36<=Supuestos!$B$29,-PMT(Supuestos!$B$28/12,Supuestos!$B$29,Supuestos!$B$27),0),0) -> 79204.794 | AL5: =IF(AL4>0,IF(37<=Supuestos!$B$29,-PMT(Supuestos!$B$28/12,Supuestos!$B$29,Supuestos!$B$27),0),0) -> 79204.794 | AM5: =IF(AM4>0,IF(38<=Supuestos!$B$29,-PMT(Supuestos!$B$28/12,Supuestos!$B$29,Supuestos!$B$27),0),0) -> 79204.794 | AN5: =IF(AN4>0,IF(39<=Supuestos!$B$29,-PMT(Supuestos!$B$28/12,Supuestos!$B$29,Supuestos!$B$27),0),0) -> 79204.794 | AO5: =IF(AO4>0,IF(40<=Supuestos!$B$29,-PMT(Supuestos!$B$28/12,Supuestos!$B$29,Supuestos!$B$27),0),0) -> 79204.794 | AP5: =IF(AP4>0,IF(41<=Supuestos!$B$29,-PMT(Supuestos!$B$28/12,Supuestos!$B$29,Supuestos!$B$27),0),0) -> 79204.794 | AQ5: =IF(AQ4>0,IF(42<=Supuestos!$B$29,-PMT(Supuestos!$B$28/12,Supuestos!$B$29,Supuestos!$B$27),0),0) -> 79204.794 | AR5: =IF(AR4>0,IF(43<=Supuestos!$B$29,-PMT(Supuestos!$B$28/12,Supuestos!$B$29,Supuestos!$B$27),0),0) -> 79204.794 | AS5: =IF(AS4>0,IF(44<=Supuestos!$B$29,-PMT(Supuestos!$B$28/12,Supuestos!$B$29,Supuestos!$B$27),0),0) -> 79204.794 | AT5: =IF(AT4>0,IF(45<=Supuestos!$B$29,-PMT(Supuestos!$B$28/12,Supuestos!$B$29,Supuestos!$B$27),0),0) -> 79204.794 | AU5: =IF(AU4>0,IF(46<=Supuestos!$B$29,-PMT(Supuestos!$B$28/12,Supuestos!$B$29,Supuestos!$B$27),0),0) -> 79204.794 | AV5: =IF(AV4>0,IF(47<=Supuestos!$B$29,-PMT(Supuestos!$B$28/12,Supuestos!$B$29,Supuestos!$B$27),0),0) -> 79204.794 | AW5: =IF(AW4>0,IF(48<=Supuestos!$B$29,-PMT(Supuestos!$B$28/12,Supuestos!$B$29,Supuestos!$B$27),0),0) -> 79204.794 | AX5: =IF(AX4>0,IF(49<=Supuestos!$B$29,-PMT(Supuestos!$B$28/12,Supuestos!$B$29,Supuestos!$B$27),0),0) -> 79204.794 | AY5: =IF(AY4>0,IF(50<=Supuestos!$B$29,-PMT(Supuestos!$B$28/12,Supuestos!$B$29,Supuestos!$B$27),0),0) -> 79204.794 | AZ5: =IF(AZ4>0,IF(51<=Supuestos!$B$29,-PMT(Supuestos!$B$28/12,Supuestos!$B$29,Supuestos!$B$27),0),0) -> 79204.794 | BA5: =IF(BA4>0,IF(52<=Supuestos!$B$29,-PMT(Supuestos!$B$28/12,Supuestos!$B$29,Supuestos!$B$27),0),0) -> 79204.794 | BB5: =IF(BB4>0,IF(53<=Supuestos!$B$29,-PMT(Supuestos!$B$28/12,Supuestos!$B$29,Supuestos!$B$27),0),0) -> 79204.794 | BC5: =IF(BC4>0,IF(54<=Supuestos!$B$29,-PMT(Supuestos!$B$28/12,Supuestos!$B$29,Supuestos!$B$27),0),0) -> 79204.794 | BD5: =IF(BD4>0,IF(55<=Supuestos!$B$29,-PMT(Supuestos!$B$28/12,Supuestos!$B$29,Supuestos!$B$27),0),0) -> 79204.794 | BE5: =IF(BE4>0,IF(56<=Supuestos!$B$29,-PMT(Supuestos!$B$28/12,Supuestos!$B$29,Supuestos!$B$27),0),0) -> 79204.794 | BF5: =IF(BF4>0,IF(57<=Supuestos!$B$29,-PMT(Supuestos!$B$28/12,Supuestos!$B$29,Supuestos!$B$27),0),0) -> 79204.794 | BG5: =IF(BG4>0,IF(58<=Supuestos!$B$29,-PMT(Supuestos!$B$28/12,Supuestos!$B$29,Supuestos!$B$27),0),0) -> 79204.794 | BH5: =IF(BH4>0,IF(59<=Supuestos!$B$29,-PMT(Supuestos!$B$28/12,Supuestos!$B$29,Supuestos!$B$27),0),0) -> 79204.794 | BI5: =IF(BI4>0,IF(60<=Supuestos!$B$29,-PMT(Supuestos!$B$28/12,Supuestos!$B$29,Supuestos!$B$27),0),0) -> 79204.794 | BJ5: =IF(BJ4>0,IF(61<=Supuestos!$B$29,-PMT(Supuestos!$B$28/12,Supuestos!$B$29,Supuestos!$B$27),0),0) -> 0 | BK5: =IF(BK4>0,IF(62<=Supuestos!$B$29,-PMT(Supuestos!$B$28/12,Supuestos!$B$29,Supuestos!$B$27),0),0) -> 0 | BL5: =IF(BL4>0,IF(63<=Supuestos!$B$29,-PMT(Supuestos!$B$28/12,Supuestos!$B$29,Supuestos!$B$27),0),0) -> 0 | BM5: =IF(BM4>0,IF(64<=Supuestos!$B$29,-PMT(Supuestos!$B$28/12,Supuestos!$B$29,Supuestos!$B$27),0),0) -> 0 | BN5: =IF(BN4>0,IF(65<=Supuestos!$B$29,-PMT(Supuestos!$B$28/12,Supuestos!$B$29,Supuestos!$B$27),0),0) -> 0 | BO5: =IF(BO4>0,IF(66<=Supuestos!$B$29,-PMT(Supuestos!$B$28/12,Supuestos!$B$29,Supuestos!$B$27),0),0) -> 0 | BP5: =IF(BP4>0,IF(67<=Supuestos!$B$29,-PMT(Supuestos!$B$28/12,Supuestos!$B$29,Supuestos!$B$27),0),0) -> 0 | BQ5: =IF(BQ4>0,IF(68<=Supuestos!$B$29,-PMT(Supuestos!$B$28/12,Supuestos!$B$29,Supuestos!$B$27),0),0) -> 0 | BR5: =IF(BR4>0,IF(69<=Supuestos!$B$29,-PMT(Supuestos!$B$28/12,Supuestos!$B$29,Supuestos!$B$27),0),0) -> 0 | BS5: =IF(BS4>0,IF(70<=Supuestos!$B$29,-PMT(Supuestos!$B$28/12,Supuestos!$B$29,Supuestos!$B$27),0),0) -> 0 | BT5: =IF(BT4>0,IF(71<=Supuestos!$B$29,-PMT(Supuestos!$B$28/12,Supuestos!$B$29,Supuestos!$B$27),0),0) -> 0 | BU5: =IF(BU4>0,IF(72<=Supuestos!$B$29,-PMT(Supuestos!$B$28/12,Supuestos!$B$29,Supuestos!$B$27),0),0) -> 0 | BV5: =IF(BV4>0,IF(73<=Supuestos!$B$29,-PMT(Supuestos!$B$28/12,Supuestos!$B$29,Supuestos!$B$27),0),0) -> 0 | BW5: =IF(BW4>0,IF(74<=Supuestos!$B$29,-PMT(Supuestos!$B$28/12,Supuestos!$B$29,Supuestos!$B$27),0),0) -> 0 | BX5: =IF(BX4>0,IF(75<=Supuestos!$B$29,-PMT(Supuestos!$B$28/12,Supuestos!$B$29,Supuestos!$B$27),0),0) -> 0 | BY5: =IF(BY4>0,IF(76<=Supuestos!$B$29,-PMT(Supuestos!$B$28/12,Supuestos!$B$29,Supuestos!$B$27),0),0) -> 0 | BZ5: =IF(BZ4>0,IF(77<=Supuestos!$B$29,-PMT(Supuestos!$B$28/12,Supuestos!$B$29,Supuestos!$B$27),0),0) -> 0 | CA5: =IF(CA4>0,IF(78<=Supuestos!$B$29,-PMT(Supuestos!$B$28/12,Supuestos!$B$29,Supuestos!$B$27),0),0) -> 0 | CB5: =IF(CB4>0,IF(79<=Supuestos!$B$29,-PMT(Supuestos!$B$28/12,Supuestos!$B$29,Supuestos!$B$27),0),0) -> 0 | CC5: =IF(CC4>0,IF(80<=Supuestos!$B$29,-PMT(Supuestos!$B$28/12,Supuestos!$B$29,Supuestos!$B$27),0),0) -> 0 | CD5: =IF(CD4>0,IF(81<=Supuestos!$B$29,-PMT(Supuestos!$B$28/12,Supuestos!$B$29,Supuestos!$B$27),0),0) -> 0 | CE5: =IF(CE4>0,IF(82<=Supuestos!$B$29,-PMT(Supuestos!$B$28/12,Supuestos!$B$29,Supuestos!$B$27),0),0) -> 0 | CF5: =IF(CF4>0,IF(83<=Supuestos!$B$29,-PMT(Supuestos!$B$28/12,Supuestos!$B$29,Supuestos!$B$27),0),0) -> 0 | CG5: =IF(CG4>0,IF(84<=Supuestos!$B$29,-PMT(Supuestos!$B$28/12,Supuestos!$B$29,Supuestos!$B$27),0),0) -> 0 | CH5: =IF(CH4>0,IF(85<=Supuestos!$B$29,-PMT(Supuestos!$B$28/12,Supuestos!$B$29,Supuestos!$B$27),0),0) -> 0 | CI5: =IF(CI4>0,IF(86<=Supuestos!$B$29,-PMT(Supuestos!$B$28/12,Supuestos!$B$29,Supuestos!$B$27),0),0) -> 0 | CJ5: =IF(CJ4>0,IF(87<=Supuestos!$B$29,-PMT(Supuestos!$B$28/12,Supuestos!$B$29,Supuestos!$B$27),0),0) -> 0 | CK5: =IF(CK4>0,IF(88<=Supuestos!$B$29,-PMT(Supuestos!$B$28/12,Supuestos!$B$29,Supuestos!$B$27),0),0) -> 0 | CL5: =IF(CL4>0,IF(89<=Supuestos!$B$29,-PMT(Supuestos!$B$28/12,Supuestos!$B$29,Supuestos!$B$27),0),0) -> 0 | CM5: =IF(CM4>0,IF(90<=Supuestos!$B$29,-PMT(Supuestos!$B$28/12,Supuestos!$B$29,Supuestos!$B$27),0),0) -> 0 | CN5: =IF(CN4>0,IF(91<=Supuestos!$B$29,-PMT(Supuestos!$B$28/12,Supuestos!$B$29,Supuestos!$B$27),0),0) -> 0 | CO5: =IF(CO4>0,IF(92<=Supuestos!$B$29,-PMT(Supuestos!$B$28/12,Supuestos!$B$29,Supuestos!$B$27),0),0) -> 0 | CP5: =IF(CP4>0,IF(93<=Supuestos!$B$29,-PMT(Supuestos!$B$28/12,Supuestos!$B$29,Supuestos!$B$27),0),0) -> 0 | CQ5: =IF(CQ4>0,IF(94<=Supuestos!$B$29,-PMT(Supuestos!$B$28/12,Supuestos!$B$29,Supuestos!$B$27),0),0) -> 0 | CR5: =IF(CR4>0,IF(95<=Supuestos!$B$29,-PMT(Supuestos!$B$28/12,Supuestos!$B$29,Supuestos!$B$27),0),0) -> 0 | CS5: =IF(CS4>0,IF(96<=Supuestos!$B$29,-PMT(Supuestos!$B$28/12,Supuestos!$B$29,Supuestos!$B$27),0),0) -> 0 | CT5: =IF(CT4>0,IF(97<=Supuestos!$B$29,-PMT(Supuestos!$B$28/12,Supuestos!$B$29,Supuestos!$B$27),0),0) -> 0 | CU5: =IF(CU4>0,IF(98<=Supuestos!$B$29,-PMT(Supuestos!$B$28/12,Supuestos!$B$29,Supuestos!$B$27),0),0) -> 0 | CV5: =IF(CV4>0,IF(99<=Supuestos!$B$29,-PMT(Supuestos!$B$28/12,Supuestos!$B$29,Supuestos!$B$27),0),0) -> 0 | CW5: =IF(CW4>0,IF(100<=Supuestos!$B$29,-PMT(Supuestos!$B$28/12,Supuestos!$B$29,Supuestos!$B$27),0),0) -> 0 | CX5: =IF(CX4>0,IF(101<=Supuestos!$B$29,-PMT(Supuestos!$B$28/12,Supuestos!$B$29,Supuestos!$B$27),0),0) -> 0 | CY5: =IF(CY4>0,IF(102<=Supuestos!$B$29,-PMT(Supuestos!$B$28/12,Supuestos!$B$29,Supuestos!$B$27),0),0) -> 0 | CZ5: =IF(CZ4>0,IF(103<=Supuestos!$B$29,-PMT(Supuestos!$B$28/12,Supuestos!$B$29,Supuestos!$B$27),0),0) -> 0 | DA5: =IF(DA4>0,IF(104<=Supuestos!$B$29,-PMT(Supuestos!$B$28/12,Supuestos!$B$29,Supuestos!$B$27),0),0) -> 0 | DB5: =IF(DB4>0,IF(105<=Supuestos!$B$29,-PMT(Supuestos!$B$28/12,Supuestos!$B$29,Supuestos!$B$27),0),0) -> 0 | DC5: =IF(DC4>0,IF(106<=Supuestos!$B$29,-PMT(Supuestos!$B$28/12,Supuestos!$B$29,Supuestos!$B$27),0),0) -> 0 | DD5: =IF(DD4>0,IF(107<=Supuestos!$B$29,-PMT(Supuestos!$B$28/12,Supuestos!$B$29,Supuestos!$B$27),0),0) -> 0 | DE5: =IF(DE4>0,IF(108<=Supuestos!$B$29,-PMT(Supuestos!$B$28/12,Supuestos!$B$29,Supuestos!$B$27),0),0) -> 0 | DF5: =IF(DF4>0,IF(109<=Supuestos!$B$29,-PMT(Supuestos!$B$28/12,Supuestos!$B$29,Supuestos!$B$27),0),0) -> 0 | DG5: =IF(DG4>0,IF(110<=Supuestos!$B$29,-PMT(Supuestos!$B$28/12,Supuestos!$B$29,Supuestos!$B$27),0),0) -> 0 | DH5: =IF(DH4>0,IF(111<=Supuestos!$B$29,-PMT(Supuestos!$B$28/12,Supuestos!$B$29,Supuestos!$B$27),0),0) -> 0 | DI5: =IF(DI4>0,IF(112<=Supuestos!$B$29,-PMT(Supuestos!$B$28/12,Supuestos!$B$29,Supuestos!$B$27),0),0) -> 0 | DJ5: =IF(DJ4>0,IF(113<=Supuestos!$B$29,-PMT(Supuestos!$B$28/12,Supuestos!$B$29,Supuestos!$B$27),0),0) -> 0 | DK5: =IF(DK4>0,IF(114<=Supuestos!$B$29,-PMT(Supuestos!$B$28/12,Supuestos!$B$29,Supuestos!$B$27),0),0) -> 0 | DL5: =IF(DL4>0,IF(115<=Supuestos!$B$29,-PMT(Supuestos!$B$28/12,Supuestos!$B$29,Supuestos!$B$27),0),0) -> 0 | DM5: =IF(DM4>0,IF(116<=Supuestos!$B$29,-PMT(Supuestos!$B$28/12,Supuestos!$B$29,Supuestos!$B$27),0),0) -> 0 | DN5: =IF(DN4>0,IF(117<=Supuestos!$B$29,-PMT(Supuestos!$B$28/12,Supuestos!$B$29,Supuestos!$B$27),0),0) -> 0 | DO5: =IF(DO4>0,IF(118<=Supuestos!$B$29,-PMT(Supuestos!$B$28/12,Supuestos!$B$29,Supuestos!$B$27),0),0) -> 0 | DP5: =IF(DP4>0,IF(119<=Supuestos!$B$29,-PMT(Supuestos!$B$28/12,Supuestos!$B$29,Supuestos!$B$27),0),0) -> 0 | DQ5: =IF(DQ4>0,IF(120<=Supuestos!$B$29,-PMT(Supuestos!$B$28/12,Supuestos!$B$29,Supuestos!$B$27),0),0) -> 0 | DR5: =IF(DR4>0,IF(121<=Supuestos!$B$29,-PMT(Supuestos!$B$28/12,Supuestos!$B$29,Supuestos!$B$27),0),0) -> 0 | DS5: =IF(DS4>0,IF(122<=Supuestos!$B$29,-PMT(Supuestos!$B$28/12,Supuestos!$B$29,Supuestos!$B$27),0),0) -> 0 | DT5: =IF(DT4>0,IF(123<=Supuestos!$B$29,-PMT(Supuestos!$B$28/12,Supuestos!$B$29,Supuestos!$B$27),0),0) -> 0 | DU5: =IF(DU4>0,IF(124<=Supuestos!$B$29,-PMT(Supuestos!$B$28/12,Supuestos!$B$29,Supuestos!$B$27),0),0) -> 0 | DV5: =IF(DV4>0,IF(125<=Supuestos!$B$29,-PMT(Supuestos!$B$28/12,Supuestos!$B$29,Supuestos!$B$27),0),0) -> 0 | DW5: =IF(DW4>0,IF(126<=Supuestos!$B$29,-PMT(Supuestos!$B$28/12,Supuestos!$B$29,Supuestos!$B$27),0),0) -> 0 | DX5: =IF(DX4>0,IF(127<=Supuestos!$B$29,-PMT(Supuestos!$B$28/12,Supuestos!$B$29,Supuestos!$B$27),0),0) -> 0 | DY5: =IF(DY4>0,IF(128<=Supuestos!$B$29,-PMT(Supuestos!$B$28/12,Supuestos!$B$29,Supuestos!$B$27),0),0) -> 0 | DZ5: =IF(DZ4>0,IF(129<=Supuestos!$B$29,-PMT(Supuestos!$B$28/12,Supuestos!$B$29,Supuestos!$B$27),0),0) -> 0 | EA5: =IF(EA4>0,IF(130<=Supuestos!$B$29,-PMT(Supuestos!$B$28/12,Supuestos!$B$29,Supuestos!$B$27),0),0) -> 0 | EB5: =IF(EB4>0,IF(131<=Supuestos!$B$29,-PMT(Supuestos!$B$28/12,Supuestos!$B$29,Supuestos!$B$27),0),0) -> 0 | EC5: =IF(EC4>0,IF(132<=Supuestos!$B$29,-PMT(Supuestos!$B$28/12,Supuestos!$B$29,Supuestos!$B$27),0),0) -> 0 | ED5: =IF(ED4>0,IF(133<=Supuestos!$B$29,-PMT(Supuestos!$B$28/12,Supuestos!$B$29,Supuestos!$B$27),0),0) -> 0 | EE5: =IF(EE4>0,IF(134<=Supuestos!$B$29,-PMT(Supuestos!$B$28/12,Supuestos!$B$29,Supuestos!$B$27),0),0) -> 0 | EF5: =IF(EF4>0,IF(135<=Supuestos!$B$29,-PMT(Supuestos!$B$28/12,Supuestos!$B$29,Supuestos!$B$27),0),0) -> 0 | EG5: =IF(EG4>0,IF(136<=Supuestos!$B$29,-PMT(Supuestos!$B$28/12,Supuestos!$B$29,Supuestos!$B$27),0),0) -> 0 | EH5: =IF(EH4>0,IF(137<=Supuestos!$B$29,-PMT(Supuestos!$B$28/12,Supuestos!$B$29,Supuestos!$B$27),0),0) -> 0 | EI5: =IF(EI4>0,IF(138<=Supuestos!$B$29,-PMT(Supuestos!$B$28/12,Supuestos!$B$29,Supuestos!$B$27),0),0) -> 0 | EJ5: =IF(EJ4>0,IF(139<=Supuestos!$B$29,-PMT(Supuestos!$B$28/12,Supuestos!$B$29,Supuestos!$B$27),0),0) -> 0 | EK5: =IF(EK4>0,IF(140<=Supuestos!$B$29,-PMT(Supuestos!$B$28/12,Supuestos!$B$29,Supuestos!$B$27),0),0) -> 0 | EL5: =IF(EL4>0,IF(141<=Supuestos!$B$29,-PMT(Supuestos!$B$28/12,Supuestos!$B$29,Supuestos!$B$27),0),0) -> 0 | EM5: =IF(EM4>0,IF(142<=Supuestos!$B$29,-PMT(Supuestos!$B$28/12,Supuestos!$B$29,Supuestos!$B$27),0),0) -> 0 | EN5: =IF(EN4>0,IF(143<=Supuestos!$B$29,-PMT(Supuestos!$B$28/12,Supuestos!$B$29,Supuestos!$B$27),0),0) -> 0 | EO5: =IF(EO4>0,IF(144<=Supuestos!$B$29,-PMT(Supuestos!$B$28/12,Supuestos!$B$29,Supuestos!$B$27),0),0) -> 0 | EP5: =IF(EP4>0,IF(145<=Supuestos!$B$29,-PMT(Supuestos!$B$28/12,Supuestos!$B$29,Supuestos!$B$27),0),0) -> 0 | EQ5: =IF(EQ4>0,IF(146<=Supuestos!$B$29,-PMT(Supuestos!$B$28/12,Supuestos!$B$29,Supuestos!$B$27),0),0) -> 0 | ER5: =IF(ER4>0,IF(147<=Supuestos!$B$29,-PMT(Supuestos!$B$28/12,Supuestos!$B$29,Supuestos!$B$27),0),0) -> 0 | ES5: =IF(ES4>0,IF(148<=Supuestos!$B$29,-PMT(Supuestos!$B$28/12,Supuestos!$B$29,Supuestos!$B$27),0),0) -> 0 | ET5: =IF(ET4>0,IF(149<=Supuestos!$B$29,-PMT(Supuestos!$B$28/12,Supuestos!$B$29,Supuestos!$B$27),0),0) -> 0 | EU5: =IF(EU4>0,IF(150<=Supuestos!$B$29,-PMT(Supuestos!$B$28/12,Supuestos!$B$29,Supuestos!$B$27),0),0) -> 0 | EV5: =IF(EV4>0,IF(151<=Supuestos!$B$29,-PMT(Supuestos!$B$28/12,Supuestos!$B$29,Supuestos!$B$27),0),0) -> 0 | EW5: =IF(EW4>0,IF(152<=Supuestos!$B$29,-PMT(Supuestos!$B$28/12,Supuestos!$B$29,Supuestos!$B$27),0),0) -> 0 | EX5: =IF(EX4>0,IF(153<=Supuestos!$B$29,-PMT(Supuestos!$B$28/12,Supuestos!$B$29,Supuestos!$B$27),0),0) -> 0 | EY5: =IF(EY4>0,IF(154<=Supuestos!$B$29,-PMT(Supuestos!$B$28/12,Supuestos!$B$29,Supuestos!$B$27),0),0) -> 0 | EZ5: =IF(EZ4>0,IF(155<=Supuestos!$B$29,-PMT(Supuestos!$B$28/12,Supuestos!$B$29,Supuestos!$B$27),0),0) -> 0 | FA5: =IF(FA4>0,IF(156<=Supuestos!$B$29,-PMT(Supuestos!$B$28/12,Supuestos!$B$29,Supuestos!$B$27),0),0) -> 0 | FB5: =IF(FB4>0,IF(157<=Supuestos!$B$29,-PMT(Supuestos!$B$28/12,Supuestos!$B$29,Supuestos!$B$27),0),0) -> 0 | FC5: =IF(FC4>0,IF(158<=Supuestos!$B$29,-PMT(Supuestos!$B$28/12,Supuestos!$B$29,Supuestos!$B$27),0),0) -> 0 | FD5: =IF(FD4>0,IF(159<=Supuestos!$B$29,-PMT(Supuestos!$B$28/12,Supuestos!$B$29,Supuestos!$B$27),0),0) -> 0 | FE5: =IF(FE4>0,IF(160<=Supuestos!$B$29,-PMT(Supuestos!$B$28/12,Supuestos!$B$29,Supuestos!$B$27),0),0) -> 0 | FF5: =IF(FF4>0,IF(161<=Supuestos!$B$29,-PMT(Supuestos!$B$28/12,Supuestos!$B$29,Supuestos!$B$27),0),0) -> 0 | FG5: =IF(FG4>0,IF(162<=Supuestos!$B$29,-PMT(Supuestos!$B$28/12,Supuestos!$B$29,Supuestos!$B$27),0),0) -> 0 | FH5: =IF(FH4>0,IF(163<=Supuestos!$B$29,-PMT(Supuestos!$B$28/12,Supuestos!$B$29,Supuestos!$B$27),0),0) -> 0 | FI5: =IF(FI4>0,IF(164<=Supuestos!$B$29,-PMT(Supuestos!$B$28/12,Supuestos!$B$29,Supuestos!$B$27),0),0) -> 0 | FJ5: =IF(FJ4>0,IF(165<=Supuestos!$B$29,-PMT(Supuestos!$B$28/12,Supuestos!$B$29,Supuestos!$B$27),0),0) -> 0 | FK5: =IF(FK4>0,IF(166<=Supuestos!$B$29,-PMT(Supuestos!$B$28/12,Supuestos!$B$29,Supuestos!$B$27),0),0) -> 0 | FL5: =IF(FL4>0,IF(167<=Supuestos!$B$29,-PMT(Supuestos!$B$28/12,Supuestos!$B$29,Supuestos!$B$27),0),0) -> 0 | FM5: =IF(FM4>0,IF(168<=Supuestos!$B$29,-PMT(Supuestos!$B$28/12,Supuestos!$B$29,Supuestos!$B$27),0),0) -> 0 | FN5: =IF(FN4>0,IF(169<=Supuestos!$B$29,-PMT(Supuestos!$B$28/12,Supuestos!$B$29,Supuestos!$B$27),0),0) -> 0 | FO5: =IF(FO4>0,IF(170<=Supuestos!$B$29,-PMT(Supuestos!$B$28/12,Supuestos!$B$29,Supuestos!$B$27),0),0) -> 0 | FP5: =IF(FP4>0,IF(171<=Supuestos!$B$29,-PMT(Supuestos!$B$28/12,Supuestos!$B$29,Supuestos!$B$27),0),0) -> 0 | FQ5: =IF(FQ4>0,IF(172<=Supuestos!$B$29,-PMT(Supuestos!$B$28/12,Supuestos!$B$29,Supuestos!$B$27),0),0) -> 0 | FR5: =IF(FR4>0,IF(173<=Supuestos!$B$29,-PMT(Supuestos!$B$28/12,Supuestos!$B$29,Supuestos!$B$27),0),0) -> 0 | FS5: =IF(FS4>0,IF(174<=Supuestos!$B$29,-PMT(Supuestos!$B$28/12,Supuestos!$B$29,Supuestos!$B$27),0),0) -> 0 | FT5: =IF(FT4>0,IF(175<=Supuestos!$B$29,-PMT(Supuestos!$B$28/12,Supuestos!$B$29,Supuestos!$B$27),0),0) -> 0 | FU5: =IF(FU4>0,IF(176<=Supuestos!$B$29,-PMT(Supuestos!$B$28/12,Supuestos!$B$29,Supuestos!$B$27),0),0) -> 0 | FV5: =IF(FV4>0,IF(177<=Supuestos!$B$29,-PMT(Supuestos!$B$28/12,Supuestos!$B$29,Supuestos!$B$27),0),0) -> 0 | FW5: =IF(FW4>0,IF(178<=Supuestos!$B$29,-PMT(Supuestos!$B$28/12,Supuestos!$B$29,Supuestos!$B$27),0),0) -> 0 | FX5: =IF(FX4>0,IF(179<=Supuestos!$B$29,-PMT(Supuestos!$B$28/12,Supuestos!$B$29,Supuestos!$B$27),0),0) -> 0 | FY5: =IF(FY4>0,IF(180<=Supuestos!$B$29,-PMT(Supuestos!$B$28/12,Supuestos!$B$29,Supuestos!$B$27),0),0) -> 0 | FZ5: =IF(FZ4>0,IF(181<=Supuestos!$B$29,-PMT(Supuestos!$B$28/12,Supuestos!$B$29,Supuestos!$B$27),0),0) -> 0 | GA5: =IF(GA4>0,IF(182<=Supuestos!$B$29,-PMT(Supuestos!$B$28/12,Supuestos!$B$29,Supuestos!$B$27),0),0) -> 0 | GB5: =IF(GB4>0,IF(183<=Supuestos!$B$29,-PMT(Supuestos!$B$28/12,Supuestos!$B$29,Supuestos!$B$27),0),0) -> 0 | GC5: =IF(GC4>0,IF(184<=Supuestos!$B$29,-PMT(Supuestos!$B$28/12,Supuestos!$B$29,Supuestos!$B$27),0),0) -> 0 | GD5: =IF(GD4>0,IF(185<=Supuestos!$B$29,-PMT(Supuestos!$B$28/12,Supuestos!$B$29,Supuestos!$B$27),0),0) -> 0 | GE5: =IF(GE4>0,IF(186<=Supuestos!$B$29,-PMT(Supuestos!$B$28/12,Supuestos!$B$29,Supuestos!$B$27),0),0) -> 0 | GF5: =IF(GF4>0,IF(187<=Supuestos!$B$29,-PMT(Supuestos!$B$28/12,Supuestos!$B$29,Supuestos!$B$27),0),0) -> 0 | GG5: =IF(GG4>0,IF(188<=Supuestos!$B$29,-PMT(Supuestos!$B$28/12,Supuestos!$B$29,Supuestos!$B$27),0),0) -> 0 | GH5: =IF(GH4>0,IF(189<=Supuestos!$B$29,-PMT(Supuestos!$B$28/12,Supuestos!$B$29,Supuestos!$B$27),0),0) -> 0 | GI5: =IF(GI4>0,IF(190<=Supuestos!$B$29,-PMT(Supuestos!$B$28/12,Supuestos!$B$29,Supuestos!$B$27),0),0) -> 0 | GJ5: =IF(GJ4>0,IF(191<=Supuestos!$B$29,-PMT(Supuestos!$B$28/12,Supuestos!$B$29,Supuestos!$B$27),0),0) -> 0 | GK5: =IF(GK4>0,IF(192<=Supuestos!$B$29,-PMT(Supuestos!$B$28/12,Supuestos!$B$29,Supuestos!$B$27),0),0) -> 0 | GL5: =IF(GL4>0,IF(193<=Supuestos!$B$29,-PMT(Supuestos!$B$28/12,Supuestos!$B$29,Supuestos!$B$27),0),0) -> 0 | GM5: =IF(GM4>0,IF(194<=Supuestos!$B$29,-PMT(Supuestos!$B$28/12,Supuestos!$B$29,Supuestos!$B$27),0),0) -> 0 | GN5: =IF(GN4>0,IF(195<=Supuestos!$B$29,-PMT(Supuestos!$B$28/12,Supuestos!$B$29,Supuestos!$B$27),0),0) -> 0 | GO5: =IF(GO4>0,IF(196<=Supuestos!$B$29,-PMT(Supuestos!$B$28/12,Supuestos!$B$29,Supuestos!$B$27),0),0) -> 0 | GP5: =IF(GP4>0,IF(197<=Supuestos!$B$29,-PMT(Supuestos!$B$28/12,Supuestos!$B$29,Supuestos!$B$27),0),0) -> 0 | GQ5: =IF(GQ4>0,IF(198<=Supuestos!$B$29,-PMT(Supuestos!$B$28/12,Supuestos!$B$29,Supuestos!$B$27),0),0) -> 0 | GR5: =IF(GR4>0,IF(199<=Supuestos!$B$29,-PMT(Supuestos!$B$28/12,Supuestos!$B$29,Supuestos!$B$27),0),0) -> 0 | GS5: =IF(GS4>0,IF(200<=Supuestos!$B$29,-PMT(Supuestos!$B$28/12,Supuestos!$B$29,Supuestos!$B$27),0),0) -> 0 | GT5: =IF(GT4>0,IF(201<=Supuestos!$B$29,-PMT(Supuestos!$B$28/12,Supuestos!$B$29,Supuestos!$B$27),0),0) -> 0 | GU5: =IF(GU4>0,IF(202<=Supuestos!$B$29,-PMT(Supuestos!$B$28/12,Supuestos!$B$29,Supuestos!$B$27),0),0) -> 0 | GV5: =IF(GV4>0,IF(203<=Supuestos!$B$29,-PMT(Supuestos!$B$28/12,Supuestos!$B$29,Supuestos!$B$27),0),0) -> 0 | GW5: =IF(GW4>0,IF(204<=Supuestos!$B$29,-PMT(Supuestos!$B$28/12,Supuestos!$B$29,Supuestos!$B$27),0),0) -> 0 | GX5: =IF(GX4>0,IF(205<=Supuestos!$B$29,-PMT(Supuestos!$B$28/12,Supuestos!$B$29,Supuestos!$B$27),0),0) -> 0 | GY5: =IF(GY4>0,IF(206<=Supuestos!$B$29,-PMT(Supuestos!$B$28/12,Supuestos!$B$29,Supuestos!$B$27),0),0) -> 0 | GZ5: =IF(GZ4>0,IF(207<=Supuestos!$B$29,-PMT(Supuestos!$B$28/12,Supuestos!$B$29,Supuestos!$B$27),0),0) -> 0 | HA5: =IF(HA4>0,IF(208<=Supuestos!$B$29,-PMT(Supuestos!$B$28/12,Supuestos!$B$29,Supuestos!$B$27),0),0) -> 0 | HB5: =IF(HB4>0,IF(209<=Supuestos!$B$29,-PMT(Supuestos!$B$28/12,Supuestos!$B$29,Supuestos!$B$27),0),0) -> 0 | HC5: =IF(HC4>0,IF(210<=Supuestos!$B$29,-PMT(Supuestos!$B$28/12,Supuestos!$B$29,Supuestos!$B$27),0),0) -> 0 | HD5: =IF(HD4>0,IF(211<=Supuestos!$B$29,-PMT(Supuestos!$B$28/12,Supuestos!$B$29,Supuestos!$B$27),0),0) -> 0 | HE5: =IF(HE4>0,IF(212<=Supuestos!$B$29,-PMT(Supuestos!$B$28/12,Supuestos!$B$29,Supuestos!$B$27),0),0) -> 0 | HF5: =IF(HF4>0,IF(213<=Supuestos!$B$29,-PMT(Supuestos!$B$28/12,Supuestos!$B$29,Supuestos!$B$27),0),0) -> 0 | HG5: =IF(HG4>0,IF(214<=Supuestos!$B$29,-PMT(Supuestos!$B$28/12,Supuestos!$B$29,Supuestos!$B$27),0),0) -> 0 | HH5: =IF(HH4>0,IF(215<=Supuestos!$B$29,-PMT(Supuestos!$B$28/12,Supuestos!$B$29,Supuestos!$B$27),0),0) -> 0 | HI5: =IF(HI4>0,IF(216<=Supuestos!$B$29,-PMT(Supuestos!$B$28/12,Supuestos!$B$29,Supuestos!$B$27),0),0) -> 0 | HJ5: =IF(HJ4>0,IF(217<=Supuestos!$B$29,-PMT(Supuestos!$B$28/12,Supuestos!$B$29,Supuestos!$B$27),0),0) -> 0 | HK5: =IF(HK4>0,IF(218<=Supuestos!$B$29,-PMT(Supuestos!$B$28/12,Supuestos!$B$29,Supuestos!$B$27),0),0) -> 0 | HL5: =IF(HL4>0,IF(219<=Supuestos!$B$29,-PMT(Supuestos!$B$28/12,Supuestos!$B$29,Supuestos!$B$27),0),0) -> 0 | HM5: =IF(HM4>0,IF(220<=Supuestos!$B$29,-PMT(Supuestos!$B$28/12,Supuestos!$B$29,Supuestos!$B$27),0),0) -> 0 | HN5: =IF(HN4>0,IF(221<=Supuestos!$B$29,-PMT(Supuestos!$B$28/12,Supuestos!$B$29,Supuestos!$B$27),0),0) -> 0 | HO5: =IF(HO4>0,IF(222<=Supuestos!$B$29,-PMT(Supuestos!$B$28/12,Supuestos!$B$29,Supuestos!$B$27),0),0) -> 0 | HP5: =IF(HP4>0,IF(223<=Supuestos!$B$29,-PMT(Supuestos!$B$28/12,Supuestos!$B$29,Supuestos!$B$27),0),0) -> 0 | HQ5: =IF(HQ4>0,IF(224<=Supuestos!$B$29,-PMT(Supuestos!$B$28/12,Supuestos!$B$29,Supuestos!$B$27),0),0) -> 0 | HR5: =IF(HR4>0,IF(225<=Supuestos!$B$29,-PMT(Supuestos!$B$28/12,Supuestos!$B$29,Supuestos!$B$27),0),0) -> 0 | HS5: =IF(HS4>0,IF(226<=Supuestos!$B$29,-PMT(Supuestos!$B$28/12,Supuestos!$B$29,Supuestos!$B$27),0),0) -> 0 | HT5: =IF(HT4>0,IF(227<=Supuestos!$B$29,-PMT(Supuestos!$B$28/12,Supuestos!$B$29,Supuestos!$B$27),0),0) -> 0 | HU5: =IF(HU4>0,IF(228<=Supuestos!$B$29,-PMT(Supuestos!$B$28/12,Supuestos!$B$29,Supuestos!$B$27),0),0) -> 0 | HV5: =IF(HV4>0,IF(229<=Supuestos!$B$29,-PMT(Supuestos!$B$28/12,Supuestos!$B$29,Supuestos!$B$27),0),0) -> 0 | HW5: =IF(HW4>0,IF(230<=Supuestos!$B$29,-PMT(Supuestos!$B$28/12,Supuestos!$B$29,Supuestos!$B$27),0),0) -> 0 | HX5: =IF(HX4>0,IF(231<=Supuestos!$B$29,-PMT(Supuestos!$B$28/12,Supuestos!$B$29,Supuestos!$B$27),0),0) -> 0 | HY5: =IF(HY4>0,IF(232<=Supuestos!$B$29,-PMT(Supuestos!$B$28/12,Supuestos!$B$29,Supuestos!$B$27),0),0) -> 0 | HZ5: =IF(HZ4>0,IF(233<=Supuestos!$B$29,-PMT(Supuestos!$B$28/12,Supuestos!$B$29,Supuestos!$B$27),0),0) -> 0 | IA5: =IF(IA4>0,IF(234<=Supuestos!$B$29,-PMT(Supuestos!$B$28/12,Supuestos!$B$29,Supuestos!$B$27),0),0) -> 0 | IB5: =IF(IB4>0,IF(235<=Supuestos!$B$29,-PMT(Supuestos!$B$28/12,Supuestos!$B$29,Supuestos!$B$27),0),0) -> 0 | IC5: =IF(IC4>0,IF(236<=Supuestos!$B$29,-PMT(Supuestos!$B$28/12,Supuestos!$B$29,Supuestos!$B$27),0),0) -> 0 | ID5: =IF(ID4>0,IF(237<=Supuestos!$B$29,-PMT(Supuestos!$B$28/12,Supuestos!$B$29,Supuestos!$B$27),0),0) -> 0 | IE5: =IF(IE4>0,IF(238<=Supuestos!$B$29,-PMT(Supuestos!$B$28/12,Supuestos!$B$29,Supuestos!$B$27),0),0) -> 0 | IF5: =IF(IF4>0,IF(239<=Supuestos!$B$29,-PMT(Supuestos!$B$28/12,Supuestos!$B$29,Supuestos!$B$27),0),0) -> 0 | IG5: =IF(IG4>0,IF(240<=Supuestos!$B$29,-PMT(Supuestos!$B$28/12,Supuestos!$B$29,Supuestos!$B$27),0),0) -> 0 | IH5: =IF(IH4>0,IF(241<=Supuestos!$B$29,-PMT(Supuestos!$B$28/12,Supuestos!$B$29,Supuestos!$B$27),0),0) -> 0 | II5: =IF(II4>0,IF(242<=Supuestos!$B$29,-PMT(Supuestos!$B$28/12,Supuestos!$B$29,Supuestos!$B$27),0),0) -> 0 | IJ5: =IF(IJ4>0,IF(243<=Supuestos!$B$29,-PMT(Supuestos!$B$28/12,Supuestos!$B$29,Supuestos!$B$27),0),0) -> 0 | IK5: =IF(IK4>0,IF(244<=Supuestos!$B$29,-PMT(Supuestos!$B$28/12,Supuestos!$B$29,Supuestos!$B$27),0),0) -> 0 | IL5: =IF(IL4>0,IF(245<=Supuestos!$B$29,-PMT(Supuestos!$B$28/12,Supuestos!$B$29,Supuestos!$B$27),0),0) -> 0 | IM5: =IF(IM4>0,IF(246<=Supuestos!$B$29,-PMT(Supuestos!$B$28/12,Supuestos!$B$29,Supuestos!$B$27),0),0) -> 0 | IN5: =IF(IN4>0,IF(247<=Supuestos!$B$29,-PMT(Supuestos!$B$28/12,Supuestos!$B$29,Supuestos!$B$27),0),0) -> 0 | IO5: =IF(IO4>0,IF(248<=Supuestos!$B$29,-PMT(Supuestos!$B$28/12,Supuestos!$B$29,Supuestos!$B$27),0),0) -> 0 | IP5: =IF(IP4>0,IF(249<=Supuestos!$B$29,-PMT(Supuestos!$B$28/12,Supuestos!$B$29,Supuestos!$B$27),0),0) -> 0 | IQ5: =IF(IQ4>0,IF(250<=Supuestos!$B$29,-PMT(Supuestos!$B$28/12,Supuestos!$B$29,Supuestos!$B$27),0),0) -> 0 | IR5: =IF(IR4>0,IF(251<=Supuestos!$B$29,-PMT(Supuestos!$B$28/12,Supuestos!$B$29,Supuestos!$B$27),0),0) -> 0 | IS5: =IF(IS4>0,IF(252<=Supuestos!$B$29,-PMT(Supuestos!$B$28/12,Supuestos!$B$29,Supuestos!$B$27),0),0) -> 0 | IT5: =IF(IT4>0,IF(253<=Supuestos!$B$29,-PMT(Supuestos!$B$28/12,Supuestos!$B$29,Supuestos!$B$27),0),0) -> 0 | IU5: =IF(IU4>0,IF(254<=Supuestos!$B$29,-PMT(Supuestos!$B$28/12,Supuestos!$B$29,Supuestos!$B$27),0),0) -> 0 | IV5: =IF(IV4>0,IF(255<=Supuestos!$B$29,-PMT(Supuestos!$B$28/12,Supuestos!$B$29,Supuestos!$B$27),0),0) -> 0 | IW5: =IF(IW4>0,IF(256<=Supuestos!$B$29,-PMT(Supuestos!$B$28/12,Supuestos!$B$29,Supuestos!$B$27),0),0) -> 0 | IX5: =IF(IX4>0,IF(257<=Supuestos!$B$29,-PMT(Supuestos!$B$28/12,Supuestos!$B$29,Supuestos!$B$27),0),0) -> 0 | IY5: =IF(IY4>0,IF(258<=Supuestos!$B$29,-PMT(Supuestos!$B$28/12,Supuestos!$B$29,Supuestos!$B$27),0),0) -> 0 | IZ5: =IF(IZ4>0,IF(259<=Supuestos!$B$29,-PMT(Supuestos!$B$28/12,Supuestos!$B$29,Supuestos!$B$27),0),0) -> 0 | JA5: =IF(JA4>0,IF(260<=Supuestos!$B$29,-PMT(Supuestos!$B$28/12,Supuestos!$B$29,Supuestos!$B$27),0),0) -> 0 | JB5: =IF(JB4>0,IF(261<=Supuestos!$B$29,-PMT(Supuestos!$B$28/12,Supuestos!$B$29,Supuestos!$B$27),0),0) -> 0 | JC5: =IF(JC4>0,IF(262<=Supuestos!$B$29,-PMT(Supuestos!$B$28/12,Supuestos!$B$29,Supuestos!$B$27),0),0) -> 0 | JD5: =IF(JD4>0,IF(263<=Supuestos!$B$29,-PMT(Supuestos!$B$28/12,Supuestos!$B$29,Supuestos!$B$27),0),0) -> 0 | JE5: =IF(JE4>0,IF(264<=Supuestos!$B$29,-PMT(Supuestos!$B$28/12,Supuestos!$B$29,Supuestos!$B$27),0),0) -> 0 | JF5: =IF(JF4>0,IF(265<=Supuestos!$B$29,-PMT(Supuestos!$B$28/12,Supuestos!$B$29,Supuestos!$B$27),0),0) -> 0 | JG5: =IF(JG4>0,IF(266<=Supuestos!$B$29,-PMT(Supuestos!$B$28/12,Supuestos!$B$29,Supuestos!$B$27),0),0) -> 0 | JH5: =IF(JH4>0,IF(267<=Supuestos!$B$29,-PMT(Supuestos!$B$28/12,Supuestos!$B$29,Supuestos!$B$27),0),0) -> 0 | JI5: =IF(JI4>0,IF(268<=Supuestos!$B$29,-PMT(Supuestos!$B$28/12,Supuestos!$B$29,Supuestos!$B$27),0),0) -> 0 | JJ5: =IF(JJ4>0,IF(269<=Supuestos!$B$29,-PMT(Supuestos!$B$28/12,Supuestos!$B$29,Supuestos!$B$27),0),0) -> 0 | JK5: =IF(JK4>0,IF(270<=Supuestos!$B$29,-PMT(Supuestos!$B$28/12,Supuestos!$B$29,Supuestos!$B$27),0),0) -> 0 | JL5: =IF(JL4>0,IF(271<=Supuestos!$B$29,-PMT(Supuestos!$B$28/12,Supuestos!$B$29,Supuestos!$B$27),0),0) -> 0 | JM5: =IF(JM4>0,IF(272<=Supuestos!$B$29,-PMT(Supuestos!$B$28/12,Supuestos!$B$29,Supuestos!$B$27),0),0) -> 0 | JN5: =IF(JN4>0,IF(273<=Supuestos!$B$29,-PMT(Supuestos!$B$28/12,Supuestos!$B$29,Supuestos!$B$27),0),0) -> 0 | JO5: =IF(JO4>0,IF(274<=Supuestos!$B$29,-PMT(Supuestos!$B$28/12,Supuestos!$B$29,Supuestos!$B$27),0),0) -> 0 | JP5: =IF(JP4>0,IF(275<=Supuestos!$B$29,-PMT(Supuestos!$B$28/12,Supuestos!$B$29,Supuestos!$B$27),0),0) -> 0 | JQ5: =IF(JQ4>0,IF(276<=Supuestos!$B$29,-PMT(Supuestos!$B$28/12,Supuestos!$B$29,Supuestos!$B$27),0),0) -> 0 | JR5: =IF(JR4>0,IF(277<=Supuestos!$B$29,-PMT(Supuestos!$B$28/12,Supuestos!$B$29,Supuestos!$B$27),0),0) -> 0 | JS5: =IF(JS4>0,IF(278<=Supuestos!$B$29,-PMT(Supuestos!$B$28/12,Supuestos!$B$29,Supuestos!$B$27),0),0) -> 0 | JT5: =IF(JT4>0,IF(279<=Supuestos!$B$29,-PMT(Supuestos!$B$28/12,Supuestos!$B$29,Supuestos!$B$27),0),0) -> 0 | JU5: =IF(JU4>0,IF(280<=Supuestos!$B$29,-PMT(Supuestos!$B$28/12,Supuestos!$B$29,Supuestos!$B$27),0),0) -> 0 | JV5: =IF(JV4>0,IF(281<=Supuestos!$B$29,-PMT(Supuestos!$B$28/12,Supuestos!$B$29,Supuestos!$B$27),0),0) -> 0 | JW5: =IF(JW4>0,IF(282<=Supuestos!$B$29,-PMT(Supuestos!$B$28/12,Supuestos!$B$29,Supuestos!$B$27),0),0) -> 0 | JX5: =IF(JX4>0,IF(283<=Supuestos!$B$29,-PMT(Supuestos!$B$28/12,Supuestos!$B$29,Supuestos!$B$27),0),0) -> 0 | JY5: =IF(JY4>0,IF(284<=Supuestos!$B$29,-PMT(Supuestos!$B$28/12,Supuestos!$B$29,Supuestos!$B$27),0),0) -> 0 | JZ5: =IF(JZ4>0,IF(285<=Supuestos!$B$29,-PMT(Supuestos!$B$28/12,Supuestos!$B$29,Supuestos!$B$27),0),0) -> 0 | KA5: =IF(KA4>0,IF(286<=Supuestos!$B$29,-PMT(Supuestos!$B$28/12,Supuestos!$B$29,Supuestos!$B$27),0),0) -> 0 | KB5: =IF(KB4>0,IF(287<=Supuestos!$B$29,-PMT(Supuestos!$B$28/12,Supuestos!$B$29,Supuestos!$B$27),0),0) -> 0 | KC5: =IF(KC4>0,IF(288<=Supuestos!$B$29,-PMT(Supuestos!$B$28/12,Supuestos!$B$29,Supuestos!$B$27),0),0) -> 0 | KD5: =IF(KD4>0,IF(289<=Supuestos!$B$29,-PMT(Supuestos!$B$28/12,Supuestos!$B$29,Supuestos!$B$27),0),0) -> 0 | KE5: =IF(KE4>0,IF(290<=Supuestos!$B$29,-PMT(Supuestos!$B$28/12,Supuestos!$B$29,Supuestos!$B$27),0),0) -> 0 | KF5: =IF(KF4>0,IF(291<=Supuestos!$B$29,-PMT(Supuestos!$B$28/12,Supuestos!$B$29,Supuestos!$B$27),0),0) -> 0 | KG5: =IF(KG4>0,IF(292<=Supuestos!$B$29,-PMT(Supuestos!$B$28/12,Supuestos!$B$29,Supuestos!$B$27),0),0) -> 0 | KH5: =IF(KH4>0,IF(293<=Supuestos!$B$29,-PMT(Supuestos!$B$28/12,Supuestos!$B$29,Supuestos!$B$27),0),0) -> 0 | KI5: =IF(KI4>0,IF(294<=Supuestos!$B$29,-PMT(Supuestos!$B$28/12,Supuestos!$B$29,Supuestos!$B$27),0),0) -> 0 | KJ5: =IF(KJ4>0,IF(295<=Supuestos!$B$29,-PMT(Supuestos!$B$28/12,Supuestos!$B$29,Supuestos!$B$27),0),0) -> 0 | KK5: =IF(KK4>0,IF(296<=Supuestos!$B$29,-PMT(Supuestos!$B$28/12,Supuestos!$B$29,Supuestos!$B$27),0),0) -> 0 | KL5: =IF(KL4>0,IF(297<=Supuestos!$B$29,-PMT(Supuestos!$B$28/12,Supuestos!$B$29,Supuestos!$B$27),0),0) -> 0 | KM5: =IF(KM4>0,IF(298<=Supuestos!$B$29,-PMT(Supuestos!$B$28/12,Supuestos!$B$29,Supuestos!$B$27),0),0) -> 0 | KN5: =IF(KN4>0,IF(299<=Supuestos!$B$29,-PMT(Supuestos!$B$28/12,Supuestos!$B$29,Supuestos!$B$27),0),0) -> 0 | KO5: =IF(KO4>0,IF(300<=Supuestos!$B$29,-PMT(Supuestos!$B$28/12,Supuestos!$B$29,Supuestos!$B$27),0),0) -> 0
A6: Intereses | B6: =B4*Supuestos!$B$28/12 -> 23333.333 | C6: =C4*Supuestos!$B$28/12 -> 23007.416 | D6: =D4*Supuestos!$B$28/12 -> 22679.598 | E6: =E4*Supuestos!$B$28/12 -> 22349.868 | F6: =F4*Supuestos!$B$28/12 -> 22018.214 | G6: =G4*Supuestos!$B$28/12 -> 21684.626 | H6: =H4*Supuestos!$B$28/12 -> 21349.092 | I6: =I4*Supuestos!$B$28/12 -> 21011.6 | ... KO6: =KO4*Supuestos!$B$28/12 -> 1.3292948e-10
A7: Saldo Final | B7: =B4+B6-B5 -> 3944128.5 | C7: =C4+C6-C5 -> 3887931.2 | D7: =D4+D6-D5 -> 3831406 | E7: =E4+E6-E5 -> 3774551 | F7: =F4+F6-F5 -> 3717364.5 | G7: =G4+G6-G5 -> 3659844.3 | H7: =H4+H6-H5 -> 3601988.6 | I7: =I4+I6-I5 -> 3543795.4 | ... KO7: =KO4+KO6-KO5 -> 2.292084e-08
A8: Amortización de Capital | B8: =B5-B6 -> 55871.461 | C8: =C5-C6 -> 56197.378 | D8: =D5-D6 -> 56525.196 | E8: =E5-E6 -> 56854.926 | F8: =F5-F6 -> 57186.58 | G8: =G5-G6 -> 57520.168 | H8: =H5-H6 -> 57855.702 | I8: =I5-I6 -> 58193.194 | ... KO8: =KO5-KO6 -> -1.3292948e-10

Sheet Flujo de Caja
A1: FLUJO DE CAJA LIBRE
A3: Concepto | B3: Mes 0 | C3: Mes 1 | D3: Mes 2 | E3: Mes 3 | F3: Mes 4 | G3: Mes 5 | H3: Mes 6 | I3: Mes 7 | J3: Mes 8 | K3: Mes 9 | L3: Mes 10 | M3: Mes 11 | N3: Mes 12 | O3: Mes 13 | P3: Mes 14 | Q3: Mes 15 | R3: Mes 16 | S3: Mes 17 | T3: Mes 18 | U3: Mes 19 | V3: Mes 20 | W3: Mes 21 | X3: Mes 22 | Y3: Mes 23 | Z3: Mes 24 | AA3: Mes 25 | AB3: Mes 26 | AC3: Mes 27 | AD3: Mes 28 | AE3: Mes 29 | AF3: Mes 30 | AG3: Mes 31 | AH3: Mes 32 | AI3: Mes 33 | AJ3: Mes 34 | AK3: Mes 35 | AL3: Mes 36 | AM3: Mes 37 | AN3: Mes 38 | AO3: Mes 39 | AP3: Mes 40 | AQ3: Mes 41 | AR3: Mes 42 | AS3: Mes 43 | AT3: Mes 44 | AU3: Mes 45 | AV3: Mes 46 | AW3: Mes 47 | AX3: Mes 48 | AY3: Mes 49 | AZ3: Mes 50 | BA3: Mes 51 | BB3: Mes 52 | BC3: Mes 53 | BD3: Mes 54 | BE3: Mes 55 | BF3: Mes 56 | BG3: Mes 57 | BH3: Mes 58 | BI3: Mes 59 | BJ3: Mes 60 | BK3: Mes 61 | BL3: Mes 62 | BM3: Mes 63 | BN3: Mes 64 | BO3: Mes 65 | BP3: Mes 66 | BQ3: Mes 67 | BR3: Mes 68 | BS3: Mes 69 | BT3: Mes 70 | BU3: Mes 71 | BV3: Mes 72 | BW3: Mes 73 | BX3: Mes 74 | BY3: Mes 75 | BZ3: Mes 76 | CA3: Mes 77 | CB3: Mes 78 | CC3: Mes 79 | CD3: Mes 80 | CE3: Mes 81 | CF3: Mes 82 | CG3: Mes 83 | CH3: Mes 84 | CI3: Mes 85 | CJ3: Mes 86 | CK3: Mes 87 | CL3: Mes 88 | CM3: Mes 89 | CN3: Mes 90 | CO3: Mes 91 | CP3: Mes 92 | CQ3: Mes 93 | CR3: Mes 94 | CS3: Mes 95 | CT3: Mes 96 | CU3: Mes 97 | CV3: Mes 98 | CW3: Mes 99 | CX3: Mes 100 | CY3: Mes 101 | CZ3: Mes 102 | DA3: Mes 103 | DB3: Mes 104 | DC3: Mes 105 | DD3: Mes 106 | DE3: Mes 107 | DF3: Mes 108 | DG3: Mes 109 | DH3: Mes 110 | DI3: Mes 111 | DJ3: Mes 112 | DK3: Mes 113 | DL3: Mes 114 | DM3: Mes 115 | DN3: Mes 116 | DO3: Mes 117 | DP3: Mes 118 | DQ3: Mes 119 | DR3: Mes 120 | DS3: Mes 121 | DT3: Mes 122 | DU3: Mes 123 | DV3: Mes 124 | DW3: Mes 125 | DX3: Mes 126 | DY3: Mes 127 | DZ3: Mes 128 | EA3: Mes 129 | EB3: Mes 130 | EC3: Mes 131 | ED3: Mes 132 | EE3: Mes 133 | EF3: Mes 134 | EG3: Mes 135 | EH3: Mes 136 | EI3: Mes 137 | EJ3: Mes 138 | EK3: Mes 139 | EL3: Mes 140 | EM3: Mes 141 | EN3: Mes 142 | EO3: Mes 143 | EP3: Mes 144 | EQ3: Mes 145 | ER3: Mes 146 | ES3: Mes 147 | ET3: Mes 148 | EU3: Mes 149 | EV3: Mes 150 | EW3: Mes 151 | EX3: Mes 152 | EY3: Mes 153 | EZ3: Mes 154 | FA3: Mes 155 | FB3: Mes 156 | FC3: Mes 157 | FD3: Mes 158 | FE3: Mes 159 | FF3: Mes 160 | FG3: Mes 161 | FH3: Mes 162 | FI3: Mes 163 | FJ3: Mes 164 | FK3: Mes 165 | FL3: Mes 166 | FM3: Mes 167 | FN3: Mes 168 | FO3: Mes 169 | FP3: Mes 170 | FQ3: Mes 171 | FR3: Mes 172 | FS3: Mes 173 | FT3: Mes 174 | FU3: Mes 175 | FV3: Mes 176 | FW3: Mes 177 | FX3: Mes 178 | FY3: Mes 179 | FZ3: Mes 180 | GA3: Mes 181 | GB3: Mes 182 | GC3: Mes 183 | GD3: Mes 184 | GE3: Mes 185 | GF3: Mes 186 | GG3: Mes 187 | GH3: Mes 188 | GI3: Mes 189 | GJ3: Mes 190 | GK3: Mes 191 | GL3: Mes 192 | GM3: Mes 193 | GN3: Mes 194 | GO3: Mes 195 | GP3: Mes 196 | GQ3: Mes 197 | GR3: Mes 198 | GS3: Mes 199 | GT3: Mes 200 | GU3: Mes 201 | GV3: Mes 202 | GW3: Mes 203 | GX3: Mes 204 | GY3: Mes 205 | GZ3: Mes 206 | HA3: Mes 207 | HB3: Mes 208 | HC3: Mes 209 | HD3: Mes 210 | HE3: Mes 211 | HF3: Mes 212 | HG3: Mes 213 | HH3: Mes 214 | HI3: Mes 215 | HJ3: Mes 216 | HK3: Mes 217 | HL3: Mes 218 | HM3: Mes 219 | HN3: Mes 220 | HO3: Mes 221 | HP3: Mes 222 | HQ3: Mes 223 | HR3: Mes 224 | HS3: Mes 225 | HT3: Mes 226 | HU3: Mes 227 | HV3: Mes 228 | HW3: Mes 229 | HX3: Mes 230 | HY3: Mes 231 | HZ3: Mes 232 | IA3: Mes 233 | IB3: Mes 234 | IC3: Mes 235 | ID3: Mes 236 | IE3: Mes 237 | IF3: Mes 238 | IG3: Mes 239 | IH3: Mes 240 | II3: Mes 241 | IJ3: Mes 242 | IK3: Mes 243 | IL3: Mes 244 | IM3: Mes 245 | IN3: Mes 246 | IO3: Mes 247 | IP3: Mes 248 | IQ3: Mes 249 | IR3: Mes 250 | IS3: Mes 251 | IT3: Mes 252 | IU3: Mes 253 | IV3: Mes 254 | IW3: Mes 255 | IX3: Mes 256 | IY3: Mes 257 | IZ3: Mes 258 | JA3: Mes 259 | JB3: Mes 260 | JC3: Mes 261 | JD3: Mes 262 | JE3: Mes 263 | JF3: Mes 264 | JG3: Mes 265 | JH3: Mes 266 | JI3: Mes 267 | JJ3: Mes 268 | JK3: Mes 269 | JL3: Mes 270 | JM3: Mes 271 | JN3: Mes 272 | JO3: Mes 273 | JP3: Mes 274 | JQ3: Mes 275 | JR3: Mes 276 | JS3: Mes 277 | JT3: Mes 278 | JU3: Mes 279 | JV3: Mes 280 | JW3: Mes 281 | JX3: Mes 282 | JY3: Mes 283 | JZ3: Mes 284 | KA3: Mes 285 | KB3: Mes 286 | KC3: Mes 287 | KD3: Mes 288 | KE3: Mes 289 | KF3: Mes 290 | KG3: Mes 291 | KH3: Mes 292 | KI3: Mes 293 | KJ3: Mes 294 | KK3: Mes 295 | KL3: Mes 296 | KM3: Mes 297 | KN3: Mes 298 | KO3: Mes 299 | KP3: Mes 300
A4: EBIT | B4: 0 | C4: ='Estado de Resultados'!B11 -> -575666.67 | D4: ='Estado de Resultados'!C11 -> -575666.67 | E4: ='Estado de Resultados'!D11 -> -575666.67 | F4: ='Estado de Resultados'!E11 -> -575666.67 | G4: ='Estado de Resultados'!F11 -> -575666.67 | H4: ='Estado de Resultados'!G11 -> -575666.67 | I4: ='Estado de Resultados'!H11 -> -575666.67 | J4: ='Estado de Resultados'!I11 -> -575666.67 | ... KP4: ='Estado de Resultados'!KO11 -> 27292826
A5: Impuestos sobre EBIT | B5: 0 | C5: =IF(C4>0,C4*'Panel de Control'!$B$15,0) -> 0 | D5: =IF(D4>0,D4*'Panel de Control'!$B$15,0) -> 0 | E5: =IF(E4>0,E4*'Panel de Control'!$B$15,0) -> 0 | F5: =IF(F4>0,F4*'Panel de Control'!$B$15,0) -> 0 | G5: =IF(G4>0,G4*'Panel de Control'!$B$15,0) -> 0 | H5: =IF(H4>0,H4*'Panel de Control'!$B$15,0) -> 0 | I5: =IF(I4>0,I4*'Panel de Control'!$B$15,0) -> 0 | J5: =IF(J4>0,J4*'Panel de Control'!$B$15,0) -> 0 | ... KP5: =IF(KP4>0,KP4*'Panel de Control'!$B$15,0) -> 7369062.9
A6: NOPAT (EBIT después de impuestos) | B6: 0 | C6: =C4-C5 -> -575666.67 | D6: =D4-D5 -> -575666.67 | E6: =E4-E5 -> -575666.67 | F6: =F4-F5 -> -575666.67 | G6: =G4-G5 -> -575666.67 | H6: =H4-H5 -> -575666.67 | I6: =I4-I5 -> -575666.67 | J6: =J4-J5 -> -575666.67 | ... KP6: =KP4-KP5 -> 19923763
A7: (+) Depreciación | B7: 0 | C7: =Costos!B16 -> 416666.67 | D7: =Costos!C16 -> 416666.67 | E7: =Costos!D16 -> 416666.67 | F7: =Costos!E16 -> 416666.67 | G7: =Costos!F16 -> 416666.67 | H7: =Costos!G16 -> 416666.67 | I7: =Costos!H16 -> 416666.67 | J7: =Costos!I16 -> 416666.67 | ... KP7: =Costos!KO16 -> 0
A8: (-) CAPEX | B8: =-Supuestos!$B$4 -> -50000000 | C8: 0 | D8: 0 | E8: 0 | F8: 0 | G8: 0 | H8: 0 | I8: 0 | J8: 0 | K8: 0 | L8: 0 | M8: 0 | N8: 0 | O8: 0 | P8: 0 | Q8: 0 | R8: 0 | S8: 0 | T8: 0 | U8: 0 | V8: 0 | W8: 0 | X8: 0 | Y8: 0 | Z8: 0 | AA8: 0 | AB8: 0 | AC8: 0 | AD8: 0 | AE8: 0 | AF8: 0 | AG8: 0 | AH8: 0 | AI8: 0 | AJ8: 0 | AK8: 0 | AL8: 0 | AM8: 0 | AN8: 0 | AO8: 0 | AP8: 0 | AQ8: 0 | AR8: 0 | AS8: 0 | AT8: 0 | AU8: 0 | AV8: 0 | AW8: 0 | AX8: 0 | AY8: 0 | AZ8: 0 | BA8: 0 | BB8: 0 | BC8: 0 | BD8: 0 | BE8: 0 | BF8: 0 | BG8: 0 | BH8: 0 | BI8: 0 | BJ8: 0 | BK8: 0 | BL8: 0 | BM8: 0 | BN8: 0 | BO8: 0 | BP8: 0 | BQ8: 0 | BR8: 0 | BS8: 0 | BT8: 0 | BU8: 0 | BV8: 0 | BW8: 0 | BX8: 0 | BY8: 0 | BZ8: 0 | CA8: 0 | CB8: 0 | CC8: 0 | CD8: 0 | CE8: 0 | CF8: 0 | CG8: 0 | CH8: 0 | CI8: 0 | CJ8: 0 | CK8: 0 | CL8: 0 | CM8: 0 | CN8: 0 | CO8: 0 | CP8: 0 | CQ8: 0 | CR8: 0 | CS8: 0 | CT8: 0 | CU8: 0 | CV8: 0 | CW8: 0 | CX8: 0 | CY8: 0 | CZ8: 0 | DA8: 0 | DB8: 0 | DC8: 0 | DD8: 0 | DE8: 0 | DF8: 0 | DG8: 0 | DH8: 0 | DI8: 0 | DJ8: 0 | DK8: 0 | DL8: 0 | DM8: 0 | DN8: 0 | DO8: 0 | DP8: 0 | DQ8: 0 | DR8: 0 | DS8: 0 | DT8: 0 | DU8: 0 | DV8: 0 | DW8: 0 | DX8: 0 | DY8: 0 | DZ8: 0 | EA8: 0 | EB8: 0 | EC8: 0 | ED8: 0 | EE8: 0 | EF8: 0 | EG8: 0 | EH8: 0 | EI8: 0 | EJ8: 0 | EK8: 0 | EL8: 0 | EM8: 0 | EN8: 0 | EO8: 0 | EP8: 0 | EQ8: 0 | ER8: 0 | ES8: 0 | ET8: 0 | EU8: 0 | EV8: 0 | EW8: 0 | EX8: 0 | EY8: 0 | EZ8: 0 | FA8: 0 | FB8: 0 | FC8: 0 | FD8: 0 | FE8: 0 | FF8: 0 | FG8: 0 | FH8: 0 | FI8: 0 | FJ8: 0 | FK8: 0 | FL8: 0 | FM8: 0 | FN8: 0 | FO8: 0 | FP8: 0 | FQ8: 0 | FR8: 0 | FS8: 0 | FT8: 0 | FU8: 0 | FV8: 0 | FW8: 0 | FX8: 0 | FY8: 0 | FZ8: 0 | GA8: 0 | GB8: 0 | GC8: 0 | GD8: 0 | GE8: 0 | GF8: 0 | GG8: 0 | GH8: 0 | GI8: 0 | GJ8: 0 | GK8: 0 | GL8: 0 | GM8: 0 | GN8: 0 | GO8: 0 | GP8: 0 | GQ8: 0 | GR8: 0 | GS8: 0 | GT8: 0 | GU8: 0 | GV8: 0 | GW8: 0 | GX8: 0 | GY8: 0 | GZ8: 0 | HA8: 0 | HB8: 0 | HC8: 0 | HD8: 0 | HE8: 0 | HF8: 0 | HG8: 0 | HH8: 0 | HI8: 0 | HJ8: 0 | HK8: 0 | HL8: 0 | HM8: 0 | HN8: 0 | HO8: 0 | HP8: 0 | HQ8: 0 | HR8: 0 | HS8: 0 | HT8: 0 | HU8: 0 | HV8: 0 | HW8: 0 | HX8: 0 | HY8: 0 | HZ8: 0 | IA8: 0 | IB8: 0 | IC8: 0 | ID8: 0 | IE8: 0 | IF8: 0 | IG8: 0 | IH8: 0 | II8: 0 | IJ8: 0 | IK8: 0 | IL8: 0 | IM8: 0 | IN8: 0 | IO8: 0 | IP8: 0 | IQ8: 0 | IR8: 0 | IS8: 0 | IT8: 0 | IU8: 0 | IV8: 0 | IW8: 0 | IX8: 0 | IY8: 0 | IZ8: 0 | JA8: 0 | JB8: 0 | JC8: 0 | JD8: 0 | JE8: 0 | JF8: 0 | JG8: 0 | JH8: 0 | JI8: 0 | JJ8: 0 | JK8: 0 | JL8: 0 | JM8: 0 | JN8: 0 | JO8: 0 | JP8: 0 | JQ8: 0 | JR8: 0 | JS8: 0 | JT8: 0 | JU8: 0 | JV8: 0 | JW8: 0 | JX8: 0 | JY8: 0 | JZ8: 0 | KA8: 0 | KB8: 0 | KC8: 0 | KD8: 0 | KE8: 0 | KF8: 0 | KG8: 0 | KH8: 0 | KI8: 0 | KJ8: 0 | KK8: 0 | KL8: 0 | KM8: 0 | KN8: 0 | KO8: 0 | KP8: 0
A9: (-) Cambio en Capital de Trabajo | B9: =-Supuestos!$B$5 -> -7000000 | C9: 0 | D9: 0 | E9: 0 | F9: 0 | G9: 0 | H9: 0 | I9: 0 | J9: 0 | K9: 0 | L9: 0 | M9: 0 | N9: 0 | O9: 0 | P9: 0 | Q9: 0 | R9: 0 | S9: 0 | T9: 0 | U9: 0 | V9: 0 | W9: 0 | X9: 0 | Y9: 0 | Z9: 0 | AA9: 0 | AB9: 0 | AC9: 0 | AD9: 0 | AE9: 0 | AF9: 0 | AG9: 0 | AH9: 0 | AI9: 0 | AJ9: 0 | AK9: 0 | AL9: 0 | AM9: 0 | AN9: 0 | AO9: 0 | AP9: 0 | AQ9: 0 | AR9: 0 | AS9: 0 | AT9: 0 | AU9: 0 | AV9: 0 | AW9: 0 | AX9: 0 | AY9: 0 | AZ9: 0 | BA9: 0 | BB9: 0 | BC9: 0 | BD9: 0 | BE9: 0 | BF9: 0 | BG9: 0 | BH9: 0 | BI9: 0 | BJ9: 0 | BK9: 0 | BL9: 0 | BM9: 0 | BN9: 0 | BO9: 0 | BP9: 0 | BQ9: 0 | BR9: 0 | BS9: 0 | BT9: 0 | BU9: 0 | BV9: 0 | BW9: 0 | BX9: 0 | BY9: 0 | BZ9: 0 | CA9: 0 | CB9: 0 | CC9: 0 | CD9: 0 | CE9: 0 | CF9: 0 | CG9: 0 | CH9: 0 | CI9: 0 | CJ9: 0 | CK9: 0 | CL9: 0 | CM9: 0 | CN9: 0 | CO9: 0 | CP9: 0 | CQ9: 0 | CR9: 0 | CS9: 0 | CT9: 0 | CU9: 0 | CV9: 0 | CW9: 0 | CX9: 0 | CY9: 0 | CZ9: 0 | DA9: 0 | DB9: 0 | DC9: 0 | DD9: 0 | DE9: 0 | DF9: 0 | DG9: 0 | DH9: 0 | DI9: 0 | DJ9: 0 | DK9: 0 | DL9: 0 | DM9: 0 | DN9: 0 | DO9: 0 | DP9: 0 | DQ9: 0 | DR9: 0 | DS9: 0 | DT9: 0 | DU9: 0 | DV9: 0 | DW9: 0 | DX9: 0 | DY9: 0 | DZ9: 0 | EA9: 0 | EB9: 0 | EC9: 0 | ED9: 0 | EE9: 0 | EF9: 0 | EG9: 0 | EH9: 0 | EI9: 0 | EJ9: 0 | EK9: 0 | EL9: 0 | EM9: 0 | EN9: 0 | EO9: 0 | EP9: 0 | EQ9: 0 | ER9: 0 | ES9: 0 | ET9: 0 | EU9: 0 | EV9: 0 | EW9: 0 | EX9: 0 | EY9: 0 | EZ9: 0 | FA9: 0 | FB9: 0 | FC9: 0 | FD9: 0 | FE9: 0 | FF9: 0 | FG9: 0 | FH9: 0 | FI9: 0 | FJ9: 0 | FK9: 0 | FL9: 0 | FM9: 0 | FN9: 0 | FO9: 0 | FP9: 0 | FQ9: 0 | FR9: 0 | FS9: 0 | FT9: 0 | FU9: 0 | FV9: 0 | FW9: 0 | FX9: 0 | FY9: 0 | FZ9: 0 | GA9: 0 | GB9: 0 | GC9: 0 | GD9: 0 | GE9: 0 | GF9: 0 | GG9: 0 | GH9: 0 | GI9: 0 | GJ9: 0 | GK9: 0 | GL9: 0 | GM9: 0 | GN9: 0 | GO9: 0 | GP9: 0 | GQ9: 0 | GR9: 0 | GS9: 0 | GT9: 0 | GU9: 0 | GV9: 0 | GW9: 0 | GX9: 0 | GY9: 0 | GZ9: 0 | HA9: 0 | HB9: 0 | HC9: 0 | HD9: 0 | HE9: 0 | HF9: 0 | HG9: 0 | HH9: 0 | HI9: 0 | HJ9: 0 | HK9: 0 | HL9: 0 | HM9: 0 | HN9: 0 | HO9: 0 | HP9: 0 | HQ9: 0 | HR9: 0 | HS9: 0 | HT9: 0 | HU9: 0 | HV9: 0 | HW9: 0 | HX9: 0 | HY9: 0 | HZ9: 0 | IA9: 0 | IB9: 0 | IC9: 0 | ID9: 0 | IE9: 0 | IF9: 0 | IG9: 0 | IH9: 0 | II9: 0 | IJ9: 0 | IK9: 0 | IL9: 0 | IM9: 0 | IN9: 0 | IO9: 0 | IP9: 0 | IQ9: 0 | IR9: 0 | IS9: 0 | IT9: 0 | IU9: 0 | IV9: 0 | IW9: 0 | IX9: 0 | IY9: 0 | IZ9: 0 | JA9: 0 | JB9: 0 | JC9: 0 | JD9: 0 | JE9: 0 | JF9: 0 | JG9: 0 | JH9: 0 | JI9: 0 | JJ9: 0 | JK9: 0 | JL9: 0 | JM9: 0 | JN9: 0 | JO9: 0 | JP9: 0 | JQ9: 0 | JR9: 0 | JS9: 0 | JT9: 0 | JU9: 0 | JV9: 0 | JW9: 0 | JX9: 0 | JY9: 0 | JZ9: 0 | KA9: 0 | KB9: 0 | KC9: 0 | KD9: 0 | KE9: 0 | KF9: 0 | KG9: 0 | KH9: 0 | KI9: 0 | KJ9: 0 | KK9: 0 | KL9: 0 | KM9: 0 | KN9: 0 | KO9: 0 | KP9: 0
A10: (-) Gastos Pre-operativos | B10: =-Supuestos!$B$6 -> -500000 | C10: 0 | D10: 0 | E10: 0 | F10: 0 | G10: 0 | H10: 0 | I10: 0 | J10: 0 | K10: 0 | L10: 0 | M10: 0 | N10: 0 | O10: 0 | P10: 0 | Q10: 0 | R10: 0 | S10: 0 | T10: 0 | U10: 0 | V10: 0 | W10: 0 | X10: 0 | Y10: 0 | Z10: 0 | AA10: 0 | AB10: 0 | AC10: 0 | AD10: 0 | AE10: 0 | AF10: 0 | AG10: 0 | AH10: 0 | AI10: 0 | AJ10: 0 | AK10: 0 | AL10: 0 | AM10: 0 | AN10: 0 | AO10: 0 | AP10: 0 | AQ10: 0 | AR10: 0 | AS10: 0 | AT10: 0 | AU10: 0 | AV10: 0 | AW10: 0 | AX10: 0 | AY10: 0 | AZ10: 0 | BA10: 0 | BB10: 0 | BC10: 0 | BD10: 0 | BE10: 0 | BF10: 0 | BG10: 0 | BH10: 0 | BI10: 0 | BJ10: 0 | BK10: 0 | BL10: 0 | BM10: 0 | BN10: 0 | BO10: 0 | BP10: 0 | BQ10: 0 | BR10: 0 | BS10: 0 | BT10: 0 | BU10: 0 | BV10: 0 | BW10: 0 | BX10: 0 | BY10: 0 | BZ10: 0 | CA10: 0 | CB10: 0 | CC10: 0 | CD10: 0 | CE10: 0 | CF10: 0 | CG10: 0 | CH10: 0 | CI10: 0 | CJ10: 0 | CK10: 0 | CL10: 0 | CM10: 0 | CN10: 0 | CO10: 0 | CP10: 0 | CQ10: 0 | CR10: 0 | CS10: 0 | CT10: 0 | CU10: 0 | CV10: 0 | CW10: 0 | CX10: 0 | CY10: 0 | CZ10: 0 | DA10: 0 | DB10: 0 | DC10: 0 | DD10: 0 | DE10: 0 | DF10: 0 | DG10: 0 | DH10: 0 | DI10: 0 | DJ10: 0 | DK10: 0 | DL10: 0 | DM10: 0 | DN10: 0 | DO10: 0 | DP10: 0 | DQ10: 0 | DR10: 0 | DS10: 0 | DT10: 0 | DU10: 0 | DV10: 0 | DW10: 0 | DX10: 0 | DY10: 0 | DZ10: 0 | EA10: 0 | EB10: 0 | EC10: 0 | ED10: 0 | EE10: 0 | EF10: 0 | EG10: 0 | EH10: 0 | EI10: 0 | EJ10: 0 | EK10: 0 | EL10: 0 | EM10: 0 | EN10: 0 | EO10: 0 | EP10: 0 | EQ10: 0 | ER10: 0 | ES10: 0 | ET10: 0 | EU10: 0 | EV10: 0 | EW10: 0 | EX10: 0 | EY10: 0 | EZ10: 0 | FA10: 0 | FB10: 0 | FC10: 0 | FD10: 0 | FE10: 0 | FF10: 0 | FG10: 0 | FH10: 0 | FI10: 0 | FJ10: 0 | FK10: 0 | FL10: 0 | FM10: 0 | FN10: 0 | FO10: 0 | FP10: 0 | FQ10: 0 | FR10: 0 | FS10: 0 | FT10: 0 | FU10: 0 | FV10: 0 | FW10: 0 | FX10: 0 | FY10: 0 | FZ10: 0 | GA10: 0 | GB10: 0 | GC10: 0 | GD10: 0 | GE10: 0 | GF10: 0 | GG10: 0 | GH10: 0 | GI10: 0 | GJ10: 0 | GK10: 0 | GL10: 0 | GM10: 0 | GN10: 0 | GO10: 0 | GP10: 0 | GQ10: 0 | GR10: 0 | GS10: 0 | GT10: 0 | GU10: 0 | GV10: 0 | GW10: 0 | GX10: 0 | GY10: 0 | GZ10: 0 | HA10: 0 | HB10: 0 | HC10: 0 | HD10: 0 | HE10: 0 | HF10: 0 | HG10: 0 | HH10: 0 | HI10: 0 | HJ10: 0 | HK10: 0 | HL10: 0 | HM10: 0 | HN10: 0 | HO10: 0 | HP10: 0 | HQ10: 0 | HR10: 0 | HS10: 0 | HT10: 0 | HU10: 0 | HV10: 0 | HW10: 0 | HX10: 0 | HY10: 0 | HZ10: 0 | IA10: 0 | IB10: 0 | IC10: 0 | ID10: 0 | IE10: 0 | IF10: 0 | IG10: 0 | IH10: 0 | II10: 0 | IJ10: 0 | IK10: 0 | IL10: 0 | IM10: 0 | IN10: 0 | IO10: 0 | IP10: 0 | IQ10: 0 | IR10: 0 | IS10: 0 | IT10: 0 | IU10: 0 | IV10: 0 | IW10: 0 | IX10: 0 | IY10: 0 | IZ10: 0 | JA10: 0 | JB10: 0 | JC10: 0 | JD10: 0 | JE10: 0 | JF10: 0 | JG10: 0 | JH10: 0 | JI10: 0 | JJ10: 0 | JK10: 0 | JL10: 0 | JM10: 0 | JN10: 0 | JO10: 0 | JP10: 0 | JQ10: 0 | JR10: 0 | JS10: 0 | JT10: 0 | JU10: 0 | JV10: 0 | JW10: 0 | JX10: 0 | JY10: 0 | JZ10: 0 | KA10: 0 | KB10: 0 | KC10: 0 | KD10: 0 | KE10: 0 | KF10: 0 | KG10: 0 | KH10: 0 | KI10: 0 | KJ10: 0 | KK10: 0 | KL10: 0 | KM10: 0 | KN10: 0 | KO10: 0 | KP10: 0
A11: (+) Valor Residual | B11: 0 | C11: 0 | D11: 0 | E11: 0 | F11: 0 | G11: 0 | H11: 0 | I11: 0 | J11: 0 | K11: 0 | L11: 0 | M11: 0 | N11: 0 | O11: 0 | P11: 0 | Q11: 0 | R11: 0 | S11: 0 | T11: 0 | U11: 0 | V11: 0 | W11: 0 | X11: 0 | Y11: 0 | Z11: 0 | AA11: 0 | AB11: 0 | AC11: 0 | AD11: 0 | AE11: 0 | AF11: 0 | AG11: 0 | AH11: 0 | AI11: 0 | AJ11: 0 | AK11: 0 | AL11: 0 | AM11: 0 | AN11: 0 | AO11: 0 | AP11: 0 | AQ11: 0 | AR11: 0 | AS11: 0 | AT11: 0 | AU11: 0 | AV11: 0 | AW11: 0 | AX11: 0 | AY11: 0 | AZ11: 0 | BA11: 0 | BB11: 0 | BC11: 0 | BD11: 0 | BE11: 0 | BF11: 0 | BG11: 0 | BH11: 0 | BI11: 0 | BJ11: =Supuestos!$B$4*Supuestos!$B$32 -> 10000000 | BK11: 0 | BL11: 0 | BM11: 0 | BN11: 0 | BO11: 0 | BP11: 0 | BQ11: 0 | BR11: 0 | BS11: 0 | BT11: 0 | BU11: 0 | BV11: 0 | BW11: 0 | BX11: 0 | BY11: 0 | BZ11: 0 | CA11: 0 | CB11: 0 | CC11: 0 | CD11: 0 | CE11: 0 | CF11: 0 | CG11: 0 | CH11: 0 | CI11: 0 | CJ11: 0 | CK11: 0 | CL11: 0 | CM11: 0 | CN11: 0 | CO11: 0 | CP11: 0 | CQ11: 0 | CR11: 0 | CS11: 0 | CT11: 0 | CU11: 0 | CV11: 0 | CW11: 0 | CX11: 0 | CY11: 0 | CZ11: 0 | DA11: 0 | DB11: 0 | DC11: 0 | DD11: 0 | DE11: 0 | DF11: 0 | DG11: 0 | DH11: 0 | DI11: 0 | DJ11: 0 | DK11: 0 | DL11: 0 | DM11: 0 | DN11: 0 | DO11: 0 | DP11: 0 | DQ11: 0 | DR11: 0 | DS11: 0 | DT11: 0 | DU11: 0 | DV11: 0 | DW11: 0 | DX11: 0 | DY11: 0 | DZ11: 0 | EA11: 0 | EB11: 0 | EC11: 0 | ED11: 0 | EE11: 0 | EF11: 0 | EG11: 0 | EH11: 0 | EI11: 0 | EJ11: 0 | EK11: 0 | EL11: 0 | EM11: 0 | EN11: 0 | EO11: 0 | EP11: 0 | EQ11: 0 | ER11: 0 | ES11: 0 | ET11: 0 | EU11: 0 | EV11: 0 | EW11: 0 | EX11: 0 | EY11: 0 | EZ11: 0 | FA11: 0 | FB11: 0 | FC11: 0 | FD11: 0 | FE11: 0 | FF11: 0 | FG11: 0 | FH11: 0 | FI11: 0 | FJ11: 0 | FK11: 0 | FL11: 0 | FM11: 0 | FN11: 0 | FO11: 0 | FP11: 0 | FQ11: 0 | FR11: 0 | FS11: 0 | FT11: 0 | FU11: 0 | FV11: 0 | FW11: 0 | FX11: 0 | FY11: 0 | FZ11: 0 | GA11: 0 | GB11: 0 | GC11: 0 | GD11: 0 | GE11: 0 | GF11: 0 | GG11: 0 | GH11: 0 | GI11: 0 | GJ11: 0 | GK11: 0 | GL11: 0 | GM11: 0 | GN11: 0 | GO11: 0 | GP11: 0 | GQ11: 0 | GR11: 0 | GS11: 0 | GT11: 0 | GU11: 0 | GV11: 0 | GW11: 0 | GX11: 0 | GY11: 0 | GZ11: 0 | HA11: 0 | HB11: 0 | HC11: 0 | HD11: 0 | HE11: 0 | HF11: 0 | HG11: 0 | HH11: 0 | HI11: 0 | HJ11: 0 | HK11: 0 | HL11: 0 | HM11: 0 | HN11: 0 | HO11: 0 | HP11: 0 | HQ11: 0 | HR11: 0 | HS11: 0 | HT11: 0 | HU11: 0 | HV11: 0 | HW11: 0 | HX11: 0 | HY11: 0 | HZ11: 0 | IA11: 0 | IB11: 0 | IC11: 0 | ID11: 0 | IE11: 0 | IF11: 0 | IG11: 0 | IH11: 0 | II11: 0 | IJ11: 0 | IK11: 0 | IL11: 0 | IM11: 0 | IN11: 0 | IO11: 0 | IP11: 0 | IQ11: 0 | IR11: 0 | IS11: 0 | IT11: 0 | IU11: 0 | IV11: 0 | IW11: 0 | IX11: 0 | IY11: 0 | IZ11: 0 | JA11: 0 | JB11: 0 | JC11: 0 | JD11: 0 | JE11: 0 | JF11: 0 | JG11: 0 | JH11: 0 | JI11: 0 | JJ11: 0 | JK11: 0 | JL11: 0 | JM11: 0 | JN11: 0 | JO11: 0 | JP11: 0 | JQ11: 0 | JR11: 0 | JS11: 0 | JT11: 0 | JU11: 0 | JV11: 0 | JW11: 0 | JX11: 0 | JY11: 0 | JZ11: 0 | KA11: 0 | KB11: 0 | KC11: 0 | KD11: 0 | KE11: 0 | KF11: 0 | KG11: 0 | KH11: 0 | KI11: 0 | KJ11: 0 | KK11: 0 | KL11: 0 | KM11: 0 | KN11: 0 | KO11: 0 | KP11: 0
A13: FLUJO DE CAJA LIBRE | B13: =B6+SUM(B7:B11) -> -57500000 | C13: =C6+SUM(C7:C11) -> -159000 | D13: =D6+SUM(D7:D11) -> -159000 | E13: =E6+SUM(E7:E11) -> -159000 | F13: =F6+SUM(F7:F11) -> -159000 | G13: =G6+SUM(G7:G11) -> -159000 | H13: =H6+SUM(H7:H11) -> -159000 | I13: =I6+SUM(I7:I11) -> -159000 | ... KP13: =KP6+SUM(KP7:KP11) -> 19923763
A14: Flujo de Caja Acumulado | B14: =B13 -> -57500000 | C14: =B14+C13 -> -57659000 | D14: =C14+D13 -> -57818000 | E14: =D14+E13 -> -57977000 | F14: =E14+F13 -> -58136000 | G14: =F14+G13 -> -58295000 | H14: =G14+H13 -> -58454000 | I14: =H14+I13 -> -58613000 | J14: =I14+J13 -> -58772000 | ... KP14: =KO14+KP13 -> 2.1876276e+09
A15: Flujo de Caja Descontado | B15: =B13 -> -57500000 | C15: =C13/POWER(1+((1+'Panel de Control'!$B$14)^(1/12)-1),COLUMN()-2) -> -157505.46 | D15: =D13/POWER(1+((1+'Panel de Control'!$B$14)^(1/12)-1),COLUMN()-2) -> -156024.97 | E15: =E13/POWER(1+((1+'Panel de Control'!$B$14)^(1/12)-1),COLUMN()-2) -> -154558.4 | F15: =F13/POWER(1+((1+'Panel de Control'!$B$14)^(1/12)-1),COLUMN()-2) -> -153105.61 | G15: =G13/POWER(1+((1+'Panel de Control'!$B$14)^(1/12)-1),COLUMN()-2) -> -151666.48 | H15: =H13/POWER(1+((1+'Panel de Control'!$B$14)^(1/12)-1),COLUMN()-2) -> -150240.88 | I15: =I13/POWER(1+((1+'Panel de Control'!$B$14)^(1/12)-1),COLUMN()-2) -> -148828.67 | J15: =J13/POWER(1+((1+'Panel de Control'!$B$14)^(1/12)-1),COLUMN()-2) -> -147429.74 | ... KP15: =KP13/POWER(1+((1+'Panel de Control'!$B$14)^(1/12)-1),COLUMN()-2) -> 1171981.6

Sheet Resumen
A1: RESUMEN EJECUTIVO E INDICADORES
A3: INDICADORES FINANCIEROS PRINCIPALES
A5: VAN (Valor Actual Neto): | B5: =SUM('Flujo de Caja'!B15:BJ15) -> -24259406
A6: TIR (Tasa Interna de Retorno) - Mensual: | B6: =IFERROR(IRR('Flujo de Caja'!B13:BJ13,-0.005),"n/d") -> -0.0021329917
A7: TIR Anual Efectiva: | B7: =IFERROR(POWER(1+B6,12)-1,"n/d") -> -0.025297748
A8: Período de Recuperación (meses): | B8: =IFERROR(MATCH(TRUE(),INDEX('Flujo de Caja'!C14:BJ14>0,0),0),"-") -> -
A9: ROI (Return on Investment): | B9: ='Flujo de Caja'!BJ14/(Supuestos!$B$4+Supuestos!$B$5+Supuestos!$B$6) -> -0.097106988
A11: ANÁLISIS DE RENTABILIDAD
A13: Margen Bruto Promedio (primeros 60 meses): | B13: =AVERAGE('Estado de Resultados'!B18:BI18) -> 0.63
A14: Margen EBITDA Promedio (primeros 60 meses): | B14: =AVERAGE('Estado de Resultados'!B19:BI19) -> 0.064172754
A15: Margen Neto Promedio (primeros 60 meses): | B15: =AVERAGE('Estado de Resultados'!B20:BI20) -> 0.017530108
A17: TOTALES ACUMULADOS (Horizonte de Evaluación)
A19: Ingresos Totales Acumulados: | B19: =SUM('Estado de Resultados'!C4:BJ4) -> 7.4270219e+08
A20: Costos y Gastos Totales Acumulados: | B20: =SUM(Costos!C18:BJ18) -> 7.1379981e+08
A21: EBITDA Total Acumulado: | B21: =SUM('Estado de Resultados'!C9:BJ9) -> 53902381
A22: Utilidad Neta Total Acumulada: | B22: =SUM('Estado de Resultados'!C15:BJ15) -> 18401029
A24: INFORMACIÓN DEL FINANCIAMIENTO
A26: Monto del Préstamo: | B26: =Supuestos!$B$27 -> 4000000
A27: Tasa de Interés Anual: | B27: =Supuestos!$B$28 -> 0.07
A28: Plazo (meses): | B28: =Supuestos!$B$29 -> 60
A29: Total Intereses Pagados: | B29: =SUM(Financiamiento!C6:BK6) -> 728954.32
A31: ANÁLISIS DE SENSIBILIDAD - PARÁMETROS
A33: Variación en Ingresos: | B33: 0
A34: Variación en Costos Variables: | B34: 0
A35: Variación en Costos Fijos: | B35: 0

Sheet Escenarios
A1: ANÁLISIS DE ESCENARIOS
A3: Configure diferentes escenarios para el proyecto:
A5: Variables | B5: Pesimista | C5: Base | D5: Optimista
A7: Crecimiento Anual Ingresos | B7: 0.05 | C7: =Supuestos!$B$10 -> 0.07 | D7: 0.25
A8: % Costos Variables sobre Ventas | B8: 0.5 | C8: =Supuestos!$B$13 -> 0.37 | D8: 0.3
A9: Tasa de Descuento (WACC) | B9: 0.18 | C9: ='Panel de Control'!$B$14 -> 0.12 | D9: 0.09
A10: Inversión Inicial en Activos Fijos | B10: =C10*1.2 -> 60000000 | C10: =Supuestos!$B$4 -> 50000000 | D10: =C10*0.8 -> 40000000
A12: RESULTADOS POR ESCENARIO
A14: Indicador | B14: Pesimista | C14: Base | D14: Optimista
A16: VAN | B16: Variable con escenario | C16: =Resumen!$B$5 -> -24259406 | D16: Variable con escenario
A17: TIR Anual | B17: Variable con escenario | C17: =Resumen!$B$7 -> -0.025297748 | D17: Variable con escenario
A18: Período de Recuperación | B18: Variable con escenario | C18: =Resumen!$B$8 -> - | D18: Variable con escenario
A20: NOTA: Pesimista y Optimista se recalculan automáticamente en el software Amberes Intelligence
A21: (el Excel solo muestra el caso Base). Los capex de ambos escenarios se definen como ±20% de la base.

Sheet Valoración
A1: VALORACIÓN DE LA EMPRESA
A3: MÉTODOS DE VALORACIÓN
A5: MÉTODO 1: FLUJO DE CAJA DESCONTADO
A7: Valor Presente de los Flujos (VAN): | B7: =Resumen!$B$5 -> -24259406
A8: Inversión Inicial: | B8: =Supuestos!$B$4+Supuestos!$B$5+Supuestos!$B$6 -> 57500000
A9: Valor de la Empresa (Enterprise Value): | B9: =B7+B8 -> 33240594
A11: MÉTODO 2: MÚLTIPLOS COMPARABLES
A13: EBITDA Promedio Anual (primeros 5 años): | B13: =SUM('Estado de Resultados'!B9:BI9)/5 -> 10237756
A14: Múltiplo EV/EBITDA (comparable): | B14: 8
A15: Valor de la Empresa (por múltiplo): | B15: =B13*B14 -> 81902048
A17: MÉTODO 3: VALOR PATRIMONIAL
A19: Activos Totales al final del período: | B19: =Supuestos!$B$4-SUM(Costos!B16:BI16)+Supuestos!$B$5 -> 32000000
A20: Pasivos (Deuda Financiera Pendiente): | B20: =Financiamiento!BI7 -> 5.6752469e-09
A21: Patrimonio Neto (Valor en Libros): | B21: =B19-B20 -> 32000000
A24: RESUMEN DE VALORACIÓN
A26: Método Flujo de Caja Descontado: | B26: =B9 -> 33240594
A27: Método Múltiplos (EV/EBITDA): | B27: =B15 -> 81902048
A28: Método Valor Patrimonial: | B28: =B21 -> 32000000
A30: Valoración Promedio: | B30: =AVERAGE(B26:B28) -> 49047547
A33: PARÁMETROS PARA M&A
A35: Prima por Control (%): | B35: 0.2
A36: Valor con Prima por Control: | B36: =B30*(1+B35) -> 58857057
A38: Sinergias Esperadas (valor anual): | B38: 50000
A39: Valor Presente de Sinergias (perpetuidad): | B39: =B38/'Panel de Control'!$B$14 -> 416666.67
A41: VALOR TOTAL INCLUYENDO SINERGIAS: | B41: =B36+B39 -> 59273723

Sheet Ratios Financieros
A1: RATIOS E INDICADORES FINANCIEROS
A3: RATIOS DE LIQUIDEZ
A5: Capital de Trabajo (mes 60): | B5: =Supuestos!$B$5 -> 7000000
A7: RATIOS DE RENTABILIDAD
A9: ROA (Return on Assets) - sobre activos iniciales: | B9: =SUM('Estado de Resultados'!B15:M15)/(Supuestos!$B$4+Supuestos!$B$5) -> -0.12572045
A10: ROE (Return on Equity) - sin deuda: | B10: =SUM('Estado de Resultados'!B15:M15)/(Supuestos!$B$4+Supuestos!$B$5+Supuestos!$B$6-Supuestos!$B$27) -> -0.13394515
A12: RATIOS DE ENDEUDAMIENTO
A14: Ratio Deuda/Patrimonio (D/E) inicial: | B14: =Supuestos!$B$27/(Supuestos!$B$4+Supuestos!$B$5+Supuestos!$B$6-Supuestos!$B$27) -> 0.074766355
A15: Ratio de Cobertura de Intereses (Mes 12): | B15: =IFERROR('Estado de Resultados'!M11/Financiamiento!M6,"-") -> -29.308197
A17: MÉTRICAS DE EFICIENCIA
A19: Rotación de Activos (veces/año): | B19: =SUM('Estado de Resultados'!B4:M4)/(Supuestos!$B$4+Supuestos!$B$5) -> 2.2526316
A20: Días de Capital de Trabajo: | B20: =(Supuestos!$B$5/SUM('Estado de Resultados'!B4:M4))*365 -> 19.898754
A22: PUNTO DE EQUILIBRIO
A24: Costos Fijos Mensuales Totales: | B24: =SUM(Supuestos!$B$16:$B$20) -> 6900000
A25: Margen de Contribución (%): | B25: =1-Supuestos!$B$13 -> 0.63
A26: Punto de Equilibrio Mensual (ventas): | B26: =B24/B25 -> 10952381
A27: Margen de Seguridad (mes 1): | B27: =(Ingresos!B6-B26)/Ingresos!B6 -> -0.023587005
A29: ANÁLISIS DE CRECIMIENTO
A31: Crecimiento Promedio Mensual Ingresos (año 1): | B31: =(Ingresos!M6/Ingresos!B6)^(1/11)-1 -> 0
A32: CAGR Ingresos (Años 1-5): | B32: =(Ingresos!BI6/Ingresos!B6)^(1/4.9167)-1 -> 0.056587052

Sheet Balance
A1: BALANCE Y SUPUESTOS DE PROYECCIÓN
A2: Opcional. Con un solo período se usa como balance inicial; con dos (anterior y actual) el software además reconstruye el flujo de caja por diferencias. En blanco: se estima desde el P&L y se marca "estimado".
A4: BALANCE (saldos al cierre de cada período) | B4: Período anterior | C4: Período actual
A5: Caja y bancos | D5: Si se deja en blanco, se estima como 1 mes de gastos operativos
A6: Clientes (cuentas por cobrar) | D6: En blanco: se estima con DSO
A7: Inventarios | D7: En blanco: se estima con DIO (0 en servicios)
A8: Activo fijo neto | D8: En blanco: se estima desde el capex y la depreciación
A9: Proveedores (cuentas por pagar) | D9: En blanco: se estima con DPO
A10: Deuda financiera | D10: En blanco: se toma del Financiamiento si existe
A11: Capital social | D11: En blanco: se calcula para que el balance cuadre
A12: Resultados acumulados | D12: En blanco: se calcula para que el balance cuadre
A15: SUPUESTOS DE PROYECCIÓN
A16: DSO – Días de cobro | D16: Defecto 30 días
A17: DIO – Días de inventario | D17: Defecto: 0 en servicios
A18: DPO – Días de pago a proveedores | D18: Defecto: según el negocio
A19: Capex (% de ingresos) | D19: Defecto: 3% estimado
A20: Pago de deuda (capital) mensual | D20: Defecto: 0
A21: Payout (dividendos sobre utilidad) | D21: Defecto: 0%
A22: Costo de la deuda (Kd) | D22: Defecto: 7,5%
A23: Tasa de impuesto | D23: Defecto: la del P&L o Panel de Control

Sheet Estado de Flujo de Caja
A1: ESTADO DE FLUJO DE CAJA (opcional)
A2: Complételo solo si no tiene P&L: el software reconstruye P&L y balance estimados desde estas cifras. Períodos en columnas (12 meses o uno anual).
A3: Concepto | B3: Ene | C3: Feb | D3: Mar | E3: Abr | F3: May | G3: Jun | H3: Jul | I3: Ago | J3: Sep | K3: Oct | L3: Nov | M3: Dic
A4: Ingresos cobrados (opcional)
A5: Utilidad neta
A6: (+) Depreciación y amortización
A7: Variación de capital de trabajo
A8: FLUJO OPERACIONAL
A9: Capex (compra de activos fijos)
A10: FLUJO DE INVERSIÓN
A11: Obtención de deuda
A12: Pago de deuda
A13: Dividendos
A14: Intereses pagados
A15: Impuestos pagados
... A21: Signos: ingresos de caja en positivo y salidas en negativo (o positivas, el software las normaliza).

Sheet M&A
A1: M&A Y VALORACIÓN – PARÁMETROS
A2: Opcional. Columna B = su dato (si lo completa, tiene prioridad). Columna C = referencia de mercado. En blanco: el software autocompleta desde el modelo.
A4: OPERACIÓN (DCF)
A5: Ingresos base (año 0) | C5: Defecto: ingresos anualizados del P&L
A6: Crecimiento anual de ingresos | C6: Defecto: tendencia del P&L
A7: Margen EBITDA | C7: Defecto: margen del P&L
A8: D&A (% de ingresos) | C8: Defecto: del P&L o 3%
A9: CAPEX (% de ingresos) | C9: Defecto: 3%
A10: Capital de trabajo (% de ingresos) | C10: Defecto: 10%
A11: Tasa de impuesto | C11: Chile: 27% (régimen general)
A12: Años de proyección | C12: Defecto: 5
A14: COSTO DE CAPITAL (CAPM / WACC)
A15: Crecimiento terminal (g) | C15: Referencia 2%–3%
A16: Tasa libre de riesgo (Rf) | C16: Bono soberano a 10 años
A17: Beta | C17: Beta apalancada del sector
A18: Premio por riesgo de mercado (ERP) | C18: Referencia 5%–6%
A19: Riesgo país / tamaño | C19: Prima adicional según país y tamaño
A20: Costo de deuda antes de impuestos (Kd) | C20: Tasa de financiamiento
A21: Deuda / (Deuda + Patrimonio) objetivo | C21: Estructura de capital objetivo
A22: WACC (opcional, reemplaza el calculado) | C22: Solo si desea forzar el WACC
A24: MÚLTIPLOS, DEUDA Y SINERGIAS
A25: Múltiplo EV/EBITDA | C25: Comparables del sector
A26: Deuda financiera neta | C26: Deuda − caja
A27: Sinergias de costos (anual) | C27: Ahorro recurrente esperado
A28: Sinergias de ingresos (anual) | C28: Ingresos incrementales esperados
A29: Años para capturar sinergias | C29: Defecto: 3
A30: Costo de integración (one-off) | C30: Costo único de integración
A31: Prima por control | C31: Referencia 20%–30%

Sheet P&L Productiva - Real
A1: ESTADO DE RESULTADOS - EMPRESA PRODUCTIVA
A2: Escenario: Real
A3: Cifras en USD
A5: Concepto | B5: Enero | C5: Febrero | D5: Marzo | E5: Abril | F5: Mayo | G5: Junio | H5: Julio | I5: Agosto | J5: Septiembre | K5: Octubre | L5: Noviembre | M5: Diciembre | N5: TOTAL AÑO
A6: INGRESOS OPERACIONALES
A7: Ventas Producto A | B7: 0 | C7: 0 | D7: 0 | E7: 0 | F7: 0 | G7: 0 | H7: 0 | I7: 0 | J7: 0 | K7: 0 | L7: 0 | M7: 0 | N7: 0
A8: Ventas Producto B | B8: 0 | C8: 0 | D8: 0 | E8: 0 | F8: 0 | G8: 0 | H8: 0 | I8: 0 | J8: 0 | K8: 0 | L8: 0 | M8: 0 | N8: 0
A9: Ventas Producto C | B9: 0 | C9: 0 | D9: 0 | E9: 0 | F9: 0 | G9: 0 | H9: 0 | I9: 0 | J9: 0 | K9: 0 | L9: 0 | M9: 0 | N9: 0
A10: Ventas Otros Productos | B10: 0 | C10: 0 | D10: 0 | E10: 0 | F10: 0 | G10: 0 | H10: 0 | I10: 0 | J10: 0 | K10: 0 | L10: 0 | M10: 0 | N10: =SUM(B10:M10) -> 0
A11: Total Ingresos Brutos | B11: =SUM(B7:B10) -> 0 | C11: =SUM(C7:C10) -> 0 | D11: =SUM(D7:D10) -> 0 | E11: =SUM(E7:E10) -> 0 | F11: =SUM(F7:F10) -> 0 | G11: =SUM(G7:G10) -> 0 | H11: =SUM(H7:H10) -> 0 | I11: =SUM(I7:I10) -> 0 | ... N11: =SUM(N7:N10) -> 0
A12: (-) Devoluciones y Descuentos | B12: 0 | C12: 0 | D12: 0 | E12: 0 | F12: 0 | G12: 0 | H12: 0 | I12: 0 | J12: 0 | K12: 0 | L12: 0 | M12: 0 | N12: 0
A13: (-) Bonificaciones | B13: 0 | C13: 0 | D13: 0 | E13: 0 | F13: 0 | G13: 0 | H13: 0 | I13: 0 | J13: 0 | K13: 0 | L13: 0 | M13: 0 | N13: =SUM(B13:M13) -> 0
A14: INGRESOS NETOS | B14: =B11-B12-B13 -> 0 | C14: =C11-C12-C13 -> 0 | D14: =D11-D12-D13 -> 0 | E14: =E11-E12-E13 -> 0 | F14: =F11-F12-F13 -> 0 | G14: =G11-G12-G13 -> 0 | H14: =H11-H12-H13 -> 0 | I14: =I11-I12-I13 -> 0 | ... N14: =N11-N12-N13 -> 0
A15: COSTO DE VENTAS
A16: Inventario Inicial | B16: 0 | C16: 0 | D16: 0 | E16: 0 | F16: 0 | G16: 0 | H16: 0 | I16: 0 | J16: 0 | K16: 0 | L16: 0 | M16: 0 | N16: 0
A17: (+) Compras de Materia Prima | B17: 0 | C17: 0 | D17: 0 | E17: 0 | F17: 0 | G17: 0 | H17: 0 | I17: 0 | J17: 0 | K17: 0 | L17: 0 | M17: 0 | N17: 0
A18: (+) Mano de Obra Directa | B18: 0 | C18: 0 | D18: 0 | E18: 0 | F18: 0 | G18: 0 | H18: 0 | I18: 0 | J18: 0 | K18: 0 | L18: 0 | M18: 0 | N18: 0
A19: (+) Costos Indirectos de Fabricación | B19: 0 | C19: 0 | D19: 0 | E19: 0 | F19: 0 | G19: 0 | H19: 0 | I19: 0 | J19: 0 | K19: 0 | L19: 0 | M19: 0 | N19: 0
A20: Depreciación Equipos Producción | B20: 0 | C20: 0 | D20: 0 | E20: 0 | F20: 0 | G20: 0 | H20: 0 | I20: 0 | J20: 0 | K20: 0 | L20: 0 | M20: 0 | N20: 0
A21: Servicios Planta | B21: 0 | C21: 0 | D21: 0 | E21: 0 | F21: 0 | G21: 0 | H21: 0 | I21: 0 | J21: 0 | K21: 0 | L21: 0 | M21: 0 | N21: 0
A22: Mantenimiento Equipos | B22: 0 | C22: 0 | D22: 0 | E22: 0 | F22: 0 | G22: 0 | H22: 0 | I22: 0 | J22: 0 | K22: 0 | L22: 0 | M22: 0 | N22: 0
A23: Otros CIF | B23: 0 | C23: 0 | D23: 0 | E23: 0 | F23: 0 | G23: 0 | H23: 0 | I23: 0 | J23: 0 | K23: 0 | L23: 0 | M23: 0 | N23: 0
A24: (-) Inventario Final | B24: 0 | C24: 0 | D24: 0 | E24: 0 | F24: 0 | G24: 0 | H24: 0 | I24: 0 | J24: 0 | K24: 0 | L24: 0 | M24: 0 | N24: 0
A25: COSTO DE VENTAS TOTAL | B25: {=SUM(B16:B23-B24)} -> 0 | C25: {=SUM(C16:C23-C24)} -> 0 | D25: {=SUM(D16:D23-D24)} -> 0 | E25: {=SUM(E16:E23-E24)} -> 0 | F25: {=SUM(F16:F23-F24)} -> 0 | G25: {=SUM(G16:G23-G24)} -> 0 | H25: {=SUM(H16:H23-H24)} -> 0 | I25: {=SUM(I16:I23-I24)} -> 0 | ... N25: {=SUM(N16:N23-N24)} -> 0
A26: UTILIDAD BRUTA | B26: =B14-B25 -> 0 | C26: =C14-C25 -> 0 | D26: =D14-D25 -> 0 | E26: =E14-E25 -> 0 | F26: =F14-F25 -> 0 | G26: =G14-G25 -> 0 | H26: =H14-H25 -> 0 | I26: =I14-I25 -> 0 | ... N26: =N14-N25 -> 0
A27: Margen Bruto % | B27: =IFERROR(B26/B14,0) -> 0 | C27: =IFERROR(C26/C14,0) -> 0 | D27: =IFERROR(D26/D14,0) -> 0 | E27: =IFERROR(E26/E14,0) -> 0 | F27: =IFERROR(F26/F14,0) -> 0 | G27: =IFERROR(G26/G14,0) -> 0 | H27: =IFERROR(H26/H14,0) -> 0 | I27: =IFERROR(I26/I14,0) -> 0 | ... N27: =IFERROR(N26/N14,0) -> 0
A28: GASTOS OPERACIONALES
A29: Gastos de Ventas
A30: Sueldos Área Ventas | B30: 0 | C30: 0 | D30: 0 | E30: 0 | F30: 0 | G30: 0 | H30: 0 | I30: 0 | J30: 0 | K30: 0 | L30: 0 | M30: 0 | N30: 0
A31: Comisiones | B31: 0 | C31: 0 | D31: 0 | E31: 0 | F31: 0 | G31: 0 | H31: 0 | I31: 0 | J31: 0 | K31: 0 | L31: 0 | M31: 0 | N31: 0
A32: Publicidad y Marketing | B32: 0 | C32: 0 | D32: 0 | E32: 0 | F32: 0 | G32: 0 | H32: 0 | I32: 0 | J32: 0 | K32: 0 | L32: 0 | M32: 0 | N32: 0
A33: Transporte y Distribución | B33: 0 | C33: 0 | D33: 0 | E33: 0 | F33: 0 | G33: 0 | H33: 0 | I33: 0 | J33: 0 | K33: 0 | L33: 0 | M33: 0 | N33: 0
A34: Otros Gastos Ventas | B34: 0 | C34: 0 | D34: 0 | E34: 0 | F34: 0 | G34: 0 | H34: 0 | I34: 0 | J34: 0 | K34: 0 | L34: 0 | M34: 0 | N34: 0
A35: Gastos de Administración
A36: Sueldos Área Administrativa | B36: 0 | C36: 0 | D36: 0 | E36: 0 | F36: 0 | G36: 0 | H36: 0 | I36: 0 | J36: 0 | K36: 0 | L36: 0 | M36: 0 | N36: 0
A37: Honorarios Profesionales | B37: 0 | C37: 0 | D37: 0 | E37: 0 | F37: 0 | G37: 0 | H37: 0 | I37: 0 | J37: 0 | K37: 0 | L37: 0 | M37: 0 | N37: 0
A38: Arriendo Oficinas | B38: 0 | C38: 0 | D38: 0 | E38: 0 | F38: 0 | G38: 0 | H38: 0 | I38: 0 | J38: 0 | K38: 0 | L38: 0 | M38: 0 | N38: 0
A39: Servicios Básicos | B39: 0 | C39: 0 | D39: 0 | E39: 0 | F39: 0 | G39: 0 | H39: 0 | I39: 0 | J39: 0 | K39: 0 | L39: 0 | M39: 0 | N39: 0
A40: Seguros | B40: 0 | C40: 0 | D40: 0 | E40: 0 | F40: 0 | G40: 0 | H40: 0 | I40: 0 | J40: 0 | K40: 0 | L40: 0 | M40: 0 | N40: 0
A41: Depreciación Activos Administrativos | B41: 0 | C41: 0 | D41: 0 | E41: 0 | F41: 0 | G41: 0 | H41: 0 | I41: 0 | J41: 0 | K41: 0 | L41: 0 | M41: 0 | N41: 0
A42: Amortización Intangibles | B42: 0 | C42: 0 | D42: 0 | E42: 0 | F42: 0 | G42: 0 | H42: 0 | I42: 0 | J42: 0 | K42: 0 | L42: 0 | M42: 0 | N42: 0
A43: Otros Gastos Administrativos | B43: 0 | C43: 0 | D43: 0 | E43: 0 | F43: 0 | G43: 0 | H43: 0 | I43: 0 | J43: 0 | K43: 0 | L43: 0 | M43: 0 | N43: 0
A44: TOTAL GASTOS OPERACIONALES | B44: =SUM(B29:B43) -> 0
A45: UTILIDAD OPERACIONAL (EBIT) | B45: =B26-B44 -> 0 | C45: =C26-C44 -> 0 | D45: =D26-D44 -> 0 | E45: =E26-E44 -> 0 | F45: =F26-F44 -> 0 | G45: =G26-G44 -> 0 | H45: =H26-H44 -> 0 | I45: =I26-I44 -> 0 | ... M45: =M26-M44 -> 0 | N45: =SUM(B45:M45) -> 0
A46: Margen Operacional % | B46: =IFERROR(B45/B14,0) -> 0 | C46: =IFERROR(C45/C14,0) -> 0 | D46: =IFERROR(D45/D14,0) -> 0 | E46: =IFERROR(E45/E14,0) -> 0 | F46: =IFERROR(F45/F14,0) -> 0 | G46: =IFERROR(G45/G14,0) -> 0 | H46: =IFERROR(H45/H14,0) -> 0 | I46: =IFERROR(I45/I14,0) -> 0 | ... N46: =IFERROR(N45/N14,0) -> 0
A47: OTROS INGRESOS Y GASTOS
A48: (+) Ingresos Financieros | B48: 0 | C48: 0 | D48: 0 | E48: 0 | F48: 0 | G48: 0 | H48: 0 | I48: 0 | J48: 0 | K48: 0 | L48: 0 | M48: 0 | N48: 0
A49: (+) Otros Ingresos No Operacionales | B49: 0 | C49: 0 | D49: 0 | E49: 0 | F49: 0 | G49: 0 | H49: 0 | I49: 0 | J49: 0 | K49: 0 | L49: 0 | M49: 0 | N49: 0
A50: (+) Utilidad en Venta de Activos | B50: 0 | C50: 0 | D50: 0 | E50: 0 | F50: 0 | G50: 0 | H50: 0 | I50: 0 | J50: 0 | K50: 0 | L50: 0 | M50: 0 | N50: 0
A51: (-) Gastos Financieros | B51: 0 | C51: 0 | D51: 0 | E51: 0 | F51: 0 | G51: 0 | H51: 0 | I51: 0 | J51: 0 | K51: 0 | L51: 0 | M51: 0 | N51: 0
A52: (-) Pérdida en Venta de Activos | B52: 0 | C52: 0 | D52: 0 | E52: 0 | F52: 0 | G52: 0 | H52: 0 | I52: 0 | J52: 0 | K52: 0 | L52: 0 | M52: 0 | N52: 0
A53: (-) Otros Gastos No Operacionales | B53: 0 | C53: 0 | D53: 0 | E53: 0 | F53: 0 | G53: 0 | H53: 0 | I53: 0 | J53: 0 | K53: 0 | L53: 0 | M53: 0 | N53: 0
A54: TOTAL OTROS INGRESOS (GASTOS) | B54: =SUM(B48:B50)-B51-B52-B53 -> 0 | C54: =SUM(C48:C50)-C51-C52-C53 -> 0 | D54: =SUM(D48:D50)-D51-D52-D53 -> 0 | E54: =SUM(E48:E50)-E51-E52-E53 -> 0 | F54: =SUM(F48:F50)-F51-F52-F53 -> 0 | G54: =SUM(G48:G50)-G51-G52-G53 -> 0 | H54: =SUM(H48:H50)-H51-H52-H53 -> 0 | I54: =SUM(I48:I50)-I51-I52-I53 -> 0 | ... N54: =SUM(N48:N50)-N51-N52-N53 -> 0
A55: UTILIDAD ANTES DE IMPUESTOS (EBT) | B55: =B45+B54 -> 0 | C55: =C45+C54 -> 0 | D55: =D45+D54 -> 0 | E55: =E45+E54 -> 0 | F55: =F45+F54 -> 0 | G55: =G45+G54 -> 0 | H55: =H45+H54 -> 0 | I55: =I45+I54 -> 0 | ... N55: =N45+N54 -> 0
A56: (-) Impuesto a la Renta (25%) | B56: =B55*0.25 -> 0 | C56: =C55*0.25 -> 0 | D56: =D55*0.25 -> 0 | E56: =E55*0.25 -> 0 | F56: =F55*0.25 -> 0 | G56: =G55*0.25 -> 0 | H56: =H55*0.25 -> 0 | I56: =I55*0.25 -> 0 | ... N56: =N55*0.25 -> 0
A57: UTILIDAD NETA | B57: =B55-B56 -> 0 | C57: =C55-C56 -> 0 | D57: =D55-D56 -> 0 | E57: =E55-E56 -> 0 | F57: =F55-F56 -> 0 | G57: =G55-G56 -> 0 | H57: =H55-H56 -> 0 | I57: =I55-I56 -> 0 | ... M57: =M55-M56 -> 0 | N57: =SUM(B57:M57) -> 0
A58: Margen Neto % | B58: =IFERROR(B57/B14,0) -> 0 | C58: =IFERROR(C57/C14,0) -> 0 | D58: =IFERROR(D57/D14,0) -> 0 | E58: =IFERROR(E57/E14,0) -> 0 | F58: =IFERROR(F57/F14,0) -> 0 | G58: =IFERROR(G57/G14,0) -> 0 | H58: =IFERROR(H57/H14,0) -> 0 | I58: =IFERROR(I57/I14,0) -> 0 | ... N58: =IFERROR(N57/N14,0) -> 0

Sheet P&L Productiva - Budget
A1: ESTADO DE RESULTADOS - EMPRESA PRODUCTIVA
A2: Escenario: Budget
A3: Cifras en USD
A5: Concepto | B5: Enero | C5: Febrero | D5: Marzo | E5: Abril | F5: Mayo | G5: Junio | H5: Julio | I5: Agosto | J5: Septiembre | K5: Octubre | L5: Noviembre | M5: Diciembre | N5: TOTAL AÑO
A6: INGRESOS OPERACIONALES
A7: Ventas Producto A | B7: 0 | C7: 0 | D7: 0 | E7: 0 | F7: 0 | G7: 0 | H7: 0 | I7: 0 | J7: 0 | K7: 0 | L7: 0 | M7: 0 | N7: 0
A8: Ventas Producto B | B8: 0 | C8: 0 | D8: 0 | E8: 0 | F8: 0 | G8: 0 | H8: 0 | I8: 0 | J8: 0 | K8: 0 | L8: 0 | M8: 0 | N8: 0
A9: Ventas Producto C | B9: 0 | C9: 0 | D9: 0 | E9: 0 | F9: 0 | G9: 0 | H9: 0 | I9: 0 | J9: 0 | K9: 0 | L9: 0 | M9: 0 | N9: 0
A10: Ventas Otros Productos | B10: 0 | C10: 0 | D10: 0 | E10: 0 | F10: 0 | G10: 0 | H10: 0 | I10: 0 | J10: 0 | K10: 0 | L10: 0 | M10: 0 | N10: =SUM(B10:M10) -> 0
A11: Total Ingresos Brutos | B11: =SUM(B7:B10) -> 0 | C11: =SUM(C7:C10) -> 0 | D11: =SUM(D7:D10) -> 0 | E11: =SUM(E7:E10) -> 0 | F11: =SUM(F7:F10) -> 0 | G11: =SUM(G7:G10) -> 0 | H11: =SUM(H7:H10) -> 0 | I11: =SUM(I7:I10) -> 0 | ... N11: =SUM(N7:N10) -> 0
A12: (-) Devoluciones y Descuentos | B12: 0 | C12: 0 | D12: 0 | E12: 0 | F12: 0 | G12: 0 | H12: 0 | I12: 0 | J12: 0 | K12: 0 | L12: 0 | M12: 0 | N12: 0
A13: (-) Bonificaciones | B13: 0 | C13: 0 | D13: 0 | E13: 0 | F13: 0 | G13: 0 | H13: 0 | I13: 0 | J13: 0 | K13: 0 | L13: 0 | M13: 0 | N13: =SUM(B13:M13) -> 0
A14: INGRESOS NETOS | B14: =SUM(B7:B11)-B12-B13 -> 0 | C14: =SUM(C7:C11)-C12-C13 -> 0 | D14: =SUM(D7:D11)-D12-D13 -> 0 | E14: =SUM(E7:E11)-E12-E13 -> 0 | F14: =SUM(F7:F11)-F12-F13 -> 0 | G14: =SUM(G7:G11)-G12-G13 -> 0 | H14: =SUM(H7:H11)-H12-H13 -> 0 | I14: =SUM(I7:I11)-I12-I13 -> 0 | ... N14: =SUM(N7:N11)-N12-N13 -> 0
A15: COSTO DE VENTAS
A16: Inventario Inicial | B16: 0 | C16: 0 | D16: 0 | E16: 0 | F16: 0 | G16: 0 | H16: 0 | I16: 0 | J16: 0 | K16: 0 | L16: 0 | M16: 0 | N16: 0
A17: (+) Compras de Materia Prima | B17: 0 | C17: 0 | D17: 0 | E17: 0 | F17: 0 | G17: 0 | H17: 0 | I17: 0 | J17: 0 | K17: 0 | L17: 0 | M17: 0 | N17: 0
A18: (+) Mano de Obra Directa | B18: 0 | C18: 0 | D18: 0 | E18: 0 | F18: 0 | G18: 0 | H18: 0 | I18: 0 | J18: 0 | K18: 0 | L18: 0 | M18: 0 | N18: 0
A19: (+) Costos Indirectos de Fabricación | B19: 0 | C19: 0 | D19: 0 | E19: 0 | F19: 0 | G19: 0 | H19: 0 | I19: 0 | J19: 0 | K19: 0 | L19: 0 | M19: 0 | N19: 0
A20: Depreciación Equipos Producción | B20: 0 | C20: 0 | D20: 0 | E20: 0 | F20: 0 | G20: 0 | H20: 0 | I20: 0 | J20: 0 | K20: 0 | L20: 0 | M20: 0 | N20: 0
A21: Servicios Planta | B21: 0 | C21: 0 | D21: 0 | E21: 0 | F21: 0 | G21: 0 | H21: 0 | I21: 0 | J21: 0 | K21: 0 | L21: 0 | M21: 0 | N21: 0
A22: Mantenimiento Equipos | B22: 0 | C22: 0 | D22: 0 | E22: 0 | F22: 0 | G22: 0 | H22: 0 | I22: 0 | J22: 0 | K22: 0 | L22: 0 | M22: 0 | N22: 0
A23: Otros CIF | B23: 0 | C23: 0 | D23: 0 | E23: 0 | F23: 0 | G23: 0 | H23: 0 | I23: 0 | J23: 0 | K23: 0 | L23: 0 | M23: 0 | N23: 0
A24: (-) Inventario Final | B24: 0 | C24: 0 | D24: 0 | E24: 0 | F24: 0 | G24: 0 | H24: 0 | I24: 0 | J24: 0 | K24: 0 | L24: 0 | M24: 0 | N24: 0
A25: COSTO DE VENTAS TOTAL | B25: {=SUM(B16:B23-B24)} -> 0 | C25: {=SUM(C16:C23-C24)} -> 0 | D25: {=SUM(D16:D23-D24)} -> 0 | E25: {=SUM(E16:E23-E24)} -> 0 | F25: {=SUM(F16:F23-F24)} -> 0 | G25: {=SUM(G16:G23-G24)} -> 0 | H25: {=SUM(H16:H23-H24)} -> 0 | I25: {=SUM(I16:I23-I24)} -> 0 | ... N25: {=SUM(N16:N23-N24)} -> 0
A26: UTILIDAD BRUTA | B26: =B14-B25 -> 0 | C26: =C14-C25 -> 0 | D26: =D14-D25 -> 0 | E26: =E14-E25 -> 0 | F26: =F14-F25 -> 0 | G26: =G14-G25 -> 0 | H26: =H14-H25 -> 0 | I26: =I14-I25 -> 0 | ... N26: =N14-N25 -> 0
A27: Margen Bruto % | B27: =IFERROR(B26/B14,0) -> 0 | C27: =IFERROR(C26/C14,0) -> 0 | D27: =IFERROR(D26/D14,0) -> 0 | E27: =IFERROR(E26/E14,0) -> 0 | F27: =IFERROR(F26/F14,0) -> 0 | G27: =IFERROR(G26/G14,0) -> 0 | H27: =IFERROR(H26/H14,0) -> 0 | I27: =IFERROR(I26/I14,0) -> 0 | ... N27: =IFERROR(N26/N14,0) -> 0
A28: GASTOS OPERACIONALES
A29: Gastos de Ventas
A30: Sueldos Área Ventas | B30: 0 | C30: 0 | D30: 0 | E30: 0 | F30: 0 | G30: 0 | H30: 0 | I30: 0 | J30: 0 | K30: 0 | L30: 0 | M30: 0 | N30: 0
A31: Comisiones | B31: 0 | C31: 0 | D31: 0 | E31: 0 | F31: 0 | G31: 0 | H31: 0 | I31: 0 | J31: 0 | K31: 0 | L31: 0 | M31: 0 | N31: 0
A32: Publicidad y Marketing | B32: 0 | C32: 0 | D32: 0 | E32: 0 | F32: 0 | G32: 0 | H32: 0 | I32: 0 | J32: 0 | K32: 0 | L32: 0 | M32: 0 | N32: 0
A33: Transporte y Distribución | B33: 0 | C33: 0 | D33: 0 | E33: 0 | F33: 0 | G33: 0 | H33: 0 | I33: 0 | J33: 0 | K33: 0 | L33: 0 | M33: 0 | N33: 0
A34: Otros Gastos Ventas | B34: 0 | C34: 0 | D34: 0 | E34: 0 | F34: 0 | G34: 0 | H34: 0 | I34: 0 | J34: 0 | K34: 0 | L34: 0 | M34: 0 | N34: 0
A35: Gastos de Administración
A36: Sueldos Área Administrativa | B36: 0 | C36: 0 | D36: 0 | E36: 0 | F36: 0 | G36: 0 | H36: 0 | I36: 0 | J36: 0 | K36: 0 | L36: 0 | M36: 0 | N36: 0
A37: Honorarios Profesionales | B37: 0 | C37: 0 | D37: 0 | E37: 0 | F37: 0 | G37: 0 | H37: 0 | I37: 0 | J37: 0 | K37: 0 | L37: 0 | M37: 0 | N37: 0
A38: Arriendo Oficinas | B38: 0 | C38: 0 | D38: 0 | E38: 0 | F38: 0 | G38: 0 | H38: 0 | I38: 0 | J38: 0 | K38: 0 | L38: 0 | M38: 0 | N38: 0
A39: Servicios Básicos | B39: 0 | C39: 0 | D39: 0 | E39: 0 | F39: 0 | G39: 0 | H39: 0 | I39: 0 | J39: 0 | K39: 0 | L39: 0 | M39: 0 | N39: 0
A40: Seguros | B40: 0 | C40: 0 | D40: 0 | E40: 0 | F40: 0 | G40: 0 | H40: 0 | I40: 0 | J40: 0 | K40: 0 | L40: 0 | M40: 0 | N40: 0
A41: Depreciación Activos Administrativos | B41: 0 | C41: 0 | D41: 0 | E41: 0 | F41: 0 | G41: 0 | H41: 0 | I41: 0 | J41: 0 | K41: 0 | L41: 0 | M41: 0 | N41: 0
A42: Amortización Intangibles | B42: 0 | C42: 0 | D42: 0 | E42: 0 | F42: 0 | G42: 0 | H42: 0 | I42: 0 | J42: 0 | K42: 0 | L42: 0 | M42: 0 | N42: 0
A43: Otros Gastos Administrativos | B43: 0 | C43: 0 | D43: 0 | E43: 0 | F43: 0 | G43: 0 | H43: 0 | I43: 0 | J43: 0 | K43: 0 | L43: 0 | M43: 0 | N43: 0
A44: TOTAL GASTOS OPERACIONALES | B44: =SUM(B30:B43) -> 0 | C44: =SUM(C30:C43) -> 0 | D44: =SUM(D30:D43) -> 0 | E44: =SUM(E30:E43) -> 0 | F44: =SUM(F30:F43) -> 0 | G44: =SUM(G30:G43) -> 0 | H44: =SUM(H30:H43) -> 0 | I44: =SUM(I30:I43) -> 0 | ... N44: =SUM(N30:N43) -> 0
A45: UTILIDAD OPERACIONAL (EBIT) | B45: =B26-B44 -> 0 | C45: =C26-C44 -> 0 | D45: =D26-D44 -> 0 | E45: =E26-E44 -> 0 | F45: =F26-F44 -> 0 | G45: =G26-G44 -> 0 | H45: =H26-H44 -> 0 | I45: =I26-I44 -> 0 | ... N45: =N26-N44 -> 0
A46: Margen Operacional % | B46: =IFERROR(B45/B14,0) -> 0 | C46: =IFERROR(C45/C14,0) -> 0 | D46: =IFERROR(D45/D14,0) -> 0 | E46: =IFERROR(E45/E14,0) -> 0 | F46: =IFERROR(F45/F14,0) -> 0 | G46: =IFERROR(G45/G14,0) -> 0 | H46: =IFERROR(H45/H14,0) -> 0 | I46: =IFERROR(I45/I14,0) -> 0 | ... N46: =IFERROR(N45/N14,0) -> 0
A47: OTROS INGRESOS Y GASTOS
A48: (+) Ingresos Financieros | B48: 0 | C48: 0 | D48: 0 | E48: 0 | F48: 0 | G48: 0 | H48: 0 | I48: 0 | J48: 0 | K48: 0 | L48: 0 | M48: 0 | N48: 0
A49: (+) Otros Ingresos No Operacionales | B49: 0 | C49: 0 | D49: 0 | E49: 0 | F49: 0 | G49: 0 | H49: 0 | I49: 0 | J49: 0 | K49: 0 | L49: 0 | M49: 0 | N49: 0
A50: (+) Utilidad en Venta de Activos | B50: 0 | C50: 0 | D50: 0 | E50: 0 | F50: 0 | G50: 0 | H50: 0 | I50: 0 | J50: 0 | K50: 0 | L50: 0 | M50: 0 | N50: 0
A51: (-) Gastos Financieros | B51: 0 | C51: 0 | D51: 0 | E51: 0 | F51: 0 | G51: 0 | H51: 0 | I51: 0 | J51: 0 | K51: 0 | L51: 0 | M51: 0 | N51: 0
A52: (-) Pérdida en Venta de Activos | B52: 0 | C52: 0 | D52: 0 | E52: 0 | F52: 0 | G52: 0 | H52: 0 | I52: 0 | J52: 0 | K52: 0 | L52: 0 | M52: 0 | N52: 0
A53: (-) Otros Gastos No Operacionales | B53: 0 | C53: 0 | D53: 0 | E53: 0 | F53: 0 | G53: 0 | H53: 0 | I53: 0 | J53: 0 | K53: 0 | L53: 0 | M53: 0 | N53: 0
A54: TOTAL OTROS INGRESOS (GASTOS) | B54: =SUM(B48:B50)-B51-B52-B53 -> 0 | C54: =SUM(C48:C50)-C51-C52-C53 -> 0 | D54: =SUM(D48:D50)-D51-D52-D53 -> 0 | E54: =SUM(E48:E50)-E51-E52-E53 -> 0 | F54: =SUM(F48:F50)-F51-F52-F53 -> 0 | G54: =SUM(G48:G50)-G51-G52-G53 -> 0 | H54: =SUM(H48:H50)-H51-H52-H53 -> 0 | I54: =SUM(I48:I50)-I51-I52-I53 -> 0 | ... N54: =SUM(N48:N50)-N51-N52-N53 -> 0
A55: UTILIDAD ANTES DE IMPUESTOS (EBT) | B55: =B45+B54 -> 0 | C55: =C45+C54 -> 0 | D55: =D45+D54 -> 0 | E55: =E45+E54 -> 0 | F55: =F45+F54 -> 0 | G55: =G45+G54 -> 0 | H55: =H45+H54 -> 0 | I55: =I45+I54 -> 0 | ... N55: =N45+N54 -> 0
A56: (-) Impuesto a la Renta (25%) | B56: =B55*0.25 -> 0 | C56: =C55*0.25 -> 0 | D56: =D55*0.25 -> 0 | E56: =E55*0.25 -> 0 | F56: =F55*0.25 -> 0 | G56: =G55*0.25 -> 0 | H56: =H55*0.25 -> 0 | I56: =I55*0.25 -> 0 | ... N56: =N55*0.25 -> 0
A57: UTILIDAD NETA | B57: =B55-B56 -> 0 | C57: =C55-C56 -> 0 | D57: =D55-D56 -> 0 | E57: =E55-E56 -> 0 | F57: =F55-F56 -> 0 | G57: =G55-G56 -> 0 | H57: =H55-H56 -> 0 | I57: =I55-I56 -> 0 | ... N57: =N55-N56 -> 0
A58: Margen Neto % | B58: =IFERROR(B57/B14,0) -> 0 | C58: =IFERROR(C57/C14,0) -> 0 | D58: =IFERROR(D57/D14,0) -> 0 | E58: =IFERROR(E57/E14,0) -> 0 | F58: =IFERROR(F57/F14,0) -> 0 | G58: =IFERROR(G57/G14,0) -> 0 | H58: =IFERROR(H57/H14,0) -> 0 | I58: =IFERROR(I57/I14,0) -> 0 | ... N58: =IFERROR(N57/N14,0) -> 0

Sheet P&L Productiva - Forecast
A1: ESTADO DE RESULTADOS - EMPRESA PRODUCTIVA
A2: Escenario: Forecast
A3: Cifras en USD
A5: Concepto | B5: Enero | C5: Febrero | D5: Marzo | E5: Abril | F5: Mayo | G5: Junio | H5: Julio | I5: Agosto | J5: Septiembre | K5: Octubre | L5: Noviembre | M5: Diciembre | N5: TOTAL AÑO
A6: INGRESOS OPERACIONALES
A7: Ventas Producto A | B7: 0 | C7: 0 | D7: 0 | E7: 0 | F7: 0 | G7: 0 | H7: 0 | I7: 0 | J7: 0 | K7: 0 | L7: 0 | M7: 0 | N7: 0
A8: Ventas Producto B | B8: 0 | C8: 0 | D8: 0 | E8: 0 | F8: 0 | G8: 0 | H8: 0 | I8: 0 | J8: 0 | K8: 0 | L8: 0 | M8: 0 | N8: 0
A9: Ventas Producto C | B9: 0 | C9: 0 | D9: 0 | E9: 0 | F9: 0 | G9: 0 | H9: 0 | I9: 0 | J9: 0 | K9: 0 | L9: 0 | M9: 0 | N9: 0
A10: Ventas Otros Productos | B10: 0 | C10: 0 | D10: 0 | E10: 0 | F10: 0 | G10: 0 | H10: 0 | I10: 0 | J10: 0 | K10: 0 | L10: 0 | M10: 0 | N10: =SUM(B10:M10) -> 0
A11: Total Ingresos Brutos | B11: =SUM(B7:B10) -> 0 | C11: =SUM(C7:C10) -> 0 | D11: =SUM(D7:D10) -> 0 | E11: =SUM(E7:E10) -> 0 | F11: =SUM(F7:F10) -> 0 | G11: =SUM(G7:G10) -> 0 | H11: =SUM(H7:H10) -> 0 | I11: =SUM(I7:I10) -> 0 | ... N11: =SUM(N7:N10) -> 0
A12: (-) Devoluciones y Descuentos | B12: 0 | C12: 0 | D12: 0 | E12: 0 | F12: 0 | G12: 0 | H12: 0 | I12: 0 | J12: 0 | K12: 0 | L12: 0 | M12: 0 | N12: 0
A13: (-) Bonificaciones | B13: 0 | C13: 0 | D13: 0 | E13: 0 | F13: 0 | G13: 0 | H13: 0 | I13: 0 | J13: 0 | K13: 0 | L13: 0 | M13: 0 | N13: =SUM(B13:M13) -> 0
A14: INGRESOS NETOS | B14: {=SUM(B7:B11-B12-B13)} -> 0 | C14: {=SUM(C7:C11-C12-C13)} -> 0 | D14: {=SUM(D7:D11-D12-D13)} -> 0 | E14: {=SUM(E7:E11-E12-E13)} -> 0 | F14: {=SUM(F7:F11-F12-F13)} -> 0 | G14: {=SUM(G7:G11-G12-G13)} -> 0 | H14: {=SUM(H7:H11-H12-H13)} -> 0 | I14: {=SUM(I7:I11-I12-I13)} -> 0 | ... N14: {=SUM(N7:N11-N12-N13)} -> 0
A15: COSTO DE VENTAS
A16: Inventario Inicial | B16: 0 | C16: 0 | D16: 0 | E16: 0 | F16: 0 | G16: 0 | H16: 0 | I16: 0 | J16: 0 | K16: 0 | L16: 0 | M16: 0 | N16: 0
A17: (+) Compras de Materia Prima | B17: 0 | C17: 0 | D17: 0 | E17: 0 | F17: 0 | G17: 0 | H17: 0 | I17: 0 | J17: 0 | K17: 0 | L17: 0 | M17: 0 | N17: 0
A18: (+) Mano de Obra Directa | B18: 0 | C18: 0 | D18: 0 | E18: 0 | F18: 0 | G18: 0 | H18: 0 | I18: 0 | J18: 0 | K18: 0 | L18: 0 | M18: 0 | N18: 0
A19: (+) Costos Indirectos de Fabricación | B19: 0 | C19: 0 | D19: 0 | E19: 0 | F19: 0 | G19: 0 | H19: 0 | I19: 0 | J19: 0 | K19: 0 | L19: 0 | M19: 0 | N19: 0
A20: Depreciación Equipos Producción | B20: 0 | C20: 0 | D20: 0 | E20: 0 | F20: 0 | G20: 0 | H20: 0 | I20: 0 | J20: 0 | K20: 0 | L20: 0 | M20: 0 | N20: 0
A21: Servicios Planta | B21: 0 | C21: 0 | D21: 0 | E21: 0 | F21: 0 | G21: 0 | H21: 0 | I21: 0 | J21: 0 | K21: 0 | L21: 0 | M21: 0 | N21: 0
A22: Mantenimiento Equipos | B22: 0 | C22: 0 | D22: 0 | E22: 0 | F22: 0 | G22: 0 | H22: 0 | I22: 0 | J22: 0 | K22: 0 | L22: 0 | M22: 0 | N22: 0
A23: Otros CIF | B23: 0 | C23: 0 | D23: 0 | E23: 0 | F23: 0 | G23: 0 | H23: 0 | I23: 0 | J23: 0 | K23: 0 | L23: 0 | M23: 0 | N23: 0
A24: (-) Inventario Final | B24: 0 | C24: 0 | D24: 0 | E24: 0 | F24: 0 | G24: 0 | H24: 0 | I24: 0 | J24: 0 | K24: 0 | L24: 0 | M24: 0 | N24: 0
A25: COSTO DE VENTAS TOTAL | B25: {=SUM(B16:B23-B24)} -> 0 | C25: {=SUM(C16:C23-C24)} -> 0 | D25: {=SUM(D16:D23-D24)} -> 0 | E25: {=SUM(E16:E23-E24)} -> 0 | F25: {=SUM(F16:F23-F24)} -> 0 | G25: {=SUM(G16:G23-G24)} -> 0 | H25: {=SUM(H16:H23-H24)} -> 0 | I25: {=SUM(I16:I23-I24)} -> 0 | ... N25: {=SUM(N16:N23-N24)} -> 0
A26: UTILIDAD BRUTA | B26: =B14-B25 -> 0 | C26: =C14-C25 -> 0 | D26: =D14-D25 -> 0 | E26: =E14-E25 -> 0 | F26: =F14-F25 -> 0 | G26: =G14-G25 -> 0 | H26: =H14-H25 -> 0 | I26: =I14-I25 -> 0 | ... N26: =N14-N25 -> 0
A27: Margen Bruto % | B27: =IFERROR(B26/B14,0) -> 0 | C27: =IFERROR(C26/C14,0) -> 0 | D27: =IFERROR(D26/D14,0) -> 0 | E27: =IFERROR(E26/E14,0) -> 0 | F27: =IFERROR(F26/F14,0) -> 0 | G27: =IFERROR(G26/G14,0) -> 0 | H27: =IFERROR(H26/H14,0) -> 0 | I27: =IFERROR(I26/I14,0) -> 0 | ... N27: =IFERROR(N26/N14,0) -> 0
A28: GASTOS OPERACIONALES
A29: Gastos de Ventas
A30: Sueldos Área Ventas | B30: 0 | C30: 0 | D30: 0 | E30: 0 | F30: 0 | G30: 0 | H30: 0 | I30: 0 | J30: 0 | K30: 0 | L30: 0 | M30: 0 | N30: 0
A31: Comisiones | B31: 0 | C31: 0 | D31: 0 | E31: 0 | F31: 0 | G31: 0 | H31: 0 | I31: 0 | J31: 0 | K31: 0 | L31: 0 | M31: 0 | N31: 0
A32: Publicidad y Marketing | B32: 0 | C32: 0 | D32: 0 | E32: 0 | F32: 0 | G32: 0 | H32: 0 | I32: 0 | J32: 0 | K32: 0 | L32: 0 | M32: 0 | N32: 0
A33: Transporte y Distribución | B33: 0 | C33: 0 | D33: 0 | E33: 0 | F33: 0 | G33: 0 | H33: 0 | I33: 0 | J33: 0 | K33: 0 | L33: 0 | M33: 0 | N33: 0
A34: Otros Gastos Ventas | B34: 0 | C34: 0 | D34: 0 | E34: 0 | F34: 0 | G34: 0 | H34: 0 | I34: 0 | J34: 0 | K34: 0 | L34: 0 | M34: 0 | N34: 0
A35: Gastos de Administración
A36: Sueldos Área Administrativa | B36: 0 | C36: 0 | D36: 0 | E36: 0 | F36: 0 | G36: 0 | H36: 0 | I36: 0 | J36: 0 | K36: 0 | L36: 0 | M36: 0 | N36: 0
A37: Honorarios Profesionales | B37: 0 | C37: 0 | D37: 0 | E37: 0 | F37: 0 | G37: 0 | H37: 0 | I37: 0 | J37: 0 | K37: 0 | L37: 0 | M37: 0 | N37: 0
A38: Arriendo Oficinas | B38: 0 | C38: 0 | D38: 0 | E38: 0 | F38: 0 | G38: 0 | H38: 0 | I38: 0 | J38: 0 | K38: 0 | L38: 0 | M38: 0 | N38: 0
A39: Servicios Básicos | B39: 0 | C39: 0 | D39: 0 | E39: 0 | F39: 0 | G39: 0 | H39: 0 | I39: 0 | J39: 0 | K39: 0 | L39: 0 | M39: 0 | N39: 0
A40: Seguros | B40: 0 | C40: 0 | D40: 0 | E40: 0 | F40: 0 | G40: 0 | H40: 0 | I40: 0 | J40: 0 | K40: 0 | L40: 0 | M40: 0 | N40: 0
A41: Depreciación Activos Administrativos | B41: 0 | C41: 0 | D41: 0 | E41: 0 | F41: 0 | G41: 0 | H41: 0 | I41: 0 | J41: 0 | K41: 0 | L41: 0 | M41: 0 | N41: 0
A42: Amortización Intangibles | B42: 0 | C42: 0 | D42: 0 | E42: 0 | F42: 0 | G42: 0 | H42: 0 | I42: 0 | J42: 0 | K42: 0 | L42: 0 | M42: 0 | N42: 0
A43: Otros Gastos Administrativos | B43: 0 | C43: 0 | D43: 0 | E43: 0 | F43: 0 | G43: 0 | H43: 0 | I43: 0 | J43: 0 | K43: 0 | L43: 0 | M43: 0 | N43: 0
A44: TOTAL GASTOS OPERACIONALES | B44: =SUM(B29:B43) -> 0 | C44: =SUM(C29:C43) -> 0 | D44: =SUM(D29:D43) -> 0 | E44: =SUM(E29:E43) -> 0 | F44: =SUM(F29:F43) -> 0 | G44: =SUM(G29:G43) -> 0 | H44: =SUM(H29:H43) -> 0 | I44: =SUM(I29:I43) -> 0 | ... N44: =SUM(N29:N43) -> 0
A45: UTILIDAD OPERACIONAL (EBIT) | B45: =B26-B44 -> 0 | C45: =C26-C44 -> 0 | D45: =D26-D44 -> 0 | E45: =E26-E44 -> 0 | F45: =F26-F44 -> 0 | G45: =G26-G44 -> 0 | H45: =H26-H44 -> 0 | I45: =I26-I44 -> 0 | ... N45: =N26-N44 -> 0
A46: Margen Operacional % | B46: =IFERROR(B45/B14,0) -> 0 | C46: =IFERROR(C45/C14,0) -> 0 | D46: =IFERROR(D45/D14,0) -> 0 | E46: =IFERROR(E45/E14,0) -> 0 | F46: =IFERROR(F45/F14,0) -> 0 | G46: =IFERROR(G45/G14,0) -> 0 | H46: =IFERROR(H45/H14,0) -> 0 | I46: =IFERROR(I45/I14,0) -> 0 | ... N46: =IFERROR(N45/N14,0) -> 0
A47: OTROS INGRESOS Y GASTOS
A48: (+) Ingresos Financieros | B48: 0 | C48: 0 | D48: 0 | E48: 0 | F48: 0 | G48: 0 | H48: 0 | I48: 0 | J48: 0 | K48: 0 | L48: 0 | M48: 0 | N48: 0
A49: (+) Otros Ingresos No Operacionales | B49: 0 | C49: 0 | D49: 0 | E49: 0 | F49: 0 | G49: 0 | H49: 0 | I49: 0 | J49: 0 | K49: 0 | L49: 0 | M49: 0 | N49: 0
A50: (+) Utilidad en Venta de Activos | B50: 0 | C50: 0 | D50: 0 | E50: 0 | F50: 0 | G50: 0 | H50: 0 | I50: 0 | J50: 0 | K50: 0 | L50: 0 | M50: 0 | N50: 0
A51: (-) Gastos Financieros | B51: 0 | C51: 0 | D51: 0 | E51: 0 | F51: 0 | G51: 0 | H51: 0 | I51: 0 | J51: 0 | K51: 0 | L51: 0 | M51: 0 | N51: 0
A52: (-) Pérdida en Venta de Activos | B52: 0 | C52: 0 | D52: 0 | E52: 0 | F52: 0 | G52: 0 | H52: 0 | I52: 0 | J52: 0 | K52: 0 | L52: 0 | M52: 0 | N52: 0
A53: (-) Otros Gastos No Operacionales | B53: 0 | C53: 0 | D53: 0 | E53: 0 | F53: 0 | G53: 0 | H53: 0 | I53: 0 | J53: 0 | K53: 0 | L53: 0 | M53: 0 | N53: 0
A54: TOTAL OTROS INGRESOS (GASTOS) | B54: =SUM(B48:B50)-B51-B52-B53 -> 0 | C54: =SUM(C48:C50)-C51-C52-C53 -> 0 | D54: =SUM(D48:D50)-D51-D52-D53 -> 0 | E54: =SUM(E48:E50)-E51-E52-E53 -> 0 | F54: =SUM(F48:F50)-F51-F52-F53 -> 0 | G54: =SUM(G48:G50)-G51-G52-G53 -> 0 | H54: =SUM(H48:H50)-H51-H52-H53 -> 0 | I54: =SUM(I48:I50)-I51-I52-I53 -> 0 | ... N54: =SUM(N48:N50)-N51-N52-N53 -> 0
A55: UTILIDAD ANTES DE IMPUESTOS (EBT) | B55: =B45+B54 -> 0 | C55: =C45+C54 -> 0 | D55: =D45+D54 -> 0 | E55: =E45+E54 -> 0 | F55: =F45+F54 -> 0 | G55: =G45+G54 -> 0 | H55: =H45+H54 -> 0 | I55: =I45+I54 -> 0 | ... M55: =M45+M54 -> 0 | N55: =SUM(B55:M55) -> 0
A56: (-) Impuesto a la Renta (27%) | B56: =B55*0.25 -> 0 | C56: =C55*0.25 -> 0 | D56: =D55*0.25 -> 0 | E56: =E55*0.25 -> 0 | F56: =F55*0.25 -> 0 | G56: =G55*0.25 -> 0 | H56: =H55*0.25 -> 0 | I56: =I55*0.25 -> 0 | ... N56: =N55*0.25 -> 0
A57: UTILIDAD NETA | B57: =B55-B56 -> 0 | C57: =C55-C56 -> 0 | D57: =D55-D56 -> 0 | E57: =E55-E56 -> 0 | F57: =F55-F56 -> 0 | G57: =G55-G56 -> 0 | H57: =H55-H56 -> 0 | I57: =I55-I56 -> 0 | ... N57: =N55-N56 -> 0
A58: Margen Neto % | B58: =IFERROR(B57/B14,0) -> 0 | C58: =IFERROR(C57/C14,0) -> 0 | D58: =IFERROR(D57/D14,0) -> 0 | E58: =IFERROR(E57/E14,0) -> 0 | F58: =IFERROR(F57/F14,0) -> 0 | G58: =IFERROR(G57/G14,0) -> 0 | H58: =IFERROR(H57/H14,0) -> 0 | I58: =IFERROR(I57/I14,0) -> 0 | ... N58: =IFERROR(N57/N14,0) -> 0

Sheet P&L Servicios - Real
A1: ESTADO DE RESULTADOS - EMPRESA DE SERVICIOS
A2: Escenario: Real
A3: Cifras en USD
A5: Concepto | B5: Enero | C5: Febrero | D5: Marzo | E5: Abril | F5: Mayo | G5: Junio | H5: Julio | I5: Agosto | J5: Septiembre | K5: Octubre | L5: Noviembre | M5: Diciembre | N5: TOTAL AÑO
A6: INGRESOS POR SERVICIOS
A7: Servicios de Consultoría | B7: 2870000 | C7: 2870000 | D7: 2870000 | E7: 2870000 | F7: 2870000 | G7: 2870000 | H7: 2870000 | I7: 2870000 | J7: 2870000 | K7: 2870000 | L7: 2870000 | M7: 2870000 | N7: =SUM(B7:M7) -> 34440000
A8: Servicios de Asesoría | B8: 270000 | C8: 270000 | D8: 270000 | E8: 270000 | F8: 270000 | G8: 270000 | H8: 270000 | I8: 270000 | J8: 270000 | K8: 270000 | L8: 270000 | M8: 270000 | N8: =SUM(B8:M8) -> 3240000
A9: Servicios de Capacitación | B9: 0 | C9: 0 | D9: 0 | E9: 0 | F9: 0 | G9: 0 | H9: 0 | I9: 0 | J9: 0 | K9: 0 | L9: 0 | M9: 0 | N9: =SUM(B9:M9) -> 0
A10: Servicios de Soporte Técnico | B10: 0 | C10: 0 | D10: 0 | E10: 0 | F10: 0 | G10: 0 | H10: 0 | I10: 0 | J10: 0 | K10: 0 | L10: 0 | M10: 0 | N10: =SUM(B10:M10) -> 0
A11: Servicios de Mantenimiento | B11: 0 | C11: 0 | D11: 0 | E11: 0 | F11: 0 | G11: 0 | H11: 0 | I11: 0 | J11: 0 | K11: 0 | L11: 0 | M11: 0 | N11: =SUM(B11:M11) -> 0
A12: Otros Servicios | B12: 310000 | C12: 310000 | D12: 310000 | E12: 310000 | F12: 310000 | G12: 310000 | H12: 310000 | I12: 310000 | J12: 310000 | K12: 310000 | L12: 310000 | M12: 310000 | N12: =SUM(B12:M12) -> 3720000
A13: Total Ingresos Brutos | B13: =SUM(B7:B12) -> 3450000 | C13: =SUM(C7:C12) -> 3450000 | D13: =SUM(D7:D12) -> 3450000 | E13: =SUM(E7:E12) -> 3450000 | F13: =SUM(F7:F12) -> 3450000 | G13: =SUM(G7:G12) -> 3450000 | H13: =SUM(H7:H12) -> 3450000 | I13: =SUM(I7:I12) -> 3450000 | ... N13: =SUM(N7:N12) -> 41400000
A14: (-) Descuentos por Pronto Pago | B14: 0 | C14: 0 | D14: 0 | E14: 0 | F14: 0 | G14: 0 | H14: 0 | I14: 0 | J14: 0 | K14: 0 | L14: 0 | M14: 0 | N14: 0
A15: (-) Devoluciones | B15: 0 | C15: 0 | D15: 0 | E15: 0 | F15: 0 | G15: 0 | H15: 0 | I15: 0 | J15: 0 | K15: 0 | L15: 0 | M15: 0 | N15: =SUM(B15:M15) -> 0
A16: INGRESOS NETOS | B16: =+B13-B14-B15 -> 3450000 | C16: =+C13-C14-C15 -> 3450000 | D16: =+D13-D14-D15 -> 3450000 | E16: =+E13-E14-E15 -> 3450000 | F16: =+F13-F14-F15 -> 3450000 | G16: =+G13-G14-G15 -> 3450000 | H16: =+H13-H14-H15 -> 3450000 | I16: =+I13-I14-I15 -> 3450000 | ... M16: =+M13-M14-M15 -> 3450000 | N16: =SUM(B16:M16) -> 41400000
A17: COSTO DE SERVICIOS
A18: Personal Directo
A19: Sueldos Personal Operativo | B19: 2200000 | C19: 2200000 | D19: 2200000 | E19: 2200000 | F19: 2200000 | G19: 2200000 | H19: 2200000 | I19: 2200000 | J19: 2200000 | K19: 2200000 | L19: 2200000 | M19: 2200000 | N19: =SUM(B19:M19) -> 26400000
A20: Honorarios Consultores | B20: 0 | C20: 0 | D20: 0 | E20: 0 | F20: 0 | G20: 0 | H20: 0 | I20: 0 | J20: 0 | K20: 0 | L20: 0 | M20: 0 | N20: =SUM(B20:M20) -> 0
A21: Beneficios Sociales Personal Directo | B21: 0 | C21: 0 | D21: 0 | E21: 0 | F21: 0 | G21: 0 | H21: 0 | I21: 0 | J21: 0 | K21: 0 | L21: 0 | M21: 0 | N21: =SUM(B21:M21) -> 0
A22: Capacitación Personal | B22: 0 | C22: 0 | D22: 0 | E22: 0 | F22: 0 | G22: 0 | H22: 0 | I22: 0 | J22: 0 | K22: 0 | L22: 0 | M22: 0 | N22: =SUM(B22:M22) -> 0
A23: Costos Directos del Servicio
A24: Materiales y Suministros | B24: 0 | C24: 0 | D24: 0 | E24: 0 | F24: 0 | G24: 0 | H24: 0 | I24: 0 | J24: 0 | K24: 0 | L24: 0 | M24: 0 | N24: =SUM(B24:M24) -> 0
A25: Software y Licencias | B25: 0 | C25: 0 | D25: 0 | E25: 0 | F25: 0 | G25: 0 | H25: 0 | I25: 0 | J25: 0 | K25: 0 | L25: 0 | M25: 0 | N25: =SUM(B25:M25) -> 0
A26: Equipamiento Especializado | B26: 0 | C26: 0 | D26: 0 | E26: 0 | F26: 0 | G26: 0 | H26: 0 | I26: 0 | J26: 0 | K26: 0 | L26: 0 | M26: 0 | N26: =SUM(B26:M26) -> 0
A27: Subcontrataciones | B27: 0 | C27: 0 | D27: 0 | E27: 0 | F27: 0 | G27: 0 | H27: 0 | I27: 0 | J27: 0 | K27: 0 | L27: 0 | M27: 0 | N27: =SUM(B27:M27) -> 0
A28: Viáticos y Movilización | B28: 300000 | C28: 300000 | D28: 300000 | E28: 300000 | F28: 300000 | G28: 300000 | H28: 300000 | I28: 300000 | J28: 300000 | K28: 300000 | L28: 300000 | M28: 300000 | N28: =SUM(B28:M28) -> 3600000
A29: COSTO DE SERVICIOS TOTAL | B29: =SUM(B19:B28) -> 2500000 | C29: =SUM(C19:C28) -> 2500000 | D29: =SUM(D19:D28) -> 2500000 | E29: =SUM(E19:E28) -> 2500000 | F29: =SUM(F19:F28) -> 2500000 | G29: =SUM(G19:G28) -> 2500000 | H29: =SUM(H19:H28) -> 2500000 | I29: =SUM(I19:I28) -> 2500000 | ... M29: =SUM(M19:M28) -> 2500000 | N29: =SUM(B29:M29) -> 30000000
A30: UTILIDAD BRUTA | B30: =B16-B29 -> 950000 | C30: =C16-C29 -> 950000 | D30: =D16-D29 -> 950000 | E30: =E16-E29 -> 950000 | F30: =F16-F29 -> 950000 | G30: =G16-G29 -> 950000 | H30: =H16-H29 -> 950000 | I30: =I16-I29 -> 950000 | ... M30: =M16-M29 -> 950000 | N30: =SUM(B30:M30) -> 11400000
A31: Margen Bruto % | B31: =IFERROR(B30/B16,0) -> 0.27536232 | C31: =IFERROR(C30/C16,0) -> 0.27536232 | D31: =IFERROR(D30/D16,0) -> 0.27536232 | E31: =IFERROR(E30/E16,0) -> 0.27536232 | F31: =IFERROR(F30/F16,0) -> 0.27536232 | G31: =IFERROR(G30/G16,0) -> 0.27536232 | H31: =IFERROR(H30/H16,0) -> 0.27536232 | I31: =IFERROR(I30/I16,0) -> 0.27536232 | ... N31: =IFERROR(N30/N16,0) -> 0.27536232
A32: GASTOS OPERACIONALES
A33: Gastos de Ventas y Marketing
A34: Sueldos Área Comercial | B34: 0 | C34: 0 | D34: 0 | E34: 0 | F34: 0 | G34: 0 | H34: 0 | I34: 0 | J34: 0 | K34: 0 | L34: 0 | M34: 0 | N34: 0
A35: Comisiones de Ventas | B35: 0 | C35: 0 | D35: 0 | E35: 0 | F35: 0 | G35: 0 | H35: 0 | I35: 0 | J35: 0 | K35: 0 | L35: 0 | M35: 0 | N35: 0
A36: Publicidad y Marketing Digital | B36: 0 | C36: 0 | D36: 0 | E36: 0 | F36: 0 | G36: 0 | H36: 0 | I36: 0 | J36: 0 | K36: 0 | L36: 0 | M36: 0 | N36: 0
A37: Eventos y Networking | B37: 0 | C37: 0 | D37: 0 | E37: 0 | F37: 0 | G37: 0 | H37: 0 | I37: 0 | J37: 0 | K37: 0 | L37: 0 | M37: 0 | N37: 0
A38: Material Promocional | B38: 0 | C38: 0 | D38: 0 | E38: 0 | F38: 0 | G38: 0 | H38: 0 | I38: 0 | J38: 0 | K38: 0 | L38: 0 | M38: 0 | N38: 0
A39: Gastos de Administración
A40: Sueldos Administrativos | B40: 0 | C40: 0 | D40: 0 | E40: 0 | F40: 0 | G40: 0 | H40: 0 | I40: 0 | J40: 0 | K40: 0 | L40: 0 | M40: 0 | N40: 0
A41: Honorarios Profesionales | B41: 0 | C41: 0 | D41: 0 | E41: 0 | F41: 0 | G41: 0 | H41: 0 | I41: 0 | J41: 0 | K41: 0 | L41: 0 | M41: 0 | N41: 0
A42: Arriendo Oficinas | B42: 0 | C42: 0 | D42: 0 | E42: 0 | F42: 0 | G42: 0 | H42: 0 | I42: 0 | J42: 0 | K42: 0 | L42: 0 | M42: 0 | N42: 0
A43: Servicios Básicos | B43: 0 | C43: 0 | D43: 0 | E43: 0 | F43: 0 | G43: 0 | H43: 0 | I43: 0 | J43: 0 | K43: 0 | L43: 0 | M43: 0 | N43: 0
A44: Seguros | B44: 0 | C44: 0 | D44: 0 | E44: 0 | F44: 0 | G44: 0 | H44: 0 | I44: 0 | J44: 0 | K44: 0 | L44: 0 | M44: 0 | N44: 0
A45: Tecnología y Sistemas | B45: 0 | C45: 0 | D45: 0 | E45: 0 | F45: 0 | G45: 0 | H45: 0 | I45: 0 | J45: 0 | K45: 0 | L45: 0 | M45: 0 | N45: 0
A46: Papelería y Útiles | B46: 0 | C46: 0 | D46: 0 | E46: 0 | F46: 0 | G46: 0 | H46: 0 | I46: 0 | J46: 0 | K46: 0 | L46: 0 | M46: 0 | N46: 0
A47: Depreciación | B47: 0 | C47: 0 | D47: 0 | E47: 0 | F47: 0 | G47: 0 | H47: 0 | I47: 0 | J47: 0 | K47: 0 | L47: 0 | M47: 0 | N47: 0
A48: Amortización | B48: 0 | C48: 0 | D48: 0 | E48: 0 | F48: 0 | G48: 0 | H48: 0 | I48: 0 | J48: 0 | K48: 0 | L48: 0 | M48: 0 | N48: 0
A49: Otros Gastos Administrativos | B49: 0 | C49: 0 | D49: 0 | E49: 0 | F49: 0 | G49: 0 | H49: 0 | I49: 0 | J49: 0 | K49: 0 | L49: 0 | M49: 0 | N49: 0
A50: TOTAL GASTOS OPERACIONALES | B50: =SUM(B33:B49) -> 0 | C50: =SUM(C33:C49) -> 0 | D50: =SUM(D33:D49) -> 0 | E50: =SUM(E33:E49) -> 0 | F50: =SUM(F33:F49) -> 0 | G50: =SUM(G33:G49) -> 0 | H50: =SUM(H33:H49) -> 0 | I50: =SUM(I33:I49) -> 0 | ... N50: =SUM(N33:N49) -> 0
A51: UTILIDAD OPERACIONAL (EBIT) | B51: =B30-B50 -> 950000 | C51: =C30-C50 -> 950000 | D51: =D30-D50 -> 950000 | E51: =E30-E50 -> 950000 | F51: =F30-F50 -> 950000 | G51: =G30-G50 -> 950000 | H51: =H30-H50 -> 950000 | I51: =I30-I50 -> 950000 | ... M51: =M30-M50 -> 950000 | N51: =SUM(B51:M51) -> 11400000
A52: Margen Operacional % | B52: =IFERROR(B51/B16,0) -> 0.27536232 | C52: =IFERROR(C51/C16,0) -> 0.27536232 | D52: =IFERROR(D51/D16,0) -> 0.27536232 | E52: =IFERROR(E51/E16,0) -> 0.27536232 | F52: =IFERROR(F51/F16,0) -> 0.27536232 | G52: =IFERROR(G51/G16,0) -> 0.27536232 | H52: =IFERROR(H51/H16,0) -> 0.27536232 | I52: =IFERROR(I51/I16,0) -> 0.27536232 | ... N52: =IFERROR(N51/N16,0) -> 0.27536232
A53: OTROS INGRESOS Y GASTOS
A54: (+) Ingresos Financieros | B54: 0 | C54: 0 | D54: 0 | E54: 0 | F54: 0 | G54: 0 | H54: 0 | I54: 0 | J54: 0 | K54: 0 | L54: 0 | M54: 0 | N54: 0
A55: (+) Diferencias de Cambio Positivas | B55: 0 | C55: 0 | D55: 0 | E55: 0 | F55: 0 | G55: 0 | H55: 0 | I55: 0 | J55: 0 | K55: 0 | L55: 0 | M55: 0 | N55: 0
A56: (+) Otros Ingresos No Operacionales | B56: 0 | C56: 0 | D56: 0 | E56: 0 | F56: 0 | G56: 0 | H56: 0 | I56: 0 | J56: 0 | K56: 0 | L56: 0 | M56: 0 | N56: 0
A57: (-) Gastos Financieros | B57: 0 | C57: 0 | D57: 0 | E57: 0 | F57: 0 | G57: 0 | H57: 0 | I57: 0 | J57: 0 | K57: 0 | L57: 0 | M57: 0 | N57: 0
A58: (-) Diferencias de Cambio Negativas | B58: 0 | C58: 0 | D58: 0 | E58: 0 | F58: 0 | G58: 0 | H58: 0 | I58: 0 | J58: 0 | K58: 0 | L58: 0 | M58: 0 | N58: 0
A59: (-) Otros Gastos No Operacionales | B59: 0 | C59: 0 | D59: 0 | E59: 0 | F59: 0 | G59: 0 | H59: 0 | I59: 0 | J59: 0 | K59: 0 | L59: 0 | M59: 0 | N59: 0
A60: TOTAL OTROS INGRESOS (GASTOS) | B60: =SUM(B54:B56)-B57-B58-B59 -> 0 | C60: =SUM(C54:C56)-C57-C58-C59 -> 0 | D60: =SUM(D54:D56)-D57-D58-D59 -> 0 | E60: =SUM(E54:E56)-E57-E58-E59 -> 0 | F60: =SUM(F54:F56)-F57-F58-F59 -> 0 | G60: =SUM(G54:G56)-G57-G58-G59 -> 0 | H60: =SUM(H54:H56)-H57-H58-H59 -> 0 | I60: =SUM(I54:I56)-I57-I58-I59 -> 0 | ... N60: =SUM(N54:N56)-N57-N58-N59 -> 0
A61: UTILIDAD ANTES DE IMPUESTOS (EBT) | B61: =B51+B60 -> 950000 | C61: =C51+C60 -> 950000 | D61: =D51+D60 -> 950000 | E61: =E51+E60 -> 950000 | F61: =F51+F60 -> 950000 | G61: =G51+G60 -> 950000 | H61: =H51+H60 -> 950000 | I61: =I51+I60 -> 950000 | ... M61: =M51+M60 -> 950000 | N61: =SUM(B61:M61) -> 11400000
A62: (-) Impuesto a la Renta (27%) | B62: =B61*0.27 -> 256500 | C62: =C61*0.27 -> 256500 | D62: =D61*0.27 -> 256500 | E62: =E61*0.27 -> 256500 | F62: =F61*0.27 -> 256500 | G62: =G61*0.27 -> 256500 | H62: =H61*0.27 -> 256500 | I62: =I61*0.27 -> 256500 | ... N62: =N61*0.27 -> 3078000
A63: UTILIDAD NETA | B63: =B61-B62 -> 693500 | C63: =C61-C62 -> 693500 | D63: =D61-D62 -> 693500 | E63: =E61-E62 -> 693500 | F63: =F61-F62 -> 693500 | G63: =G61-G62 -> 693500 | H63: =H61-H62 -> 693500 | I63: =I61-I62 -> 693500 | ... M63: =M61-M62 -> 693500 | N63: =SUM(B63:M63) -> 8322000
A64: Margen Neto % | B64: =IFERROR(B63/B16,0) -> 0.20101449 | C64: =IFERROR(C63/C16,0) -> 0.20101449 | D64: =IFERROR(D63/D16,0) -> 0.20101449 | E64: =IFERROR(E63/E16,0) -> 0.20101449 | F64: =IFERROR(F63/F16,0) -> 0.20101449 | G64: =IFERROR(G63/G16,0) -> 0.20101449 | H64: =IFERROR(H63/H16,0) -> 0.20101449 | I64: =IFERROR(I63/I16,0) -> 0.20101449 | ... N64: =IFERROR(N63/N16,0) -> 0.20101449

Sheet P&L Servicios - Budget
A1: ESTADO DE RESULTADOS - EMPRESA DE SERVICIOS
A2: Escenario: Budget
A3: Cifras en USD
A5: Concepto | B5: Enero | C5: Febrero | D5: Marzo | E5: Abril | F5: Mayo | G5: Junio | H5: Julio | I5: Agosto | J5: Septiembre | K5: Octubre | L5: Noviembre | M5: Diciembre | N5: TOTAL AÑO
A6: INGRESOS POR SERVICIOS
A7: Servicios de Consultoría | B7: 1300000 | C7: 1300000 | D7: 1300000 | E7: 1300000 | F7: 1300000 | G7: 1300000 | H7: 1300000 | I7: 1300000 | J7: 1300000 | K7: 1300000 | L7: 1300000 | M7: 1300000 | N7: =SUM(B7:M7) -> 15600000
A8: Servicios de Asesoría | B8: 0 | C8: 0 | D8: 0 | E8: 0 | F8: 0 | G8: 0 | H8: 0 | I8: 0 | J8: 0 | K8: 0 | L8: 0 | M8: 0 | N8: =SUM(B8:M8) -> 0
A9: Servicios de Capacitación | B9: 570000 | C9: 570000 | D9: 570000 | E9: 570000 | F9: 570000 | G9: 570000 | H9: 570000 | I9: 570000 | J9: 570000 | K9: 570000 | L9: 570000 | M9: 570000 | N9: =SUM(B9:M9) -> 6840000
A10: Servicios de Soporte Técnico | B10: 0 | C10: 0 | D10: 0 | E10: 0 | F10: 0 | G10: 0 | H10: 0 | I10: 0 | J10: 0 | K10: 0 | L10: 0 | M10: 0 | N10: =SUM(B10:M10) -> 0
A11: Servicios de Mantenimiento | B11: 0 | C11: 0 | D11: 0 | E11: 0 | F11: 0 | G11: 0 | H11: 0 | I11: 0 | J11: 0 | K11: 0 | L11: 0 | M11: 0 | N11: =SUM(B11:M11) -> 0
A12: Otros Servicios | B12: 0 | C12: 0 | D12: 0 | E12: 0 | F12: 0 | G12: 0 | H12: 0 | I12: 0 | J12: 0 | K12: 0 | L12: 0 | M12: 0 | N12: =SUM(B12:M12) -> 0
A13: Total Ingresos Brutos | B13: =SUM(B7:B12) -> 1870000 | C13: =SUM(C7:C12) -> 1870000 | D13: =SUM(D7:D12) -> 1870000 | E13: =SUM(E7:E12) -> 1870000 | F13: =SUM(F7:F12) -> 1870000 | G13: =SUM(G7:G12) -> 1870000 | H13: =SUM(H7:H12) -> 1870000 | I13: =SUM(I7:I12) -> 1870000 | ... N13: =SUM(N7:N12) -> 22440000
A14: (-) Descuentos por Pronto Pago | B14: 0 | C14: 0 | D14: 0 | E14: 0 | F14: 0 | G14: 0 | H14: 0 | I14: 0 | J14: 0 | K14: 0 | L14: 0 | M14: 0 | N14: 0
A15: (-) Devoluciones | B15: 0 | C15: 0 | D15: 0 | E15: 0 | F15: 0 | G15: 0 | H15: 0 | I15: 0 | J15: 0 | K15: 0 | L15: 0 | M15: 0 | N15: =SUM(B15:M15) -> 0
A16: INGRESOS NETOS | B16: =+B13-B14-B15 -> 1870000 | C16: =+C13-C14-C15 -> 1870000 | D16: =+D13-D14-D15 -> 1870000 | E16: =+E13-E14-E15 -> 1870000 | F16: =+F13-F14-F15 -> 1870000 | G16: =+G13-G14-G15 -> 1870000 | H16: =+H13-H14-H15 -> 1870000 | I16: =+I13-I14-I15 -> 1870000 | ... M16: =+M13-M14-M15 -> 1870000 | N16: =SUM(B16:M16) -> 22440000
A17: COSTO DE SERVICIOS
A18: Personal Directo
A19: Sueldos Personal Operativo | B19: 1400000 | C19: 1400000 | D19: 1400000 | E19: 1400000 | F19: 1400000 | G19: 1400000 | H19: 1400000 | I19: 1400000 | J19: 1400000 | K19: 1400000 | L19: 1400000 | M19: 1400000 | N19: =SUM(B19:M19) -> 16800000
A20: Honorarios Consultores | B20: 0 | C20: 0 | D20: 0 | E20: 0 | F20: 0 | G20: 0 | H20: 0 | I20: 0 | J20: 0 | K20: 0 | L20: 0 | M20: 0 | N20: =SUM(B20:M20) -> 0
A21: Beneficios Sociales Personal Directo | B21: 0 | C21: 0 | D21: 0 | E21: 0 | F21: 0 | G21: 0 | H21: 0 | I21: 0 | J21: 0 | K21: 0 | L21: 0 | M21: 0 | N21: =SUM(B21:M21) -> 0
A22: Capacitación Personal | B22: 0 | C22: 0 | D22: 0 | E22: 0 | F22: 0 | G22: 0 | H22: 0 | I22: 0 | J22: 0 | K22: 0 | L22: 0 | M22: 0 | N22: =SUM(B22:M22) -> 0
A23: Costos Directos del Servicio
A24: Materiales y Suministros | B24: 0 | C24: 0 | D24: 0 | E24: 0 | F24: 0 | G24: 0 | H24: 0 | I24: 0 | J24: 0 | K24: 0 | L24: 0 | M24: 0 | N24: =SUM(B24:M24) -> 0
A25: Software y Licencias | B25: 0 | C25: 0 | D25: 0 | E25: 0 | F25: 0 | G25: 0 | H25: 0 | I25: 0 | J25: 0 | K25: 0 | L25: 0 | M25: 0 | N25: =SUM(B25:M25) -> 0
A26: Equipamiento Especializado | B26: 0 | C26: 0 | D26: 0 | E26: 0 | F26: 0 | G26: 0 | H26: 0 | I26: 0 | J26: 0 | K26: 0 | L26: 0 | M26: 0 | N26: =SUM(B26:M26) -> 0
A27: Subcontrataciones | B27: 300000 | C27: 300000 | D27: 300000 | E27: 300000 | F27: 300000 | G27: 300000 | H27: 300000 | I27: 300000 | J27: 300000 | K27: 300000 | L27: 300000 | M27: 300000 | N27: =SUM(B27:M27) -> 3600000
A28: Viáticos y Movilización | B28: 0 | C28: 0 | D28: 0 | E28: 0 | F28: 0 | G28: 0 | H28: 0 | I28: 0 | J28: 0 | K28: 0 | L28: 0 | M28: 0 | N28: =SUM(B28:M28) -> 0
A29: COSTO DE SERVICIOS TOTAL | B29: =SUM(B19:B28) -> 1700000 | C29: =SUM(C19:C28) -> 1700000 | D29: =SUM(D19:D28) -> 1700000 | E29: =SUM(E19:E28) -> 1700000 | F29: =SUM(F19:F28) -> 1700000 | G29: =SUM(G19:G28) -> 1700000 | H29: =SUM(H19:H28) -> 1700000 | I29: =SUM(I19:I28) -> 1700000 | ... M29: =SUM(M19:M28) -> 1700000 | N29: =SUM(B29:M29) -> 20400000
A30: UTILIDAD BRUTA | B30: =B16-B29 -> 170000 | C30: =C16-C29 -> 170000 | D30: =D16-D29 -> 170000 | E30: =E16-E29 -> 170000 | F30: =F16-F29 -> 170000 | G30: =G16-G29 -> 170000 | H30: =H16-H29 -> 170000 | I30: =I16-I29 -> 170000 | ... M30: =M16-M29 -> 170000 | N30: =SUM(B30:M30) -> 2040000
A31: Margen Bruto % | B31: =IFERROR(B30/B16,0) -> 0.090909091 | C31: =IFERROR(C30/C16,0) -> 0.090909091 | D31: =IFERROR(D30/D16,0) -> 0.090909091 | E31: =IFERROR(E30/E16,0) -> 0.090909091 | F31: =IFERROR(F30/F16,0) -> 0.090909091 | G31: =IFERROR(G30/G16,0) -> 0.090909091 | H31: =IFERROR(H30/H16,0) -> 0.090909091 | I31: =IFERROR(I30/I16,0) -> 0.090909091 | ... N31: =IFERROR(N30/N16,0) -> 0.090909091
A32: GASTOS OPERACIONALES
A33: Gastos de Ventas y Marketing
A34: Sueldos Área Comercial | B34: 0 | C34: 0 | D34: 0 | E34: 0 | F34: 0 | G34: 0 | H34: 0 | I34: 0 | J34: 0 | K34: 0 | L34: 0 | M34: 0 | N34: 0
A35: Comisiones de Ventas | B35: 0 | C35: 0 | D35: 0 | E35: 0 | F35: 0 | G35: 0 | H35: 0 | I35: 0 | J35: 0 | K35: 0 | L35: 0 | M35: 0 | N35: 0
A36: Publicidad y Marketing Digital | B36: 0 | C36: 0 | D36: 0 | E36: 0 | F36: 0 | G36: 0 | H36: 0 | I36: 0 | J36: 0 | K36: 0 | L36: 0 | M36: 0 | N36: 0
A37: Eventos y Networking | B37: 0 | C37: 0 | D37: 0 | E37: 0 | F37: 0 | G37: 0 | H37: 0 | I37: 0 | J37: 0 | K37: 0 | L37: 0 | M37: 0 | N37: 0
A38: Material Promocional | B38: 0 | C38: 0 | D38: 0 | E38: 0 | F38: 0 | G38: 0 | H38: 0 | I38: 0 | J38: 0 | K38: 0 | L38: 0 | M38: 0 | N38: 0
A39: Gastos de Administración
A40: Sueldos Administrativos | B40: 0 | C40: 0 | D40: 0 | E40: 0 | F40: 0 | G40: 0 | H40: 0 | I40: 0 | J40: 0 | K40: 0 | L40: 0 | M40: 0 | N40: 0
A41: Honorarios Profesionales | B41: 0 | C41: 0 | D41: 0 | E41: 0 | F41: 0 | G41: 0 | H41: 0 | I41: 0 | J41: 0 | K41: 0 | L41: 0 | M41: 0 | N41: 0
A42: Arriendo Oficinas | B42: 0 | C42: 0 | D42: 0 | E42: 0 | F42: 0 | G42: 0 | H42: 0 | I42: 0 | J42: 0 | K42: 0 | L42: 0 | M42: 0 | N42: 0
A43: Servicios Básicos | B43: 0 | C43: 0 | D43: 0 | E43: 0 | F43: 0 | G43: 0 | H43: 0 | I43: 0 | J43: 0 | K43: 0 | L43: 0 | M43: 0 | N43: 0
A44: Seguros | B44: 0 | C44: 0 | D44: 0 | E44: 0 | F44: 0 | G44: 0 | H44: 0 | I44: 0 | J44: 0 | K44: 0 | L44: 0 | M44: 0 | N44: 0
A45: Tecnología y Sistemas | B45: 0 | C45: 0 | D45: 0 | E45: 0 | F45: 0 | G45: 0 | H45: 0 | I45: 0 | J45: 0 | K45: 0 | L45: 0 | M45: 0 | N45: 0
A46: Papelería y Útiles | B46: 0 | C46: 0 | D46: 0 | E46: 0 | F46: 0 | G46: 0 | H46: 0 | I46: 0 | J46: 0 | K46: 0 | L46: 0 | M46: 0 | N46: 0
A47: Depreciación | B47: 0 | C47: 0 | D47: 0 | E47: 0 | F47: 0 | G47: 0 | H47: 0 | I47: 0 | J47: 0 | K47: 0 | L47: 0 | M47: 0 | N47: 0
A48: Amortización | B48: 0 | C48: 0 | D48: 0 | E48: 0 | F48: 0 | G48: 0 | H48: 0 | I48: 0 | J48: 0 | K48: 0 | L48: 0 | M48: 0 | N48: 0
A49: Otros Gastos Administrativos | B49: 0 | C49: 0 | D49: 0 | E49: 0 | F49: 0 | G49: 0 | H49: 0 | I49: 0 | J49: 0 | K49: 0 | L49: 0 | M49: 0 | N49: 0
A50: TOTAL GASTOS OPERACIONALES | B50: =SUM(B33:B49) -> 0 | C50: =SUM(C33:C49) -> 0 | D50: =SUM(D33:D49) -> 0 | E50: =SUM(E33:E49) -> 0 | F50: =SUM(F33:F49) -> 0 | G50: =SUM(G33:G49) -> 0 | H50: =SUM(H33:H49) -> 0 | I50: =SUM(I33:I49) -> 0 | ... N50: =SUM(N33:N49) -> 0
A51: UTILIDAD OPERACIONAL (EBIT) | B51: =B30-B50 -> 170000 | C51: =C30-C50 -> 170000 | D51: =D30-D50 -> 170000 | E51: =E30-E50 -> 170000 | F51: =F30-F50 -> 170000 | G51: =G30-G50 -> 170000 | H51: =H30-H50 -> 170000 | I51: =I30-I50 -> 170000 | ... M51: =M30-M50 -> 170000 | N51: =SUM(B51:M51) -> 2040000
A52: Margen Operacional % | B52: =IFERROR(B51/B16,0) -> 0.090909091 | C52: =IFERROR(C51/C16,0) -> 0.090909091 | D52: =IFERROR(D51/D16,0) -> 0.090909091 | E52: =IFERROR(E51/E16,0) -> 0.090909091 | F52: =IFERROR(F51/F16,0) -> 0.090909091 | G52: =IFERROR(G51/G16,0) -> 0.090909091 | H52: =IFERROR(H51/H16,0) -> 0.090909091 | I52: =IFERROR(I51/I16,0) -> 0.090909091 | ... N52: =IFERROR(N51/N16,0) -> 0.090909091
A53: OTROS INGRESOS Y GASTOS
A54: (+) Ingresos Financieros | B54: 0 | C54: 0 | D54: 0 | E54: 0 | F54: 0 | G54: 0 | H54: 0 | I54: 0 | J54: 0 | K54: 0 | L54: 0 | M54: 0 | N54: 0
A55: (+) Diferencias de Cambio Positivas | B55: 0 | C55: 0 | D55: 0 | E55: 0 | F55: 0 | G55: 0 | H55: 0 | I55: 0 | J55: 0 | K55: 0 | L55: 0 | M55: 0 | N55: 0
A56: (+) Otros Ingresos No Operacionales | B56: 0 | C56: 0 | D56: 0 | E56: 0 | F56: 0 | G56: 0 | H56: 0 | I56: 0 | J56: 0 | K56: 0 | L56: 0 | M56: 0 | N56: 0
A57: (-) Gastos Financieros | B57: 0 | C57: 0 | D57: 0 | E57: 0 | F57: 0 | G57: 0 | H57: 0 | I57: 0 | J57: 0 | K57: 0 | L57: 0 | M57: 0 | N57: 0
A58: (-) Diferencias de Cambio Negativas | B58: 0 | C58: 0 | D58: 0 | E58: 0 | F58: 0 | G58: 0 | H58: 0 | I58: 0 | J58: 0 | K58: 0 | L58: 0 | M58: 0 | N58: 0
A59: (-) Otros Gastos No Operacionales | B59: 0 | C59: 0 | D59: 0 | E59: 0 | F59: 0 | G59: 0 | H59: 0 | I59: 0 | J59: 0 | K59: 0 | L59: 0 | M59: 0 | N59: 0
A60: TOTAL OTROS INGRESOS (GASTOS) | B60: =SUM(B54:B56)-B57-B58-B59 -> 0 | C60: =SUM(C54:C56)-C57-C58-C59 -> 0 | D60: =SUM(D54:D56)-D57-D58-D59 -> 0 | E60: =SUM(E54:E56)-E57-E58-E59 -> 0 | F60: =SUM(F54:F56)-F57-F58-F59 -> 0 | G60: =SUM(G54:G56)-G57-G58-G59 -> 0 | H60: =SUM(H54:H56)-H57-H58-H59 -> 0 | I60: =SUM(I54:I56)-I57-I58-I59 -> 0 | ... N60: =SUM(N54:N56)-N57-N58-N59 -> 0
A61: UTILIDAD ANTES DE IMPUESTOS (EBT) | B61: =B51+B60 -> 170000 | C61: =C51+C60 -> 170000 | D61: =D51+D60 -> 170000 | E61: =E51+E60 -> 170000 | F61: =F51+F60 -> 170000 | G61: =G51+G60 -> 170000 | H61: =H51+H60 -> 170000 | I61: =I51+I60 -> 170000 | ... M61: =M51+M60 -> 170000 | N61: =SUM(B61:M61) -> 2040000
A62: (-) Impuesto a la Renta (25%) | B62: =B61*0.27 -> 45900 | C62: =C61*0.27 -> 45900 | D62: =D61*0.27 -> 45900 | E62: =E61*0.27 -> 45900 | F62: =F61*0.27 -> 45900 | G62: =G61*0.27 -> 45900 | H62: =H61*0.27 -> 45900 | I62: =I61*0.27 -> 45900 | ... N62: =N61*0.27 -> 550800
A63: UTILIDAD NETA | B63: =B61-B62 -> 124100 | C63: =C61-C62 -> 124100 | D63: =D61-D62 -> 124100 | E63: =E61-E62 -> 124100 | F63: =F61-F62 -> 124100 | G63: =G61-G62 -> 124100 | H63: =H61-H62 -> 124100 | I63: =I61-I62 -> 124100 | ... M63: =M61-M62 -> 124100 | N63: =SUM(B63:M63) -> 1489200
A64: Margen Neto % | B64: =B63/B16 -> 0.066363636 | C64: =C63/C16 -> 0.066363636 | D64: =D63/D16 -> 0.066363636 | E64: =E63/E16 -> 0.066363636 | F64: =F63/F16 -> 0.066363636 | G64: =G63/G16 -> 0.066363636 | H64: =H63/H16 -> 0.066363636 | I64: =I63/I16 -> 0.066363636 | ... N64: =N63/N16 -> 0.066363636

Sheet P&L Servicios - Forecast
A1: ESTADO DE RESULTADOS - EMPRESA DE SERVICIOS
A2: Escenario: Forecast
A3: Cifras en USD
A5: Concepto | B5: Enero | C5: Febrero | D5: Marzo | E5: Abril | F5: Mayo | G5: Junio | H5: Julio | I5: Agosto | J5: Septiembre | K5: Octubre | L5: Noviembre | M5: Diciembre | N5: TOTAL AÑO
A6: INGRESOS POR SERVICIOS
A7: Servicios de Consultoría | B7: 2500000 | C7: 2500000 | D7: 2500000 | E7: 2500000 | F7: 2500000 | G7: 2500000 | H7: 2500000 | I7: 2500000 | J7: 2500000 | K7: 2500000 | L7: 2500000 | M7: 2500000 | N7: =SUM(B7:M7) -> 30000000
A8: Servicios de Asesoría | B8: 0 | C8: 0 | D8: 0 | E8: 0 | F8: 0 | G8: 0 | H8: 0 | I8: 0 | J8: 0 | K8: 0 | L8: 0 | M8: 0 | N8: =SUM(B8:M8) -> 0
A9: Servicios de Capacitación | B9: 0 | C9: 0 | D9: 0 | E9: 0 | F9: 0 | G9: 0 | H9: 0 | I9: 0 | J9: 0 | K9: 0 | L9: 0 | M9: 0 | N9: =SUM(B9:M9) -> 0
A10: Servicios de Soporte Técnico | B10: 0 | C10: 0 | D10: 0 | E10: 0 | F10: 0 | G10: 0 | H10: 0 | I10: 0 | J10: 0 | K10: 0 | L10: 0 | M10: 0 | N10: =SUM(B10:M10) -> 0
A11: Servicios de Mantenimiento | B11: 0 | C11: 0 | D11: 0 | E11: 0 | F11: 0 | G11: 0 | H11: 0 | I11: 0 | J11: 0 | K11: 0 | L11: 0 | M11: 0 | N11: =SUM(B11:M11) -> 0
A12: Otros Servicios | B12: 470000 | C12: 0 | D12: 470000 | E12: 470000 | F12: 470000 | G12: 470000 | H12: 470000 | I12: 0 | J12: 470000 | K12: 470000 | L12: 470000 | M12: 470000 | N12: =SUM(B12:M12) -> 4700000
A13: Total Ingresos Brutos | B13: =SUM(B7:B12) -> 2970000 | C13: =SUM(C7:C12) -> 2500000 | D13: =SUM(D7:D12) -> 2970000 | E13: =SUM(E7:E12) -> 2970000 | F13: =SUM(F7:F12) -> 2970000 | G13: =SUM(G7:G12) -> 2970000 | H13: =SUM(H7:H12) -> 2970000 | I13: =SUM(I7:I12) -> 2500000 | ... N13: =SUM(N7:N12) -> 34700000
A14: (-) Descuentos por Pronto Pago | B14: 0 | C14: 0 | D14: 0 | E14: 0 | F14: 0 | G14: 0 | H14: 0 | I14: 0 | J14: 0 | K14: 0 | L14: 0 | M14: 0 | N14: 0
A15: (-) Devoluciones | B15: 0 | C15: 0 | D15: 0 | E15: 0 | F15: 0 | G15: 0 | H15: 0 | I15: 0 | J15: 0 | K15: 0 | L15: 0 | M15: 0 | N15: =SUM(B15:M15) -> 0
A16: INGRESOS NETOS | B16: =+B13-B14-B15 -> 2970000 | C16: =+C13-C14-C15 -> 2500000 | D16: =+D13-D14-D15 -> 2970000 | E16: =+E13-E14-E15 -> 2970000 | F16: =+F13-F14-F15 -> 2970000 | G16: =+G13-G14-G15 -> 2970000 | H16: =+H13-H14-H15 -> 2970000 | I16: =+I13-I14-I15 -> 2500000 | ... M16: =+M13-M14-M15 -> 2970000 | N16: =SUM(B16:M16) -> 34700000
A17: COSTO DE SERVICIOS
A18: Personal Directo
A19: Sueldos Personal Operativo | B19: 0 | C19: 0 | D19: 0 | E19: 0 | F19: 0 | G19: 0 | H19: 0 | I19: 0 | J19: 0 | K19: 0 | L19: 0 | M19: 0 | N19: =SUM(B19:M19) -> 0
A20: Honorarios Consultores | B20: 2100000 | C20: 2100000 | D20: 2100000 | E20: 2100000 | F20: 2100000 | G20: 2100000 | H20: 2100000 | I20: 2100000 | J20: 2100000 | K20: 2100000 | L20: 2100000 | M20: 2100000 | N20: =SUM(B20:M20) -> 25200000
A21: Beneficios Sociales Personal Directo | B21: 0 | C21: 0 | D21: 0 | E21: 0 | F21: 0 | G21: 0 | H21: 0 | I21: 0 | J21: 0 | K21: 0 | L21: 0 | M21: 0 | N21: =SUM(B21:M21) -> 0
A22: Capacitación Personal | B22: 0 | C22: 0 | D22: 0 | E22: 0 | F22: 0 | G22: 0 | H22: 0 | I22: 0 | J22: 0 | K22: 0 | L22: 0 | M22: 0 | N22: =SUM(B22:M22) -> 0
A23: Costos Directos del Servicio
A24: Materiales y Suministros | B24: 0 | C24: 0 | D24: 0 | E24: 0 | F24: 0 | G24: 0 | H24: 0 | I24: 0 | J24: 0 | K24: 0 | L24: 0 | M24: 0 | N24: =SUM(B24:M24) -> 0
A25: Software y Licencias | B25: 0 | C25: 0 | D25: 0 | E25: 0 | F25: 0 | G25: 0 | H25: 0 | I25: 0 | J25: 0 | K25: 0 | L25: 0 | M25: 0 | N25: =SUM(B25:M25) -> 0
A26: Equipamiento Especializado | B26: 0 | C26: 0 | D26: 0 | E26: 0 | F26: 0 | G26: 0 | H26: 0 | I26: 0 | J26: 0 | K26: 0 | L26: 0 | M26: 0 | N26: =SUM(B26:M26) -> 0
A27: Subcontrataciones | B27: 0 | C27: 0 | D27: 0 | E27: 0 | F27: 0 | G27: 0 | H27: 0 | I27: 0 | J27: 0 | K27: 0 | L27: 0 | M27: 0 | N27: =SUM(B27:M27) -> 0
A28: Viáticos y Movilización | B28: 200000 | C28: 200000 | D28: 200000 | E28: 200000 | F28: 200000 | G28: 200000 | H28: 200000 | I28: 200000 | J28: 200000 | K28: 200000 | L28: 200000 | M28: 200000 | N28: =SUM(B28:M28) -> 2400000
A29: COSTO DE SERVICIOS TOTAL | B29: =SUM(B19:B28) -> 2300000 | C29: =SUM(C19:C28) -> 2300000 | D29: =SUM(D19:D28) -> 2300000 | E29: =SUM(E19:E28) -> 2300000 | F29: =SUM(F19:F28) -> 2300000 | G29: =SUM(G19:G28) -> 2300000 | H29: =SUM(H19:H28) -> 2300000 | I29: =SUM(I19:I28) -> 2300000 | ... M29: =SUM(M19:M28) -> 2300000 | N29: =SUM(B29:M29) -> 27600000
A30: UTILIDAD BRUTA | B30: =B16-B29 -> 670000 | C30: =C16-C29 -> 200000 | D30: =D16-D29 -> 670000 | E30: =E16-E29 -> 670000 | F30: =F16-F29 -> 670000 | G30: =G16-G29 -> 670000 | H30: =H16-H29 -> 670000 | I30: =I16-I29 -> 200000 | ... M30: =M16-M29 -> 670000 | N30: =SUM(B30:M30) -> 7100000
A31: Margen Bruto % | B31: =IFERROR(B30/B16,0) -> 0.22558923 | C31: =IFERROR(C30/C16,0) -> 0.08 | D31: =IFERROR(D30/D16,0) -> 0.22558923 | E31: =IFERROR(E30/E16,0) -> 0.22558923 | F31: =IFERROR(F30/F16,0) -> 0.22558923 | G31: =IFERROR(G30/G16,0) -> 0.22558923 | H31: =IFERROR(H30/H16,0) -> 0.22558923 | I31: =IFERROR(I30/I16,0) -> 0.08 | ... N31: =IFERROR(N30/N16,0) -> 0.20461095
A32: GASTOS OPERACIONALES
A33: Gastos de Ventas y Marketing
A34: Sueldos Área Comercial | B34: 0 | C34: 0 | D34: 0 | E34: 0 | F34: 0 | G34: 0 | H34: 0 | I34: 0 | J34: 0 | K34: 0 | L34: 0 | M34: 0 | N34: =SUM(B34:M34) -> 0
A35: Comisiones de Ventas | B35: 0 | C35: 0 | D35: 0 | E35: 0 | F35: 0 | G35: 0 | H35: 0 | I35: 0 | J35: 0 | K35: 0 | L35: 0 | M35: 0 | N35: =SUM(B35:M35) -> 0
A36: Publicidad y Marketing Digital | B36: 0 | C36: 0 | D36: 0 | E36: 0 | F36: 0 | G36: 0 | H36: 0 | I36: 0 | J36: 0 | K36: 0 | L36: 0 | M36: 0 | N36: =SUM(B36:M36) -> 0
A37: Eventos y Networking | B37: 0 | C37: 0 | D37: 0 | E37: 0 | F37: 0 | G37: 0 | H37: 0 | I37: 0 | J37: 0 | K37: 0 | L37: 0 | M37: 0 | N37: =SUM(B37:M37) -> 0
A38: Material Promocional | B38: 0 | C38: 0 | D38: 0 | E38: 0 | F38: 0 | G38: 0 | H38: 0 | I38: 0 | J38: 0 | K38: 0 | L38: 0 | M38: 0 | N38: =SUM(B38:M38) -> 0
A39: Gastos de Administración
A40: Sueldos Administrativos | B40: 0 | C40: 0 | D40: 0 | E40: 0 | F40: 0 | G40: 0 | H40: 0 | I40: 0 | J40: 0 | K40: 0 | L40: 0 | M40: 0 | N40: =SUM(B40:M40) -> 0
A41: Honorarios Profesionales | B41: 0 | C41: 0 | D41: 0 | E41: 0 | F41: 0 | G41: 0 | H41: 0 | I41: 0 | J41: 0 | K41: 0 | L41: 0 | M41: 0 | N41: =SUM(B41:M41) -> 0
A42: Arriendo Oficinas | B42: 0 | C42: 0 | D42: 0 | E42: 0 | F42: 0 | G42: 0 | H42: 0 | I42: 0 | J42: 0 | K42: 0 | L42: 0 | M42: 0 | N42: =SUM(B42:M42) -> 0
A43: Servicios Básicos | B43: 0 | C43: 0 | D43: 0 | E43: 0 | F43: 0 | G43: 0 | H43: 0 | I43: 0 | J43: 0 | K43: 0 | L43: 0 | M43: 0 | N43: =SUM(B43:M43) -> 0
A44: Seguros | B44: 0 | C44: 0 | D44: 0 | E44: 0 | F44: 0 | G44: 0 | H44: 0 | I44: 0 | J44: 0 | K44: 0 | L44: 0 | M44: 0 | N44: =SUM(B44:M44) -> 0
A45: Tecnología y Sistemas | B45: 0 | C45: 0 | D45: 0 | E45: 0 | F45: 0 | G45: 0 | H45: 0 | I45: 0 | J45: 0 | K45: 0 | L45: 0 | M45: 0 | N45: =SUM(B45:M45) -> 0
A46: Papelería y Útiles | B46: 0 | C46: 0 | D46: 0 | E46: 0 | F46: 0 | G46: 0 | H46: 0 | I46: 0 | J46: 0 | K46: 0 | L46: 0 | M46: 0 | N46: =SUM(B46:M46) -> 0
A47: Depreciación | B47: 0 | C47: 0 | D47: 0 | E47: 0 | F47: 0 | G47: 0 | H47: 0 | I47: 0 | J47: 0 | K47: 0 | L47: 0 | M47: 0 | N47: =SUM(B47:M47) -> 0
A48: Amortización | B48: 0 | C48: 0 | D48: 0 | E48: 0 | F48: 0 | G48: 0 | H48: 0 | I48: 0 | J48: 0 | K48: 0 | L48: 0 | M48: 0 | N48: =SUM(B48:M48) -> 0
A49: Otros Gastos Administrativos | B49: 0 | C49: 0 | D49: 0 | E49: 0 | F49: 0 | G49: 0 | H49: 0 | I49: 0 | J49: 0 | K49: 0 | L49: 0 | M49: 0 | N49: =SUM(B49:M49) -> 0
A50: TOTAL GASTOS OPERACIONALES | B50: =SUM(B33:B49) -> 0 | C50: =SUM(C33:C49) -> 0 | D50: =SUM(D33:D49) -> 0 | E50: =SUM(E33:E49) -> 0 | F50: =SUM(F33:F49) -> 0 | G50: =SUM(G33:G49) -> 0 | H50: =SUM(H33:H49) -> 0 | I50: =SUM(I33:I49) -> 0 | ... M50: =SUM(M33:M49) -> 0 | N50: =SUM(B50:M50) -> 0
A51: UTILIDAD OPERACIONAL (EBIT) | B51: =B30-B50 -> 670000 | C51: =C30-C50 -> 200000 | D51: =D30-D50 -> 670000 | E51: =E30-E50 -> 670000 | F51: =F30-F50 -> 670000 | G51: =G30-G50 -> 670000 | H51: =H30-H50 -> 670000 | I51: =I30-I50 -> 200000 | ... M51: =M30-M50 -> 670000 | N51: =SUM(B51:M51) -> 7100000
A52: Margen Operacional % | B52: =IFERROR(B51/B16,0) -> 0.22558923 | C52: =IFERROR(C51/C16,0) -> 0.08 | D52: =IFERROR(D51/D16,0) -> 0.22558923 | E52: =IFERROR(E51/E16,0) -> 0.22558923 | F52: =IFERROR(F51/F16,0) -> 0.22558923 | G52: =IFERROR(G51/G16,0) -> 0.22558923 | H52: =IFERROR(H51/H16,0) -> 0.22558923 | I52: =IFERROR(I51/I16,0) -> 0.08 | ... N52: =IFERROR(N51/N16,0) -> 0.20461095
A53: OTROS INGRESOS Y GASTOS
A54: (+) Ingresos Financieros | B54: 0 | C54: 0 | D54: 0 | E54: 0 | F54: 0 | G54: 0 | H54: 0 | I54: 0 | J54: 0 | K54: 0 | L54: 0 | M54: 0 | N54: 0
A55: (+) Diferencias de Cambio Positivas | B55: 0 | C55: 0 | D55: 0 | E55: 0 | F55: 0 | G55: 0 | H55: 0 | I55: 0 | J55: 0 | K55: 0 | L55: 0 | M55: 0 | N55: 0
A56: (+) Otros Ingresos No Operacionales | B56: 0 | C56: 0 | D56: 0 | E56: 0 | F56: 0 | G56: 0 | H56: 0 | I56: 0 | J56: 0 | K56: 0 | L56: 0 | M56: 0 | N56: 0
A57: (-) Gastos Financieros | B57: 0 | C57: 0 | D57: 0 | E57: 0 | F57: 0 | G57: 0 | H57: 0 | I57: 0 | J57: 0 | K57: 0 | L57: 0 | M57: 0 | N57: 0
A58: (-) Diferencias de Cambio Negativas | B58: 0 | C58: 0 | D58: 0 | E58: 0 | F58: 0 | G58: 0 | H58: 0 | I58: 0 | J58: 0 | K58: 0 | L58: 0 | M58: 0 | N58: 0
A59: (-) Otros Gastos No Operacionales | B59: 0 | C59: 0 | D59: 0 | E59: 0 | F59: 0 | G59: 0 | H59: 0 | I59: 0 | J59: 0 | K59: 0 | L59: 0 | M59: 0 | N59: 0
A60: TOTAL OTROS INGRESOS (GASTOS) | B60: =SUM(B54:B56)-B57-B58-B59 -> 0 | C60: =SUM(C54:C56)-C57-C58-C59 -> 0 | D60: =SUM(D54:D56)-D57-D58-D59 -> 0 | E60: =SUM(E54:E56)-E57-E58-E59 -> 0 | F60: =SUM(F54:F56)-F57-F58-F59 -> 0 | G60: =SUM(G54:G56)-G57-G58-G59 -> 0 | H60: =SUM(H54:H56)-H57-H58-H59 -> 0 | I60: =SUM(I54:I56)-I57-I58-I59 -> 0 | ... N60: =SUM(N54:N56)-N57-N58-N59 -> 0
A61: UTILIDAD ANTES DE IMPUESTOS (EBT) | B61: =B51+B60 -> 670000 | C61: =C51+C60 -> 200000 | D61: =D51+D60 -> 670000 | E61: =E51+E60 -> 670000 | F61: =F51+F60 -> 670000 | G61: =G51+G60 -> 670000 | H61: =H51+H60 -> 670000 | I61: =I51+I60 -> 200000 | ... M61: =M51+M60 -> 670000 | N61: =SUM(B61:M61) -> 7100000
A62: (-) Impuesto a la Renta (25%) | B62: =B61*0.27 -> 180900 | C62: =C61*0.27 -> 54000 | D62: =D61*0.27 -> 180900 | E62: =E61*0.27 -> 180900 | F62: =F61*0.27 -> 180900 | G62: =G61*0.27 -> 180900 | H62: =H61*0.27 -> 180900 | I62: =I61*0.27 -> 54000 | ... N62: =N61*0.27 -> 1917000
A63: UTILIDAD NETA | B63: =B61-B62 -> 489100 | C63: =C61-C62 -> 146000 | D63: =D61-D62 -> 489100 | E63: =E61-E62 -> 489100 | F63: =F61-F62 -> 489100 | G63: =G61-G62 -> 489100 | H63: =H61-H62 -> 489100 | I63: =I61-I62 -> 146000 | ... M63: =M61-M62 -> 489100 | N63: =SUM(B63:M63) -> 5183000
A64: Margen Neto % | B64: =B63/B16 -> 0.16468013 | C64: =C63/C16 -> 0.0584 | D64: =D63/D16 -> 0.16468013 | E64: =E63/E16 -> 0.16468013 | F64: =F63/F16 -> 0.16468013 | G64: =G63/G16 -> 0.16468013 | H64: =H63/H16 -> 0.16468013 | I64: =I63/I16 -> 0.0584 | ... N64: =N63/N16 -> 0.14936599

Sheet Control de cambios
A1: CONTROL DE CAMBIOS – CORRECCIONES A LA PLANTILLA ORIGINAL
A3: Hoja | B3: Celda / rango | C3: Fórmula original | D3: Fórmula corregida | E3: Motivo
A4: Flujo de Caja | B4: B13:KP13 | C4: =SUM(B4:B11) | D4: =B6+SUM(B7:B11) | E4: El FCL sumaba EBIT + impuestos + NOPAT (doble conteo). FCL = NOPAT + Depreciación − CAPEX − ΔCT − Pre-operativos + Valor residual.
A5: Flujo de Caja | B5: C15:KP15 | C5: =C13/POWER(1+(1+WACC)^(1/12)-1,1) | D5: =C13/(1+tasa_mensual)^(n) | E5: El exponente era siempre 1: no se descontaba por el mes del flujo. Ahora n = número de mes.
A6: Panel de Control | B6: B20 | C6: =Resumen!B6 | D6: =Resumen!B7 | E6: TIR mostraba la mensual (Resumen!B6); ahora la TIR anual efectiva.
A7: Panel de Control | B7: B21 | C7: =Resumen!B7 | D7: =Resumen!B8 | E7: Payback apuntaba a la TIR anual; ahora al período de recuperación.
A8: Panel de Control | B8: B22 | C8: =Resumen!B8 | D8: =Resumen!B9 | E8: ROI apuntaba a una celda vacía (B8); ahora a Resumen!B9.
A9: Resumen | B9: B6 | C9: =IRR('Flujo de Caja'!B13:BJ13) | D9: =IFERROR(IRR('Flujo de Caja'!B13:BJ13,-0.005),"n/d") | E9: IRR sin valor inicial falla (#NUM/#N/A) cuando el proyecto no recupera la inversión; se acota con IFERROR y semilla negativa.
A10: Resumen | B10: B7 | C10: =POWER(1+B6,12)-1 | D10: =IFERROR(POWER(1+B6,12)-1,"n/d") | E10: Protege la TIR anual contra errores de la mensual.
A11: Resumen | B11: B8 | C11: =IFERROR(MATCH(TRUE,'Flujo de Caja'!C14:BJ14>0,0),"-") | D11: =IFERROR(MATCH(TRUE,INDEX('Flujo de Caja'!C14:BJ14>0,0),0),"-") | E11: Fórmula matricial sin CSE: se envuelve en INDEX para que funcione sin Ctrl+Shift+Enter.
A12: Resumen | B12: B9 | C12: =(BJ14-(Supuestos!$B$4+Supuestos!$B$5+Supuestos!$B$6))/(Supuestos!$B$4+Supuestos!$B$5+Supuestos!$B$6) | D12: ='Flujo de Caja'!BJ14/(Supuestos!$B$4+Supuestos!$B$5+Supuestos!$B$6) | E12: BJ14 era una referencia a la hoja Resumen; el acumulado ya está neto de la inversión, no se resta de nuevo.
A13: Resumen | B13: B13 | C13: =AVERAGE('Estado de Resultados'!C18:BJ18) | D13: =AVERAGE('Estado de Resultados'!B18:BI18) | E13: El rango C:BJ estaba desfasado (Mes 1 está en la columna B del Estado de Resultados): se promediaban los meses 2–61.
A14: Resumen | B14: B14 | C14: =AVERAGE('Estado de Resultados'!C19:BJ19) | D14: =AVERAGE('Estado de Resultados'!B19:BI19) | E14: El rango C:BJ estaba desfasado (Mes 1 está en la columna B del Estado de Resultados): se promediaban los meses 2–61.
... A29: Escenarios | B29: A20 | C29: NOTA: Los escenarios Pesimista y Optimista requieren ajustar | D29: NOTA: Pesimista y Optimista se recalculan automáticamente en el software Amberes Intelligence | E29: El software simula cada escenario con su motor mensual validado.
